Workbook

Sheet Data
A1: Asset_ID | B1: Brand Type | C1: Content_Type | D1: Parent_ID | E1: Draft URL/Link | F1: Published URL/Link | G1: Author | H1: Syndication platform | I1: Headline | J1: Week # | K1: Week Of | L1: Creation Date Month | M1: Pub Date Month | N1: Created Date | O1: Publication Date | P1: Vertical | Q1: Word Count | R1: Primary Keywords | S1: Meta Description | T1: Personas (Target Audience) | U1: Draft Doc | V1: Peer Reviewer | W1: UPDATE? | X1: Test category? Yes | Y1: Reuters photo Use? Yes | Z1: Reuters Link Used? Yes | AA1: story_id | AB1: total_pvs | AC1: search_pvs | AD1: social_pvs | AE1: direct_pvs | AF1: applenews_pvs | AG1: smartnews_pvs | AH1: newsbreak_pvs | AI1: subscriber_pvs | AJ1: cluster_id | AK1: cluster_total_pvs | AL1: article_vs_co.median | AM1: cluster_vs_co.median | AN1: cluster_avg_sim_desc | AO1: topic
A2: LS-P-002 | B2: Life & Style | C2: Parent-P | E2: https://www.lifeandstylemag.com/wp-admin/post.php?post=736061&action=edit | F2: https://www.lifeandstylemag.com/posts/singles-inferno-couples-who-stayed-together-after-the-show/ | G2: Hanna Wickes | I2: ‘Single’s Inferno’: Which Couples Are Still Together From the Reality Dating Show | J2: =VLOOKUP(K2,'Weeks 2026'!A:B,2,false) -> 5 | K2: 46054 | L2: =TEXT(N2,"mmmm") -> January | M2: =TEXT(O2,"mmmm") -> February | N2: 46051 | O2: 46055 | P2: Discover | Q2: 1143 | R2: single's inferno, dating, reality show | S2: From Season 1 to Season 4, we break down what really happened to every ‘Single’s Inferno’ couple — and why none of them lasted | T2: Netflix Viewers, K-pop fans | U2: https://docs.google.com/document/d/1-l0n2VXtfqeEmmeDl1p8rdDOAkkJIEjMHG__qsNFwXs/edit?tab=t.0 | V2: Sara V | AB2: 20436 | AC2: 18750 | AD2: 19 | AE2: 1518 | AF2: 0 | AG2: 0 | AH2: 0 | AI2: 36 | AJ2: LS-P-002 | AK2: 20436 | AO2: Reality TV
A3: LS-P-006-MMC-C02 | B3: Mod Moms Club | C3: Child-C | D3: LS-P-006 | E3: https://modmomsclubstg.wpenginepowered.com/wp-admin/post.php?post=337048&action=edit | F3: https://modmomsclubstg.wpenginepowered.com/wp-admin/post.php?post=337048&action=edit | G3: Hanna Wickes | I3: Love on the Beach, Heartbreak in Reality: Why No ‘Single’s Inferno’ Couple Has Survived | J3: =VLOOKUP(K3,'Weeks 2026'!A:B,2,false) -> 5 | K3: 46054 | L3: =TEXT(N3,"mmmm") -> February | M3: =TEXT(O3,"mmmm") -> February | N3: 46055 | O3: 46055 | P3: Discover | Q3: 1024 | R3: single's inferno, dating, reality show | S3: After four seasons of Netflix’s ‘Single’s Inferno,’ no couple is still together. Here’s why every relationship ended after the cameras stopped rolling. | T3: Netflix Viewers, genral audience | U3: https://docs.google.com/document/d/1-l0n2VXtfqeEmmeDl1p8rdDOAkkJIEjMHG__qsNFwXs/edit?tab=t.0 | V3: Sara V
A4: LS-P-008 | B4: Life & Style | C4: Parent-P | E4: https://www.lifeandstylemag.com/wp-admin/post.php?post=736139&action=edit | F4: https://www.lifeandstylemag.com/posts/bindi-irwins-daughter-has-the-sweetest-bond-with-a-baby-echidna/ | G4: Hanna Wickes | I4: Bindi Sue Irwin Shares Adorable Video of Her Daughter and the Newest Member of the Australian Zoo | J4: =VLOOKUP(K4,'Weeks 2026'!A:B,2,false) -> 5 | K4: 46054 | L4: =TEXT(N4,"mmmm") -> February | M4: =TEXT(O4,"mmmm") -> February | N4: 46055 | O4: 46055 | P4: Discover | Q4: 681 | R4: bindi irwin, daughter, zoo | S4: Bindi Irwin shared a heart-melting video of her daughter Grace bonding with a baby echidna at Australia Zoo — and fans can’t get enough. | T4: General Audience | U4: https://docs.google.com/document/d/1w8GKIGqfty9-xPc0yHEp_au_PtGAS8u8dGVawzeBrmQ/edit?usp=sharing | V4: Ryan B | AB4: 287 | AC4: 61 | AD4: 10 | AE4: 175 | AF4: 0 | AG4: 0 | AH4: 0 | AI4: 3 | AJ4: LS-P-008 | AK4: 287 | AO4: Pets
A5: LS-P-008-MMC-C02 | B5: Mod Moms Club | C5: Child-C | D5: LS-P-008 | E5: https://modmomsclubstg.wpenginepowered.com/wp-admin/post.php?post=337038&action=edit | F5: https://modmomsclubstg.wpenginepowered.com/parenting/bindi-irwins-daughter-is-friends-with-echidna/ | G5: Hanna Wickes | I5: Bindi Irwin’s Daughter Is Best Friends With an Echidna — This Video Will Make Every ’90s Kid Smile | J5: =VLOOKUP(K5,'Weeks 2026'!A:B,2,false) -> 5 | K5: 46054 | L5: =TEXT(N5,"mmmm") -> February | M5: =TEXT(O5,"mmmm") -> February | N5: 46055 | O5: 46055 | P5: Discover | Q5: 829 | R5: bindi irwin, daughter, zoo | S5: If you grew up watching Steve Irwin, this sweet video of Bindi Irwin’s daughter and an echidna will hit you right in the feels. | T5: Early 2000s Nostalgia | U5: https://docs.google.com/document/d/1w8GKIGqfty9-xPc0yHEp_au_PtGAS8u8dGVawzeBrmQ/edit?usp=sharing | V5: Ryan B
A6: MMC-P-010 | B6: Mod Moms Club | C6: Parent-P | E6: https://modmomsclubstg.wpenginepowered.com/wp-admin/post.php?post=337001&action=edit | F6: https://modmomsclub.com/lifestyle-entertainment/celebrity/khaby-lame-new-deal-ai-digital-twin/ | G6: Ryan Brennan | I6: Khaby Lame’s $975 Million Deal Signals a New Era: When Your Digital Twin Becomes the Product | L6: =TEXT(N6,"mmmm") -> January | N6: 46050 | P6: Discover | Q6: 842 | R6: khaby lame, khaby lame deal, rich sparkle | S6: Khaby Lame sold his company in a $975 million deal that licenses his face and voice for AI. Here’s what his AI digital twin means for the creator economy. | T6: Aspiring Content Creator/Side Hustler | U6: https://docs.google.com/document/d/1upYTG3nqmQNb5xeIHAG60DvSNC9h0DmGfqz2SQTo87A/edit?usp=sharing | AJ6: MMC-P-010 | AK6: 532
A7: MMC-P-010-LS-C02 | B7: Life & Style | C7: Child-C | D7: MMC-P-010 | E7: https://www.lifeandstylemag.com/wp-admin/post.php?post=736114&action=edit | F7: https://www.lifeandstylemag.com/posts/khaby-lame-sells-company-authorizes-use-of-ai-digital-twin/ | G7: Ryan Brennan | I7: From Factory Worker to $975 Million: How Khaby Lame Built a Social Media Empire You Can Learn From | L7: =TEXT(N7,"mmmm") -> January | N7: 46050 | P7: Discover | Q7: 1134 | R7: khaby lame, khaby lame deal, rich sparkle | S7: Khaby Lame sold his company in a $975 million deal that licenses his face and voice for AI. Here’s what his AI digital twin means for the creator economy. | T7: Tech-Curious Professional/AI Watcher | U7: https://docs.google.com/document/d/1upYTG3nqmQNb5xeIHAG60DvSNC9h0DmGfqz2SQTo87A/edit?usp=sharing | AB7: 532 | AC7: 293 | AD7: 9 | AE7: 210 | AF7: 0 | AG7: 0 | AH7: 0 | AI7: 0 | AO7: Business
A8: MMC-P-012 | B8: Mod Moms Club | C8: Parent-P | E8: https://modmomsclubstg.wpenginepowered.com/wp-admin/post.php?post=337004&action=edit | F8: https://modmomsclub.com/lifestyle-entertainment/celebrity/selma-blair-ms-diagnosis-update-return-acting/ | G8: Ryan Brennan | I8: Selma Blair’s Return to Acting Offers a Masterclass in Redefining What’s Possible After Chronic Illness | L8: =TEXT(N8,"mmmm") -> January | N8: 46051 | P8: Discover | Q8: 898 | R8: selma blair, selma blair ms, multiple sclerosis | S8: Selma Blair opens up about being relapse-free from multiple sclerosis (MS) and shares hope amid her return to acting after thinking her career was finished. | T8: Pop Culture Nostalgic | U8: https://docs.google.com/document/d/1CGpHMESQJ47oruN2KknlA1cy0KBcdpH8grEcMj7YGbI/edit?usp=sharing | AJ8: MMC-P-012
A9: MMC-P-012-LS-C02 | B9: Life & Style | C9: Child-C | D9: MMC-P-012 | E9: https://www.lifeandstylemag.com/wp-admin/post.php?post=736118&action=edit | F9: https://www.lifeandstylemag.com/posts/selma-blair-details-return-to-acting-after-thinking-career-was-done/ | G9: Ryan Brennan | I9: Selma Blair Is Back: Beloved ’90s Star Returns to Acting After Thinking She’d Never Work Again | L9: =TEXT(N9,"mmmm") -> January | N9: 46051 | P9: Discover | Q9: 1096 | R9: selma blair, selma blair ms, multiple sclerosis | S9: Selma Blair opens up about being relapse-free from multiple sclerosis (MS) and shares hope amid her return to acting after thinking her career was finished. | T9: Trend Hunter B2C | U9: https://docs.google.com/document/d/1CGpHMESQJ47oruN2KknlA1cy0KBcdpH8grEcMj7YGbI/edit?usp=sharing
A10: MMC-P-014 | B10: Mod Moms Club | C10: Parent-P | E10: https://modmomsclubstg.wpenginepowered.com/wp-admin/post.php?post=337007&action=edit | F10: https://modmomsclub.com/lifestyle-entertainment/celebrity/jessie-james-decker-scary-nashville-ice-storm/ | G10: Ryan Brennan | I10: Jessie James Decker’s Backyard Turns Dangerous Amid Nashville’s Record-Breaking Ice Storm | L10: =TEXT(N10,"mmmm") -> January | N10: 46051 | P10: Discover | Q10: 1221 | R10: jessie james decker, exploding trees, nashville ice storm | S10: Nashville’s ice storm has gone viral with "exploding trees," widespread power outages and celebrities like Jessie James Decker sharing footage of the damage. | T10: General Audience | U10: https://docs.google.com/document/d/1Lhss9qyZCKsWvEbmgPRx47-25pxOJa4ZFYeSqESpQXU/edit?tab=t.0 | V10: Sara V | AJ10: MMC-P-014 | AK10: 259
A11: MMC-P-014-LS-C02 | B11: Life & Style | C11: Child-C | D11: MMC-P-014 | E11: https://www.lifeandstylemag.com/wp-admin/post.php?post=736123&action=edit | F11: https://www.lifeandstylemag.com/posts/jessie-james-decker-shares-video-of-exploding-trees-amid-ice-storm/ | G11: Ryan Brennan | I11: Jessie James Decker’s Terrifying Ice Storm Video Has Nashville Celebrities Sharing Their Own Footage | L11: =TEXT(N11,"mmmm") -> January | N11: 46051 | P11: Discover | Q11: 1217 | R11: jessie james decker, exploding trees, nashville ice storm | S11: Nashville’s ice storm has gone viral with "exploding trees," widespread power outages and celebrities like Jessie James Decker sharing footage of the damage. | T11: Trend Hunter B2C | U11: https://docs.google.com/document/d/1Lhss9qyZCKsWvEbmgPRx47-25pxOJa4ZFYeSqESpQXU/edit?tab=t.0 | V11: Sara V | AB11: 259 | AC11: 116 | AD11: 10 | AE11: 83 | AF11: 0 | AG11: 0 | AH11: 0 | AI11: 3 | AO11: Weather
A12: MMC-P-016 | B12: Mod Moms Club | C12: Parent-P | E12: https://modmomsclubstg.wpenginepowered.com/wp-admin/post.php?post=337016&action=edit | F12: https://modmomsclub.com/lifestyle-entertainment/celebrity/jenna-bush-hager-declassifies-secret-service-alias/ | G12: Ryan Brennan | I12: Jenna Bush Hager Reveals the Secret Identity She Used as a Teenager in the White House | L12: =TEXT(N12,"mmmm") -> January | N12: 46052 | P12: Discover | Q12: 662 | R12: jenna bush hager, secret service code names, holly crawford | S12: Jenna Bush Hager reveals the fake name the Secret Service gave her as an 18-year-old — and it turns out she wasn’t the only one running around with that name! | T12: Morning Show Enthusiast | U12: https://docs.google.com/document/d/1q_vx0VWhpoIj1rHTcX8wSlt3XvrOcB994dxHfat4P4A/edit?tab=t.0 | V12: Sara V | AJ12: MMC-P-016 | AK12: 263
A13: MMC-P-016-LS-C02 | B13: Life & Style | C13: Child-C | D13: MMC-P-016 | E13: https://www.lifeandstylemag.com/wp-admin/post.php?post=736079&action=edit | F13: https://www.lifeandstylemag.com/posts/title-page-sep-sitename-jenna-bush-hagers-secret-service-name-was-very-on-brand/ | G13: Ryan Brennan | I13: Remember When Jenna Bush Hager Finally Revealed Her Secret Service Alias — Fans Still Can’t Get Enough | L13: =TEXT(N13,"mmmm") -> January | N13: 46052 | P13: Discover | Q13: 699 | R13: jenna bush hager, secret service code names, holly crawford | S13: Jenna Bush Hager reveals the fake name the Secret Service gave her as an 18-year-old — and it turns out she wasn’t the only one running around with that name! | T13: General Audience | U13: https://docs.google.com/document/d/1q_vx0VWhpoIj1rHTcX8wSlt3XvrOcB994dxHfat4P4A/edit?tab=t.0 | V13: Sara V | AB13: 263 | AC13: 73 | AD13: 39 | AE13: 119 | AF13: 0 | AG13: 0 | AH13: 0 | AI13: 2 | AO13: Celebrity Families
A14: MMC-P-018 | B14: Mod Moms Club | C14: Parent-P | E14: https://modmomsclubstg.wpenginepowered.com/wp-admin/post.php?post=337022&action=edit | F14: https://modmomsclub.com/lifestyle-entertainment/celebrity/pete-davidson-vhs-collection-rich/ | G14: Ryan Brennan | I14: Pete Davidson’s Billion-Dollar Idea Is the Most Relatable Millennial Collector Fail Ever | L14: =TEXT(N14,"mmmm") -> January | N14: 46052 | P14: Discover | Q14: 564 | R14: pete davidson, vhs tapes, vhs collection | S14: Pete Davidson finally shares the fate of his collection of 10,000 sealed VHS tapes — and the nostalgia-fueled gamble was nowhere close to paying off. | T14: Nostalgic Millennial Collector | U14: https://docs.google.com/document/d/1aD0AklCcuoIzLIofcU0dF_JhDTDii7LBrP9FcEoOdNM/edit?tab=t.0 | V14: Sara V | AJ14: MMC-P-018 | AK14: 153
A15: MMC-P-018-LS-C02 | B15: Life & Style | C15: Child-C | D15: MMC-P-018 | E15: https://www.lifeandstylemag.com/wp-admin/post.php?post=736095&action=edit | F15: https://www.lifeandstylemag.com/posts/title-page-sep-sitename-pete-davidsons-vhs-collection-has-entered-its-flop-era/ | G15: Ryan Brennan | I15: Pete Davidson’s Billion-Dollar VHS Gamble: The Hilarious Update Fans Have Been Waiting For | L15: =TEXT(N15,"mmmm") -> January | N15: 46052 | P15: Discover | Q15: 710 | R15: pete davidson, vhs tapes, vhs collection | S15: Pete Davidson finally shares the fate of his collection of 10,000 sealed VHS tapes — and the nostalgia-fueled gamble was nowhere close to paying off. | T15: Pop Culture Enthusiast | U15: https://docs.google.com/document/d/1aD0AklCcuoIzLIofcU0dF_JhDTDii7LBrP9FcEoOdNM/edit?tab=t.0 | V15: Sara V | AB15: 153 | AC15: 34 | AD15: 14 | AE15: 89 | AF15: 0 | AG15: 0 | AH15: 0 | AI15: 0 | AO15: Television
A16: MMC-P-020 | B16: Mod Moms Club | C16: Parent-P | E16: https://modmomsclubstg.wpenginepowered.com/wp-admin/post.php?post=337027&action=edit | F16: https://modmomsclub.com/lifestyle-entertainment/celebrity/ava-raine-stepping-away-wwe-nxt/ | G16: Ryan Brennan | I16: ‘The Rock’s Daughter Ava Raine Says She’s Stepping Away From WWE & NXT | L16: =TEXT(N16,"mmmm") -> January | N16: 46052 | P16: Discover | Q16: 703 | R16: ava raine, simone johnson, dwayne johnson daughter, the rock daughter | S16: Ava Raine, daughter of Dwayne “The Rock” Johnson, is leaving the WWE at 24 and walking away from a historic family legacy to begin a new chapter of her life. | T16: Pop Culture-Following Parent | U16: https://docs.google.com/document/d/1qSLLwTXDpI7x_-oYuMmXgOH3uDNQo8STxhOUdjULtvw/edit?usp=sharing | V16: Sara V | AJ16: MMC-P-020 | AK16: 620
A17: MMC-P-020-LS-C02 | B17: Life & Style | C17: Child-C | D17: MMC-P-020 | E17: https://www.lifeandstylemag.com/wp-admin/post.php?post=736106&action=edit | F17: https://www.lifeandstylemag.com/posts/ava-raine-announces-surprise-exit-from-wwe-and-nxt/ | G17: Ryan Brennan | I17: Dwayne Johnson’s Daughter Departs NXT After Historic Run as WWE’s Youngest General Manager | L17: =TEXT(N17,"mmmm") -> January | N17: 46052 | P17: Discover | Q17: 641 | R17: ava raine, simone johnson, dwayne johnson daughter, the rock daughter | S17: Dwayne Johnson’s daughter, Ava Raine, says she's leaving NXT after making history as WWE’s youngest General Manager. | T17: Wrestling Fan & Sports Entertainment Enthusiast | U17: https://docs.google.com/document/d/1qSLLwTXDpI7x_-oYuMmXgOH3uDNQo8STxhOUdjULtvw/edit?usp=sharing | V17: Sara V | AB17: 620 | AC17: 382 | AD17: 17 | AE17: 180 | AF17: 0 | AG17: 0 | AH17: 0 | AI17: 1 | AO17: Sports
A18: LS-P-022 | B18: Life & Style | C18: Parent-P | E18: https://www.lifeandstylemag.com/?p=736143&preview=true | F18: https://www.lifeandstylemag.com/posts/essentials-to-pack-for-a-flight-that-feels-first-class/ | G18: Lauren Schuster | I18: Skip the Upgrade Fee: How to Create Your Own First-Class Experience for the Price of Economy | J18: =VLOOKUP(K18,'Weeks 2026'!A:B,2,false) -> 5 | K18: 46054 | L18: =TEXT(N18,"mmmm") -> February | M18: =TEXT(O18,"mmmm") -> February | N18: 46055 | O18: 46055 | P18: Experiences | Q18: 904 | R18: travel, flights, Vacation, | S18: Upgrade your travel experience with carry-on essentials that bring comfort, style, and first-class vibes to every flight, no upgrade required | T18: Budget-Conscious Frequent Traveler | U18: https://docs.google.com/document/d/1MwM6muzt1RXKmI4CpjT05uBhBhp_LLS8Dd8SXjI79kM/edit?tab=t.0 | V18: Lauren JG | AB18: 78 | AC18: 10 | AD18: 9 | AE18: 50 | AF18: 0 | AG18: 0 | AH18: 0 | AI18: 0 | AJ18: LS-P-022 | AK18: 78
A19: LS-P-022-MMC-C02 | B19: Mod Moms Club | C19: Child-C | D19: LS-P-022 | E19: https://modmomsclubstg.wpenginepowered.com/wp-admin/post.php?post=337049&action=edit | F19: https://modmomsclub.com/lifestyle-entertainment/your-calm-flight-checklist-simple-carry-on-essentials-that-help-anxious-flyers-feel-in-control/ | G19: Lauren Schuster | I19: Your Calm-Flight Checklist: Simple Carry-On Essentials That Help Anxious Flyers Feel in Control | J19: =VLOOKUP(K19,'Weeks 2026'!A:B,2,false) -> 5 | K19: 46054 | L19: =TEXT(N19,"mmmm") -> February | M19: =TEXT(O19,"mmmm") -> February | N19: 46055 | O19: 46055 | P19: Experiences | Q19: 1105 | R19: airplane, flight, travel, traveling | S19: Ease flight anxiety with luxurious carry-on essentials designed for comfort and calm, so every trip feels more relaxed from takeoff to landing | T19: First-Time or Anxious Flyer | U19: https://docs.google.com/document/d/1MwM6muzt1RXKmI4CpjT05uBhBhp_LLS8Dd8SXjI79kM/edit?tab=t.0 | V19: Lauren JG
A20: LS-P-024 | B20: Life & Style | C20: Parent-P | E20: https://www.lifeandstylemag.com/wp-admin/post.php?post=736100&action=edit | F20: https://www.lifeandstylemag.com/posts/how-to-plan-your-spring-garden-this-winter/ | G20: Lauren J-G | I20: Here’s How to Plan Your Spring Garden This Winter Without the Overwhelm | J20: =VLOOKUP(K20,'Weeks 2026'!A:B,2,false) -> 5 | K20: 46054 | L20: =TEXT(N20,"mmmm") -> February | M20: =TEXT(O20,"mmmm") -> February | N20: 46055 | O20: 46055 | P20: Everyday Life | Q20: 1596 | R20: gardening, home, lifestyle, planning garden | S20: Don't wait to start working on your garden in the winter months. Here's a step-by-step guide to help you have a blooming garden come spring | T20: Trend Hunter | U20: https://docs.google.com/document/d/1qslDaR69eW929cyYIWoyQjBc_OjEXyWwy3-vAJT_dDQ/edit?tab=t.0 | V20: Lauren S | AB20: 121 | AC20: 3 | AD20: 3 | AE20: 103 | AF20: 0 | AG20: 0 | AH20: 0 | AI20: 0 | AJ20: LS-P-024 | AK20: 121 | AO20: Home & Garden
A21: LS-P-024-MMC-C02 | B21: Mod Moms Club | C21: Child-C | D21: LS-P-024 | E21: https://modmomsclubstg.wpenginepowered.com/wp-admin/post.php?post=337026&action=edit | F21: https://modmomsclubstg.wpenginepowered.com/parenting/your-familys-winter-guide-to-planning-a-spring-garden-together/ | G21: Lauren J-G | I21: Your Family’s Winter Guide to Planning a Spring Garden Together | J21: =VLOOKUP(K21,'Weeks 2026'!A:B,2,false) -> 5 | K21: 46054 | L21: =TEXT(N21,"mmmm") -> February | M21: =TEXT(O21,"mmmm") -> February | N21: 46055 | O21: 46055 | P21: Everyday Life | Q21: 1293 | R21: garden, spring gardening, winter gardening, home tips | S21: Plan your winter garden as a family and set the stage for a thriving spring. Easy tips to prep, dream, and grow together. | T21: Overwhelmed Working Parent | U21: https://docs.google.com/document/d/1qslDaR69eW929cyYIWoyQjBc_OjEXyWwy3-vAJT_dDQ/edit?tab=t.0 | V21: Lauren S
A22: LS-P-026 | B22: Life & Style | C22: Parent-P | E22: https://www.lifeandstylemag.com/wp-admin/post.php?post=736085&action=edit | F22: https://www.lifeandstylemag.com/posts/your-ultimate-guide-for-spring-cleaning/ | G22: Lauren J-G | I22: Your No-Stress Spring Cleaning Playbook: A Room-by-Room Guide to a Fresher Home | J22: =VLOOKUP(K22,'Weeks 2026'!A:B,2,false) -> 5 | K22: 46054 | L22: =TEXT(N22,"mmmm") -> February | M22: =TEXT(O22,"mmmm") -> February | N22: 46055 | O22: 46055 | P22: Everyday Life | Q22: 1104 | R22: cleaning, cleaning hacks, home, lifestyle, spring cleaning | S22: Spring is almost here, which means it's time to get ready to refresh our homes after winter. Here's the ultimate guide for spring cleaning | T22: Trend Hunter | U22: https://docs.google.com/document/d/16znh8k3LtycwIYGUuRLb6B1kvk4IX-3smOKfUTLbVm0/edit?tab=t.0 | V22: Lauren S | AB22: 138 | AC22: 27 | AD22: 4 | AE22: 91 | AF22: 0 | AG22: 0 | AH22: 0 | AI22: 1 | AJ22: LS-P-026 | AK22: 138 | AO22: Home Improvement
A23: LS-P-026-MMC-C02 | B23: Mod Moms Club | C23: Child-C | D23: LS-P-026 | E23: https://modmomsclubstg.wpenginepowered.com/wp-admin/post.php?post=337020&action=edit | F23: https://modmomsclubstg.wpenginepowered.com/parenting/spring-cleaning-made-simple-a-busy-parents-guide-to-a-healthier-home-without-losing-your-weekend/ | G23: Lauren J-G | I23: Spring Cleaning Made Simple: A Busy Parent’s Guide to a Healthier Home Without Losing Your Weekend | J23: =VLOOKUP(K23,'Weeks 2026'!A:B,2,false) -> 5 | K23: 46054 | L23: =TEXT(N23,"mmmm") -> February | M23: =TEXT(O23,"mmmm") -> February | N23: 46055 | O23: 46056 | P23: Everyday Life | Q23: 1151 | R23: spring cleaning, home tips, cleaning with kids | S23: Overwhelmed by spring cleaning with kids? This step-by-step guide helps parents declutter, organize, and refresh their home without the stress. | T23: Overwhelmed Working Parent | U23: https://docs.google.com/document/d/16znh8k3LtycwIYGUuRLb6B1kvk4IX-3smOKfUTLbVm0/edit?tab=t.0 | V23: Lauren S
A24: LS-P-028 | B24: Life & Style | C24: Parent-P | E24: https://www.lifeandstylemag.com/wp-admin/post.php?post=736146&action=edit | F24: https://www.lifeandstylemag.com/posts/what-is-an-ebug-tiktok-creator-answers-everyones-questions/ | G24: Ryan Brennan | I24: What Is an EBUG? The NHL’s Most Unusual Role, Explained by a Fan Favorite | L24: =TEXT(N24,"mmmm") -> February | N24: 46055 | P24: Discover | Q24: 1463 | R24: emergency backup goalie, ebug, timm chiusano | T24: Casual Hockey Fan | U24: https://docs.google.com/document/d/1HqZimoVIvjs4VnnYTVlFpuL1d0WfYfpgPuv6KtrROBI/edit?usp=sharing | V24: Hanna W | AB24: 115 | AC24: 39 | AD24: 6 | AE24: 56 | AF24: 0 | AG24: 0 | AH24: 0 | AI24: 0 | AJ24: LS-P-028 | AK24: 115 | AO24: Sports
A25: LS-P-028-MMC-C02 | B25: Mod Moms Club | C25: Child-C | D25: LS-P-028 | E25: https://modmomsclubstg.wpenginepowered.com/wp-admin/post.php?post=337042&action=edit | F25: https://modmomsclub.com/lifestyle-entertainment/celebrity/what-is-an-ebug-emergency-backup-goalie/ | G25: Ryan Brennan | I25: What Every Hockey Parent Should Know About the NHL’s Emergency Backup Goalie Role | L25: =TEXT(N25,"mmmm") -> February | N25: 46055 | P25: Discover | Q25: 1255 | R25: emergency backup goalie, ebug, timm chiusano | U25: https://docs.google.com/document/d/1HqZimoVIvjs4VnnYTVlFpuL1d0WfYfpgPuv6KtrROBI/edit?usp=sharing | V25: Hanna W
A26: LS-P-030 | B26: Life & Style | C26: Parent-P | E26: https://www.lifeandstylemag.com/posts/alex-warrens-grammys-performance-went-wrong-heres-why/ | F26: https://www.lifeandstylemag.com/posts/alex-warrens-grammys-performance-went-wrong-heres-why/ | G26: Hanna Wickes | I26: Alex Warren’s Grammy Debut Hit a Technical Snag—Here’s How He Handled It Like a Pro | J26: =VLOOKUP(K26,'Weeks 2026'!A:B,2,false) -> 5 | K26: 46054 | L26: =TEXT(N26,"mmmm") -> February | M26: =TEXT(O26,"mmmm") -> February | N26: 46055 | O26: 46055 | P26: Discover | Q26: 716 | R26: alex warren, grammys, music, celebrity news | S26: Alex Warren experienced every performer’s nightmare when his in-ear monitors malfunctioned during the 2026 Grammys. | T26: General Audience | U26: https://docs.google.com/document/d/1BJs2J2Kw7AMmTUDhGjgKxMeqbS5rjTIVDHIe64MwCTU/edit?tab=t.0 | V26: Ryan B | AB26: 1040 | AC26: 857 | AD26: 8 | AE26: 149 | AF26: 0 | AG26: 0 | AH26: 0 | AI26: 7 | AJ26: LS-P-030 | AK26: 1040 | AO26: Events and Attractions
A27: LS-P-030-MMC-C02 | B27: Mod Moms Club | C27: Child-C | D27: LS-P-030 | E27: https://modmomsclubstg.wpenginepowered.com/lifestyle-entertainment/celebrity/alex-warrens-grammy-debut/ | F27: https://modmomsclub.com/lifestyle-entertainment/celebrity/alex-warrens-grammy-debut/ | G27: Hanna Wickes | I27: Alex Warren’s Grammys Debut Hit a Snag—But His Wife Kouvr’s Response Is the Real Story | J27: =VLOOKUP(K27,'Weeks 2026'!A:B,2,false) -> 5 | K27: 46054 | L27: =TEXT(N27,"mmmm") -> February | M27: =TEXT(O27,"mmmm") -> February | N27: 46055 | O27: 46055 | P27: Discover | Q27: 802 | R27: alex warren, grammys, music, celebrity news | S27: Alex Warren’s Grammy performance didn’t go as planned—but his response, and his wife’s support, won over fans and parents alike. | T27: Millennial Parent Following Pop Culture | U27: https://docs.google.com/document/d/1BJs2J2Kw7AMmTUDhGjgKxMeqbS5rjTIVDHIe64MwCTU/edit?tab=t.0 | V27: Ryan B
A28: LS-P-032 | B28: Life & Style | C28: Parent-P | E28: https://www.lifeandstylemag.com/wp-admin/post.php?post=736180&action=edit | F28: https://www.lifeandstylemag.com/posts/the-hidden-tribute-inside-kelsea-ballerinis-grammy-gown/ | G28: Ryan Brennan | I28: Kelsea Ballerini’s Grammy Gown Held a Heartbreaking Tribute That Fans Couldn’t See | J28: =VLOOKUP(K28,'Weeks 2026'!A:B,2,false) -> 5 | K28: 46054 | L28: =TEXT(N28,"mmmm") -> February | M28: =TEXT(O28,"mmmm") -> February | N28: 46055.594 | O28: 46055.594 | P28: Discover | Q28: 1042 | R28: kelsea ballerini, kelsea ballerini grammy | S28: Fans missed a powerful detail in Kelsea Ballerini’s Grammy gown—a hidden tribute honoring her late dog Dibs stitched close to her heart. | T28: Country Music Fan & Concert-Goer | U28: https://docs.google.com/document/d/16oks1xPwhSexKC8RplhoJH-vFami3dqnr_9NouWok3g/edit?tab=t.0 | V28: Hanna W | AB28: 308 | AC28: 127 | AD28: 10 | AE28: 110 | AF28: 0 | AG28: 0 | AH28: 0 | AI28: 0 | AJ28: LS-P-032 | AK28: 308 | AO28: Country Music
A29: LS-P-032-MMC-C02 | B29: Mod Moms Club | C29: Child-C | D29: LS-P-032 | E29: https://modmomsclubstg.wpenginepowered.com/wp-admin/post.php?post=337059&action=edit | F29: https://modmomsclub.com/lifestyle-entertainment/celebrity/kelsea-ballerini-grammy-dress-dog-tribute/ | G29: Ryan Brennan | I29: Kelsea Ballerini’s Hidden Grammy Dress Tribute Honors the ‘Greatest Gift’ of Her Life | J29: =VLOOKUP(K29,'Weeks 2026'!A:B,2,false) -> 5 | K29: 46054 | L29: =TEXT(N29,"mmmm") -> February | M29: =TEXT(O29,"mmmm") -> February | N29: 46055.594 | O29: 46055.594 | P29: Discover | Q29: 1057 | R29: kelsea ballerini, kelsea ballerini grammy | S29: Kelsea Ballerini’s Grammy dress held a secret tribute to her late dog Dibs, honoring the “greatest gift” of her life on one of music's biggest nights. | T29: Pet Owner Experiencing or Anticipating Loss | U29: https://docs.google.com/document/d/16oks1xPwhSexKC8RplhoJH-vFami3dqnr_9NouWok3g/edit?tab=t.0 | V29: Hanna W
A30: LS-P-034 | B30: Life & Style | C30: Parent-P | E30: https://modmomsclubstg.wpenginepowered.com/wp-admin/post.php?post=337105&action=edit | F30: https://www.lifeandstylemag.com/posts/cant-miss-italian-restaurants-in-nyc-for-every-price-range/ | G30: Lauren Schuster | I30: The Visiting Food Tourist’s Ultimate Guide to Italian Dining in NYC: Where to Eat When Every Meal Counts | J30: =VLOOKUP(K30,'Weeks 2026'!A:B,2,false) -> 5 | K30: 46054 | L30: =TEXT(N30,"mmmm") -> February | M30: February | N30: 46055 | O30: 46057 | P30: Experiences | Q30: 1029 | R30: dining, italian, new york city, restaurants | S30: From casual pizza slices to Michelin-level fine dining, you won’t want to miss these Italian restaurant in NYC | T30: Visiting Food Tourist | U30: https://docs.google.com/document/d/1Wn047ljvzBZ01CKY9M4PwKXGB2nWSG8GBwKr5fsr-Y4/edit?tab=t.0 | V30: Lauren JG | AB30: 209 | AC30: 18 | AD30: 5 | AE30: 166 | AF30: 0 | AG30: 0 | AH30: 0 | AI30: 10 | AJ30: LS-P-034 | AK30: 209 | AO30: Food & Drink
A31: LS-P-034-MMC-C02 | B31: Mod Moms Club | C31: Child-C | D31: LS-P-034 | E31: https://www.lifeandstylemag.com/wp-admin/post.php?post=736255&action=edit | F31: https://modmomsclubstg.wpenginepowered.com/lifestyle-entertainment/food/your-ultimate-guide-to-italian-dining-in-new-york-city-cheap-eats-to-michelin-spots/ | G31: Lauren Schuster | I31: Your Ultimate Guide to Italian Dining in New York City: Cheap Eats to Michelin Stars | J31: =VLOOKUP(K31,'Weeks 2026'!A:B,2,false) -> 5 | K31: 46054 | L31: =TEXT(N31,"mmmm") -> February | M31: =TEXT(O31,"mmmm") -> February | N31: 46055 | O31: 46058 | P31: Experiences | Q31: 923 | R31: dining, italian, new york city, restaurants | S31: From casual pizza slices to Michelin-level fine dining, be sure to check out these Italian restaurants on your next trip to NYC | T31: General Audience | U31: https://docs.google.com/document/d/1Wn047ljvzBZ01CKY9M4PwKXGB2nWSG8GBwKr5fsr-Y4/edit?tab=t.0 | V31: Lauren JG
A32: MMC-P-036 | B32: Mod Moms Club | C32: Parent-P | E32: https://modmomsclubstg.wpenginepowered.com/wp-admin/post.php?post=337070&action=edit | F32: https://modmomsclubstg.wpenginepowered.com/lifestyle-entertainment/bob-ross-paintings-sold-public-broadcasting/ | G32: Ryan Brennan | I32: Bob Ross Paintings Just Sold for 8x Their Value — And the Proceeds Are Going to a Great Cause | J32: =VLOOKUP(K32,'Weeks 2026'!A:B,2,false) -> 5 | K32: 46054 | L32: =TEXT(N32,"mmmm") -> February | M32: =TEXT(O32,"mmmm") -> February | N32: 46055 | O32: 46056 | P32: Discover | Q32: 580 | R32: bob ross, bob ross paintings, the joy of painting | S32: Three Bob Ross paintings smashed auction estimates, selling for $1.2 million and highlighting how cultural nostalgia is reshaping the art market. | T32: Trend Hunter B2C | U32: https://docs.google.com/document/d/1PhjpJs-FfaOSm2eJsE1-PbiikztvCPSES6tG6JVUJd8/edit?usp=sharing | V32: Hanna W | AJ32: MMC-P-036 | AK32: 108
A33: MMC-P-036-LS-C02 | B33: Life & Style | C33: Child-C | D33: MMC-P-036 | E33: https://www.lifeandstylemag.com/wp-admin/post.php?post=736195&action=edit | F33: https://www.lifeandstylemag.com/posts/bob-ross-paintings-just-became-the-feel-good-story-of-the-year/ | G33: Ryan Brennan | I33: Three Bob Ross Paintings You Grew Up Watching Just Raised $1.2 Million for Public Broadcasting | J33: =VLOOKUP(K33,'Weeks 2026'!A:B,2,false) -> 5 | K33: 46054 | L33: =TEXT(N33,"mmmm") -> February | M33: =TEXT(O33,"mmmm") -> February | N33: 46055 | O33: 46056 | P33: Discover | Q33: 968 | R33: bob ross, bob ross paintings, the joy of painting | S33: Bob Ross paintings made on "The Joy of Painting" sold for $1.2M, nearly eight times estimates, with proceeds going back to PBS. | T33: Nostalgic Boomer Art Enthusiast | U33: https://docs.google.com/document/d/1PhjpJs-FfaOSm2eJsE1-PbiikztvCPSES6tG6JVUJd8/edit?usp=sharing | V33: Hanna W | AB33: 108 | AC33: 19 | AD33: 5 | AE33: 67 | AF33: 0 | AG33: 0 | AH33: 0 | AI33: 0 | AO33: Television
A34: LS-P-038 | B34: Life & Style | C34: Parent-P | E34: https://www.lifeandstylemag.com/wp-admin/post.php?post=736208&action=edit | F34: https://www.lifeandstylemag.com/posts/how-to-allergy-proof-your-home/ | G34: Lauren J-G | I34: Struggle With Allergies? Your Guide to Allergy Proofing Your Home | J34: =VLOOKUP(K34,'Weeks 2026'!A:B,2,false) -> 5 | K34: 46054 | L34: =TEXT(N34,"mmmm") -> February | M34: =TEXT(O34,"mmmm") -> February | N34: 46056 | O34: 46056 | P34: Everyday Life | Q34: 1352 | R34: cleaning, cleaning tips, cleaning hacks, lifestyle, home | S34: Indoor allergens like dust mites and mold can worsen allergy and asthma symptoms. Learn how to allergy-proof your home with cleaning tips | T34: General Audience | U34: https://docs.google.com/document/d/1NRWc9EIqVU_TBfLWPBRUGNBaM0mvry5MkjUQIYS745w/edit?tab=t.0 | V34: Lauren S | AB34: 69 | AC34: 12 | AD34: 7 | AE34: 43 | AF34: 0 | AG34: 0 | AH34: 0 | AI34: 0 | AJ34: LS-P-038 | AK34: 69 | AO34: Allergies
A35: LS-P-038-MMC-C02 | B35: Mod Moms Club | C35: Child-C | D35: LS-P-038 | E35: https://modmomsclubstg.wpenginepowered.com/wp-admin/post.php?post=337080&action=edit | F35: https://modmomsclubstg.wpenginepowered.com/parenting/a-parents-guide-to-allergy-proofing-your-home/ | G35: Lauren J-G | I35: A Parent’s Guide to Allergy-Proofing Your Home This Spring | J35: =VLOOKUP(K35,'Weeks 2026'!A:B,2,false) -> 5 | K35: 46054 | L35: =TEXT(N35,"mmmm") -> February | M35: =TEXT(O35,"mmmm") -> February | N35: 46056 | O35: 46056 | P35: Everyday Life | Q35: 1144 | R35: cleaning, cleaning tips, cleaning hacks, lifestyle, home | S35: Allergies or asthma acting up at home? These doctor-recommended cleaning tips help reduce dust, dander, and other indoor allergens year-round. | T35: Parent of a Child with Asthma or Allergies | U35: https://docs.google.com/document/d/1NRWc9EIqVU_TBfLWPBRUGNBaM0mvry5MkjUQIYS745w/edit?tab=t.0 | V35: Lauren S
A36: LS-P-040 | B36: Life & Style | C36: Parent-P | E36: https://www.lifeandstylemag.com/wp-admin/post.php?post=736220&action=edit | F36: https://www.lifeandstylemag.com/posts/this-dollar-tree-diy-jewelry-organizer-is-going-viral-on-tiktok/ | G36: Lauren J-G | I36: This Dollar Tree DIY Hack Is Taking Over TikTok — and It Looks Way More Expensive Than It Is | J36: =VLOOKUP(K36,'Weeks 2026'!A:B,2,false) -> 5 | K36: 46054 | L36: =TEXT(N36,"mmmm") -> February | M36: =TEXT(O36,"mmmm") -> February | N36: 46056 | O36: 46056 | P36: Everyday Life | Q36: 1020 | R36: diy hack. dollar. tree diy. home, lifestyle | S36: A Dollar Tree DIY project from a TikTok creator is going viral for turning cheap items into a stylish organizer anyone can make at home | T36: General Audience | U36: https://docs.google.com/document/d/1UUuGTqsvUARXN7b4qI9gd8K3F5Ak57w8Eu9iYhQI86c/edit?tab=t.0 | V36: Lauren S | AB36: 174 | AC36: 49 | AD36: 9 | AE36: 87 | AF36: 0 | AG36: 0 | AH36: 0 | AI36: 0 | AJ36: LS-P-040 | AK36: 174 | AO36: Home & Garden
A37: LS-P-040-MMC-C02 | B37: Mod Moms Club | C37: Child-C | D37: LS-P-040 | E37: https://modmomsclubstg.wpenginepowered.com/wp-admin/post.php?post=337093&action=edit | F37: https://modmomsclubstg.wpenginepowered.com/lifestyle-entertainment/turn-dollar-tree-finds-into-a-stunning-two-tier-tray/ | G37: Lauren J-G | I37: Turn Dollar Tree Finds Into a Stunning Two-Tier Tray | J37: =VLOOKUP(K37,'Weeks 2026'!A:B,2,false) -> 5 | K37: 46054 | L37: =TEXT(N37,"mmmm") -> February | M37: =TEXT(O37,"mmmm") -> February | N37: 46056 | O37: 46056 | P37: Everyday Life | Q37: 1045 | R37: diy hack. dollar. tree diy. home, lifestyle | S37: See this incredible Dollar Tree DIY project that is making the rounds on the internet. You can even do it yourself at home. | T37: CRAFTY EMPTY-NESTER ON FIXED INCOME | U37: https://docs.google.com/document/d/1UUuGTqsvUARXN7b4qI9gd8K3F5Ak57w8Eu9iYhQI86c/edit?tab=t.0 | V37: Lauren S
A38: LS-P-042 | B38: Life & Style | C38: Parent-P | E38: https://www.lifeandstylemag.com/wp-admin/post.php?post=736194&action=edit | F38: https://www.lifeandstylemag.com/posts/why-the-buffalo-bills-are-betting-on-the-nfls-youngest-head-coach/ | G38: Hanna Wickes | I38: Joe Brady Takes the Helm: What the Bills’ Bold Hire Means for Buffalo’s Championship Window | J38: =VLOOKUP(K38,'Weeks 2026'!A:B,2,false) -> 5 | K38: 46054 | L38: =TEXT(N38,"mmmm") -> February | M38: =TEXT(O38,"mmmm") -> February | N38: 46055 | O38: 46056 | P38: Discover | Q38: 970 | R38: buffalo bills, joe brady, head coach | S38: The Buffalo Bills have hired Joe Brady as their next head coach. Here’s why the move signals a major shift for the franchise. | T38: Trend Hunter B2C | U38: https://docs.google.com/document/d/16oks1xPwhSexKC8RplhoJH-vFami3dqnr_9NouWok3g/edit?tab=t.0 | V38: Ryan B | AB38: 309 | AC38: 223 | AD38: 1 | AE38: 75 | AF38: 0 | AG38: 0 | AH38: 0 | AI38: 1 | AJ38: LS-P-042 | AK38: 309 | AO38: Sports
A39: LS-P-042-MMC-C02 | B39: Mod Moms Club | C39: Child-C | D39: LS-P-042 | E39: https://modmomsclubstg.wpenginepowered.com/wp-admin/post.php?post=337069&action=edit | F39: https://modmomsclubstg.wpenginepowered.com/lifestyle-entertainment/meet-joe-brady-the-young-buffalo-bills-coach/ | G39: Hanna Wickes | I39: Joe Brady Named Buffalo Bills Head Coach: What to Know About the NFL’s Youngest Hire | J39: =VLOOKUP(K39,'Weeks 2026'!A:B,2,false) -> 5 | K39: 46054 | L39: =TEXT(N39,"mmmm") -> February | M39: =TEXT(O39,"mmmm") -> February | N39: 46055 | O39: 46056 | P39: Discover | Q39: 1202 | R39: buffalo bills, joe brady, head coach | S39: Joe Brady is officially the Buffalo Bills’ new head coach. Learn about his age, contract, coaching journey, and relationship with Josh Allen. | T39: General Audience | U39: https://docs.google.com/document/d/16oks1xPwhSexKC8RplhoJH-vFami3dqnr_9NouWok3g/edit?tab=t.0 | V39: Ryan B
A40: LS-P-044 | B40: Life & Style | C40: Parent-P | E40: https://www.lifeandstylemag.com/wp-admin/post.php?post=736218&action=edit | F40: https://www.lifeandstylemag.com/posts/little-miss-sunshine-cast-reflects-on-20-years-of-memories/ | G40: Ryan Brennan | I40: The Little Miss Sunshine Cast Reflects on a Movie That Made Dysfunction Feel Universal | J40: =VLOOKUP(K40,'Weeks 2026'!A:B,2,false) -> 5 | K40: 46054 | L40: =TEXT(N40,"mmmm") -> February | M40: =TEXT(O40,"mmmm") -> February | N40: 46056 | O40: 46056 | P40: Discover | Q40: 1331 | R40: little miss sunshine, little miss sunshine cast, abigail breslin | S40: Twenty years after its Sundance premiere, the Little Miss Sunshine cast reunites to honor the film’s Oscar legacy and remember Alan Arkin. | T40: Awards Season/Film Industry Follower | U40: https://docs.google.com/document/d/1IOMh178EdVVFGnoBUoZ10EcNgsQKusrT74i6IPO4jWQ/edit?usp=sharing | V40: Hanna W | AB40: 145 | AC40: 48 | AD40: 9 | AE40: 68 | AF40: 0 | AG40: 0 | AH40: 0 | AI40: 0 | AJ40: LS-P-044 | AK40: 145 | AO40: Movies
A41: LS-P-044-MMC-C02 | B41: Mod Moms Club | C41: Child-C | D41: LS-P-044 | E41: https://modmomsclubstg.wpenginepowered.com/wp-admin/post.php?post=337082&action=edit | F41: https://modmomsclubstg.wpenginepowered.com/lifestyle-entertainment/celebrity/little-miss-sunshine-reunion-20-years/ | G41: Ryan Brennan | I41: Inside the 'Little Miss Sunshine' Reunion Fans Didn’t Know They Needed | J41: =VLOOKUP(K41,'Weeks 2026'!A:B,2,false) -> 5 | K41: 46054 | L41: =TEXT(N41,"mmmm") -> February | M41: =TEXT(O41,"mmmm") -> February | N41: 46056 | O41: 46056 | P41: Discover | Q41: 1815 | R41: little miss sunshine, little miss sunshine cast, abigail breslin | S41: The Little Miss Sunshine cast reunites 20 years later, reflecting on the indie film that made a generation feel seen—and why it still resonates today. | T41: Nostalgic Millennial Film Enthusiast | U41: https://docs.google.com/document/d/1IOMh178EdVVFGnoBUoZ10EcNgsQKusrT74i6IPO4jWQ/edit?usp=sharing | V41: Hanna W
A42: LS-P-046 | B42: Life & Style | C42: Parent-P | E42: https://www.lifeandstylemag.com/wp-admin/post.php?post=736212&action=edit | F42: https://www.lifeandstylemag.com/posts/who-is-egg-in-a-knight-of-the-seven-kingdoms-the-big-reveal-explained/ | G42: Hanna Wickes | I42: Who Is Egg in ‘A Knight of the Seven Kingdoms’? Everything You Need to Know About the Big Identity Reveal | J42: =VLOOKUP(K42,'Weeks 2026'!A:B,2,false) -> 5 | K42: 46054 | L42: =TEXT(N42,"mmmm") -> February | M42: =TEXT(O42,"mmmm") -> February | N42: 46056 | O42: 46056 | P42: Discover | Q42: 1001 | R42: a knight of the seven kingdoms, egg | S42: Episode 3 of 'A Knight of the Seven Kingdoms' revealed the truth about Egg. Here’s who he really is and why it matters for the series. | T42: Casual Streaming Viewer | U42: https://docs.google.com/document/d/13ZKDkJAWMSlrBEDPaHXdR5LuTXti0YxZTejlIrY8nEY/edit?tab=t.0 | V42: Ryan B | AB42: 410 | AC42: 319 | AD42: 13 | AE42: 72 | AF42: 0 | AG42: 0 | AH42: 0 | AI42: 4 | AJ42: LS-P-046 | AK42: 410 | AO42: Movies
A43: LS-P-046-MMC-C02 | B43: Mod Moms Club | C43: Child-C | D43: LS-P-046 | E43: https://modmomsclubstg.wpenginepowered.com/wp-admin/post.php?post=337083&action=edit | F43: https://modmomsclubstg.wpenginepowered.com/lifestyle-entertainment/celebrity/who-is-egg-in-a-knight-of-the-seven-kingdoms/ | G43: Hanna Wickes | I43: Who Is Egg in ‘A Knight of the Seven Kingdoms’? The Shocking Royal Reveal Explained | J43: =VLOOKUP(K43,'Weeks 2026'!A:B,2,false) -> 5 | K43: 46054 | L43: =TEXT(N43,"mmmm") -> February | M43: =TEXT(O43,"mmmm") -> February | N43: 46056 | O43: 46056 | P43: Discover | Q43: 989 | R43: a knight of the seven kingdoms, egg | S43: Episode 3 delivers a massive twist in HBO’s 'A Knight of the Seven Kingdoms.' Here’s the truth about Egg’s identity. | T43: General Audience | U43: https://docs.google.com/document/d/13ZKDkJAWMSlrBEDPaHXdR5LuTXti0YxZTejlIrY8nEY/edit?tab=t.0 | V43: Ryan B
A44: LS-P-048 | B44: Life & Style | C44: Parent-P | E44: https://www.lifeandstylemag.com/wp-admin/post.php?post=736233&action=edit | F44: https://www.lifeandstylemag.com/posts/internet-erupts-babies-sleeping-outside-cold/ | G44: Ryan Brennan | I44: Why Swedish Parents Let Babies Sleep Outside in Freezing Weather — And What the Science Says | J44: =VLOOKUP(K44,'Weeks 2026'!A:B,2,false) -> 5 | K44: 46054 | L44: =TEXT(N44,"mmmm") -> February | M44: =TEXT(O44,"mmmm") -> February | N44: 46056 | O44: 46056 | P44: Discover | Q44: 1061 | R44: babies sleeping outside | S44: A viral video shows babies sleeping outside in the snow. Here’s why Swedish parents do it—and what science says about cold weather sleep. | T44: Trend Hunter B2C | U44: https://docs.google.com/document/d/1d9tpgs0gEHVfJGXrU68nQwtqOVSL0QB1N2F06SHhDw0/edit?tab=t.0 | V44: Hanna W | AB44: 117 | AC44: 31 | AD44: 6 | AE44: 57 | AF44: 0 | AG44: 0 | AH44: 0 | AI44: 0 | AJ44: LS-P-048 | AK44: 326 | AO44: Parenting
A45: LS-P-048-MMC-C02 | B45: Mod Moms Club | C45: Child-C | D45: LS-P-048 | E45: https://modmomsclubstg.wpenginepowered.com/wp-admin/post.php?post=337096&action=edit | F45: https://modmomsclubstg.wpenginepowered.com/parenting/americans-criticize-scandinavian-parenting-norm/ | G45: Ryan Brennan | I45: Do Babies Really Sleep Better Outside? What Scandinavian Parents (and Research) Say | J45: =VLOOKUP(K45,'Weeks 2026'!A:B,2,false) -> 5 | K45: 46054 | L45: =TEXT(N45,"mmmm") -> February | M45: =TEXT(O45,"mmmm") -> February | N45: 46056 | O45: 46056 | P45: Discover | Q45: 779 | R45: babies sleeping outside | S45: A viral video shows a baby sleeping outside in the snow. Here’s why it's a parenting norm in Sweden and what science says about cold-weather naps. | T45: New or Expecting Parent | U45: https://docs.google.com/document/d/1d9tpgs0gEHVfJGXrU68nQwtqOVSL0QB1N2F06SHhDw0/edit?tab=t.0 | V45: Hanna W
A46: LS-P-050 | B46: Life & Style | C46: Parent-P | E46: https://www.lifeandstylemag.com/wp-admin/post.php?post=736242&action=edit | F46: https://www.lifeandstylemag.com/posts/how-to-watch-bts-netflix-reunion-concert-and-documentary/ | G46: Hanna Wickes | I46: BTS Is Back: Everything to Know About Their Netflix Reunion Concert and Documentary | J46: =VLOOKUP(K46,'Weeks 2026'!A:B,2,false) -> 5 | K46: 46054 | L46: =TEXT(N46,"mmmm") -> February | M46: =TEXT(O46,"mmmm") -> February | N46: 46056 | O46: 46056 | P46: Discover | Q46: 859 | R46: bts, comeback, reunion, netflix | S46: BTS is returning with a Netflix livestream concert and documentary. Here’s when it airs, how to watch, and what’s included. | T46: Dedicated K-Pop Fan/ARMY Member | U46: https://docs.google.com/document/d/1IATzfuJr3qniE9WvByDAiiS6j2KAM0AJ3BN18P1idEw/edit?tab=t.0 | V46: Ryan B | AB46: 573 | AC46: 449 | AD46: 9 | AE46: 107 | AF46: 0 | AG46: 0 | AH46: 0 | AI46: 0 | AJ46: LS-P-050 | AK46: 573 | AO46: Pop Culture
A47: LS-P-050-MMC-C02 | B47: Mod Moms Club | C47: Child-C | D47: LS-P-050 | E47: https://modmomsclubstg.wpenginepowered.com/wp-admin/post.php?post=337100&action=edit | F47: https://modmomsclubstg.wpenginepowered.com/lifestyle-entertainment/celebrity/what-parents-need-to-know-about-bts-comeback/ | G47: Hanna Wickes | I47: What Parents Need to Know About BTS’s Big Comeback: Livestream Concert, Documentary, and World Tour | J47: =VLOOKUP(K47,'Weeks 2026'!A:B,2,false) -> 5 | K47: 46054 | L47: =TEXT(N47,"mmmm") -> February | M47: =TEXT(O47,"mmmm") -> February | N47: 46056 | O47: 46056 | P47: Discover | Q47: 942 | R47: bts, comeback, reunion, netflix | S47: BTS is back after their four-year hiatus. Here’s what parents need to know about the livestream concert, new album and Netflix documentary. | T47: Parent of a Teen/Young Adult Fan | U47: https://docs.google.com/document/d/1IATzfuJr3qniE9WvByDAiiS6j2KAM0AJ3BN18P1idEw/edit?tab=t.0 | V47: Ryan B
A48: LS-P-048 | B48: Life & Style | C48: Parent-P | E48: https://www.lifeandstylemag.com/wp-admin/post.php?post=736267&action=edit | F48: https://www.lifeandstylemag.com/posts/cant-miss-italian-restaurants-in-nyc-for-every-price-range/ | G48: Lauren Schuster | I48: How to Choose the Right Bedroom Paint Color for Better Sleep, According to Science | J48: =VLOOKUP(K48,'Weeks 2026'!A:B,2,false) -> 5 | K48: 46054 | L48: =TEXT(N48,"mmmm") -> February | M48: =TEXT(O48,"mmmm") -> February | N48: 46056 | O48: 46056 | P48: Everyday Life | Q48: 1172 | R48: home, living, bedroom paint colors, lifestyle | S48: Struggling to sleep? Experts reveal the best bedroom paint colors for better sleep, backed by science, psychology, and interior design advice | T48: General Audience | U48: https://docs.google.com/document/d/1Kqqy3rXtbi2dsQDfa3d7T0QXYQ1Rp57ecy1elkzTYdU/edit?tab=t.0 | V48: Lauren S | AB48: 209 | AC48: 18 | AD48: 5 | AE48: 166 | AF48: 0 | AG48: 0 | AH48: 0 | AI48: 10 | AO48: Food & Drink
A49: MMC-P-049 | B49: Mod Moms Club | C49: Parent-P | E49: https://modmomsclubstg.wpenginepowered.com/wp-admin/post.php?post=337107&action=edit | F49: https://modmomsclubstg.wpenginepowered.com/parenting/the-best-bedroom-paint-colors-to-help-your-whole-family-sleep-better/ | G49: Lauren J-G | I49: The Best Bedroom Paint Colors to Help Your Whole Family Sleep Better | J49: =VLOOKUP(K49,'Weeks 2026'!A:B,2,false) -> 5 | K49: 46054 | L49: =TEXT(N49,"mmmm") -> February | M49: =TEXT(O49,"mmmm") -> February | N49: 46057 | O49: 46057 | P49: Everyday Life | Q49: 1376 | R49: home, living, bedroom paint colors, lifestyle | S49: Your bedroom paint color could be sabotaging your quality of sleep. Here are the most soothing colors to pick from. | T49: Trend Hunter | U49: https://docs.google.com/document/d/1Kqqy3rXtbi2dsQDfa3d7T0QXYQ1Rp57ecy1elkzTYdU/edit?tab=t.0 | V49: Lauren S | AJ49: MMC-P-049
A50: MMC-P-054 | B50: Mod Moms Club | C50: Parent-P | E50: https://modmomsclubstg.wpenginepowered.com/wp-admin/post.php?post=336952&action=edit | F50: https://modmomsclub.com/lifestyle-entertainment/celebrity/survivor-50-every-sole-survivor-since-2000/ | G50: Ryan Brennan | I50: Survivor 50 Is Almost Here — So Let’s Look Back at 25 Years of Sole Survivors | J50: =VLOOKUP(K50,'Weeks 2026'!A:B,2,false) -> 5 | K50: 46054 | L50: =TEXT(N50,"mmmm") -> February | M50: =TEXT(O50,"mmmm") -> February | N50: 46055 | O50: 46055 | P50: Discover | Q50: 1359 | R50: survivor 50, list of survivor winners, when did survivor start, survivor winners by season, survivor 50 cast | S50: Before “Survivor 50” crowns its next winner, let’s take a look back at every Sole Survivor from the past 25 years of one of reality TV’s most iconic series. | T50: General | U50: https://docs.google.com/document/d/1_t0dLoB4pEfciMPZAQ-jGu7uDCUUv4mEMqO9vSamlcc/edit?usp=sharing | V50: Hanna W | AJ50: MMC-P-054 | AK50: 413
A51: MMC-P-054-LS-C02 | B51: Life & Style | C51: Child-C | D51: MMC-P-054 | E51: https://www.lifeandstylemag.com/wp-admin/post.php?post=736251&action=edit | F51: https://www.lifeandstylemag.com/posts/survivor-50-is-proof-that-it-was-always-bigger-than-one-season/ | G51: Ryan Brennan | I51: Survivor 50 Feels Like a Reunion for Everyone Who Never Missed an Episode | J51: =VLOOKUP(K51,'Weeks 2026'!A:B,2,false) -> 5 | K51: 46054 | L51: =TEXT(N51,"mmmm") -> February | M51: =TEXT(O51,"mmmm") -> February | N51: 46056 | O51: 46056 | P51: Discover | Q51: 1755 | R51: survivor 50 | S51: Survivor 50 is almost here with 24 returning legends. Here’s the full cast, premiere details, and a complete look back at every Sole Survivor. | T51: Trend Hunter | U51: https://docs.google.com/document/d/1_t0dLoB4pEfciMPZAQ-jGu7uDCUUv4mEMqO9vSamlcc/edit?usp=sharing | V51: Hanna W | AB51: 413 | AC51: 305 | AD51: 7 | AE51: 91 | AF51: 0 | AG51: 0 | AH51: 0 | AI51: 0 | AO51: Reality TV
A52: MMC-P-056 | B52: Mod Moms Club | C52: Parent-P | E52: https://modmomsclubstg.wpenginepowered.com/wp-admin/post.php?post=336965&action=edit | F52: https://modmomsclub.com/lifestyle-entertainment/childhood-nostalgic-sounds-may-never-hear-again/ | G52: Ryan Brennan | I52: 26 Nostalgic Sounds From Your Childhood That Kids Today May Never Hear Again | J52: =VLOOKUP(K52,'Weeks 2026'!A:B,2,false) -> 5 | K52: 46054 | L52: =TEXT(N52,"mmmm") -> February | M52: =TEXT(O52,"mmmm") -> February | N52: 46055 | O52: 46055 | P52: Discover | Q52: 1263 | R52: nostalgic sounds, nostalgia, 90s nostalgia, 1990s nostalgia | S52: From dial-up to ice cream truck jingles, these nostalgic sounds from childhood spark major 90s nostalgia — but kids today may never hear them again. | T52: General | U52: https://docs.google.com/document/d/1eeKqcICqYHFa4lbD3F3Q8JJf88qCe_5y3afrkZ01Ttc/edit?tab=t.0 | V52: Hanna W | AJ52: MMC-P-056 | AK52: 217
A53: MMC-P-056-LS-C02 | B53: Life & Style | C53: Child-C | D53: MMC-P-056 | E53: https://www.lifeandstylemag.com/wp-admin/post.php?post=736280&action=edit | F53: https://www.lifeandstylemag.com/posts/26-nostalgic-sounds-your-kids-may-never-hear/ | G53: Ryan Brennan | I53: 26 Nostalgic Sounds That Defined Childhood — And Why They’re Disappearing Before You Notice | J53: =VLOOKUP(K53,'Weeks 2026'!A:B,2,false) -> 5 | K53: 46054 | L53: =TEXT(N53,"mmmm") -> February | M53: =TEXT(O53,"mmmm") -> February | N53: 46056 | O53: 46056 | P53: Discover | Q53: 1571 | R53: nostalgic sounds, nostalgia, 90s nostalgia, 1990s nostalgia | S53: From dial-up internet to ice cream truck jingles, these 26 nostalgic sounds defined childhood—but many have already disappeared. | T53: Trend Hunter | U53: https://docs.google.com/document/d/1eeKqcICqYHFa4lbD3F3Q8JJf88qCe_5y3afrkZ01Ttc/edit?tab=t.0 | V53: Hanna W | AB53: 217 | AC53: 31 | AD53: 5 | AE53: 160 | AF53: 0 | AG53: 0 | AH53: 0 | AI53: 1 | AO53: Technology & Computing
A54: LS-P-058 | B54: Life & Style | C54: Parent-P | E54: https://www.lifeandstylemag.com/wp-admin/post.php?post=736274&action=edit | F54: https://www.lifeandstylemag.com/posts/meet-josh-damaro-everything-to-know-about-disneys-new-ceo/ | G54: Hanna Wickes | I54: Meet Josh D’Amaro: The Disney Parks Veteran Who Is Replacing Bob Iger As Disney's New CEO | J54: =VLOOKUP(K54,'Weeks 2026'!A:B,2,false) -> 5 | K54: 46054 | L54: =TEXT(N54,"mmmm") -> February | M54: =TEXT(O54,"mmmm") -> February | N54: 46056 | O54: 46056 | P54: Discover | Q54: 880 | R54: josh d'amaro, bob iger, disney | S54: Disney has officially named Josh D’Amaro as its next CEO. Here’s everything to know about Bob Iger’s successor and what comes next. | T54: General Audience | U54: https://docs.google.com/document/d/1L4tuxd-Bc4gKhZCn_q-VHGkwL-e4GSe_LURldsMsVkg/edit?tab=t.0 | V54: Ryan B | AB54: 265 | AC54: 56 | AD54: 10 | AE54: 179 | AF54: 0 | AG54: 0 | AH54: 0 | AI54: 1 | AJ54: LS-P-058 | AK54: 265 | AO54: Business
A55: LS-P-058-MMC-C02 | B55: Mod Moms Club | C55: Child-C | D55: LS-P-058 | E55: https://modmomsclubstg.wpenginepowered.com/wp-admin/post.php?post=337109&action=edit | F55: https://modmomsclubstg.wpenginepowered.com/lifestyle-entertainment/from-disneyland-cast-member-to-ceo-what-josh-damaros-rise-means-for-your-next-disney-vacation/ | G55: Hanna Wickes | I55: From Disneyland Cast Member to CEO: What Josh D’Amaro’s Rise Means for Your Next Disney Vacation | J55: =VLOOKUP(K55,'Weeks 2026'!A:B,2,false) -> 5 | K55: 46054 | L55: =TEXT(N55,"mmmm") -> February | M55: =TEXT(O55,"mmmm") -> February | N55: 46056 | O55: 46056 | P55: Discover | Q55: 920 | R55: josh d'amaro, bob iger, disney | S55: Josh D’Amaro will officially become Disney’s CEO in March. Here’s what parents should know about Bob Iger’s transition plan. | T55: Theme Park Enthusiast/Frequent Visitor | U55: https://docs.google.com/document/d/1L4tuxd-Bc4gKhZCn_q-VHGkwL-e4GSe_LURldsMsVkg/edit?tab=t.0 | V55: Ryan B
A56: LS-P-060 | B56: Life & Style | C56: Parent-P | E56: https://www.lifeandstylemag.com/wp-admin/post.php?post=736298&action=edit | F56: https://www.lifeandstylemag.com/posts/this-functional-art-has-the-internet-feeling-nostalgic/ | G56: Ryan Brennan | I56: This Artist Is Turning ’90s Childhood Memories Into Furniture You Can Actually Use | J56: =VLOOKUP(K56,'Weeks 2026'!A:B,2,false) -> 5 | K56: 46054 | L56: =TEXT(N56,"mmmm") -> February | M56: =TEXT(O56,"mmmm") -> February | N56: 46057 | O56: 46057 | P56: Discover | Q56: 1246 | R56: functional art, nostalgic art, grace of spades | S56: Grace of Spades’ viral functional art reimagines some of your childhood favorites as furniture you can actually use in your home. | T56: Millennial Nostalgia Enthusiast | U56: https://docs.google.com/document/d/1i8jfhBr-hXqCRjAPmRXIUufu9PCBhpgl5UMt7e9P-GY/edit?usp=sharing | V56: Hanna W | AB56: 115 | AC56: 20 | AD56: 4 | AE56: 90 | AF56: 0 | AG56: 0 | AH56: 0 | AI56: 1 | AJ56: LS-P-060 | AK56: 115 | AO56: Home & Garden
A57: LS-P-060-MMC-C02 | B57: Mod Moms Club | C57: Child-C | D57: LS-P-060 | E57: https://modmomsclubstg.wpenginepowered.com/wp-admin/post.php?post=337118&action=edit | F57: https://modmomsclubstg.wpenginepowered.com/lifestyle-entertainment/celebrity/functional-art-grace-of-spades-nostalgic/ | G57: Ryan Brennan | I57: This Might Be the Most Comforting Use of Nostalgia the Internet Has Ever Seen | J57: =VLOOKUP(K57,'Weeks 2026'!A:B,2,false) -> 5 | K57: 46054 | L57: =TEXT(N57,"mmmm") -> February | M57: =TEXT(O57,"mmmm") -> February | N57: 46057 | O57: 46057 | P57: Discover | Q57: 1391 | R57: functional art, nostalgic art, grace of spades | S57: Grace of Spades is turning childhood nostalgia into functional art, including furniture inspired by GameBoys, VHS tapes, vintage candy and more. | T57: Gen X Parent Seeking Unique Home Decor | U57: https://docs.google.com/document/d/1i8jfhBr-hXqCRjAPmRXIUufu9PCBhpgl5UMt7e9P-GY/edit?usp=sharing | V57: Hanna W
A58: LS-P-062 | B58: Life & Style | C58: Parent-P | E58: https://www.lifeandstylemag.com/wp-admin/post.php?post=736301&action=edit | F58: https://www.lifeandstylemag.com/posts/why-2016-hits-different-according-to-chloe-bailey/ | G58: Hanna Wickes | I58: Chlöe Bailey Reflects on 2016 and the Era of Music We’ll Never Get Back | J58: =VLOOKUP(K58,'Weeks 2026'!A:B,2,false) -> 5 | K58: 46054 | L58: =TEXT(N58,"mmmm") -> February | M58: =TEXT(O58,"mmmm") -> February | N58: 46057 | O58: 46057 | P58: Discover | Q58: 880 | R58: chloe bailey, 2016, grammys, music | S58: Chlöe Bailey explains why 2016 nostalgia is everywhere, from music oversaturation to why the internet felt easier before algorithms took over. | T58: Gen Z Social Media Native | U58: https://docs.google.com/document/d/1eqc2q2iKOQ7QYt_e7MgN-qOiaOGBWds9Gbr42b6dxZ4/edit?tab=t.0 | V58: Ryan B | AB58: 107 | AC58: 15 | AD58: 5 | AE58: 79 | AF58: 0 | AG58: 0 | AH58: 0 | AI58: 0 | AJ58: LS-P-062 | AK58: 372 | AO58: Pop Culture
A59: LS-P-062-MMC-C02 | B59: Mod Moms Club | C59: Child-C | D59: LS-P-062 | E59: https://modmomsclubstg.wpenginepowered.com/wp-admin/post.php?post=337120&action=edit | F59: https://modmomsclubstg.wpenginepowered.com/lifestyle-entertainment/celebrity/chloe-bailey-nostalgic-for-2016-music/ | G59: Hanna Wickes | I59: Chlöe Bailey’s Grammy Red Carpet Moment Sparks a Bigger Conversation: Why Are We All So Nostalgic for 2016? | J59: =VLOOKUP(K59,'Weeks 2026'!A:B,2,false) -> 5 | K59: 46054 | L59: =TEXT(N59,"mmmm") -> February | M59: =TEXT(O59,"mmmm") -> February | N59: 46057 | O59: 46057 | P59: Discover | Q59: 730 | R59: chloe bailey, 2016, grammys, music | S59: Chlöe Bailey looks back on 2016 and why so many people miss the way music—and the internet—used to feel. | T59: General Audience | U59: https://docs.google.com/document/d/1eqc2q2iKOQ7QYt_e7MgN-qOiaOGBWds9Gbr42b6dxZ4/edit?tab=t.0 | V59: Ryan B
A60: MMC-P-064 | B60: Mod Moms Club | C60: Parent-P | E60: https://modmomsclubstg.wpenginepowered.com/wp-admin/post.php?post=337124&action=edit | F60: https://modmomsclubstg.wpenginepowered.com/lifestyle-entertainment/bluey-dominates-nielsen-ratings-artey-awards/ | G60: Ryan Brennan | I60: The Most-Watched Streaming Titles of 2025 Reveal How We Actually Watch TV | J60: =VLOOKUP(K60,'Weeks 2026'!A:B,2,false) -> 5 | K60: 46054 | L60: =TEXT(N60,"mmmm") -> February | M60: =TEXT(O60,"mmmm") -> February | N60: 46057 | O60: 46057 | P60: Discover | Q60: 1353 | R60: nielsen, nielsen ratings, artey awards | S60: Bluey dominated streaming with 45 billion minutes watched in 2025. Nielsen’s ARTEY Awards show what kids—and parents—couldn’t stop watching. | T60: Streaming-Savvy Parent | U60: https://docs.google.com/document/d/1EgDPx4ndSfZ-UwE6uJh6idZFYcemQAQbrzoNe5N9QsA/edit?usp=sharing | V60: Hanna W | AJ60: MMC-P-064 | AK60: 217
A61: MMC-P-064-LS-C02 | B61: Life & Style | C61: Child-C | D61: MMC-P-064 | E61: https://www.lifeandstylemag.com/wp-admin/post.php?post=736311&action=edit | F61: https://www.lifeandstylemag.com/posts/2025-was-the-most-heavily-streamed-year-on-record-per-nielsen/ | G61: Ryan Brennan | I61: 2025 Became Streaming’s Biggest Year Ever — and the Numbers Are Staggering | J61: =VLOOKUP(K61,'Weeks 2026'!A:B,2,false) -> 5 | K61: 46054 | L61: =TEXT(N61,"mmmm") -> February | M61: =TEXT(O61,"mmmm") -> February | N61: 46057 | O61: 46057 | P61: Discover | Q61: 1241 | R61: nielsen, nielsen ratings, artey awards | S61: Streaming hit a record 16.7 trillion minutes in 2025. From ‘Bluey’ to ‘Stranger Things,’ here’s what dominated viewing last year, per Nielsen | T61: Trend Hunter B2C | U61: https://docs.google.com/document/d/1EgDPx4ndSfZ-UwE6uJh6idZFYcemQAQbrzoNe5N9QsA/edit?usp=sharing | V61: Hanna W | AB61: 217 | AC61: 30 | AD61: 6 | AE61: 178 | AF61: 0 | AG61: 0 | AH61: 0 | AI61: 2 | AO61: Television
A62: LS-P-062 | B62: Life & Style | C62: Parent-P | E62: https://www.lifeandstylemag.com/wp-admin/post.php?post=736353&action=edit | F62: https://www.lifeandstylemag.com/posts/decor-trends-making-a-comeback-in-2026/ | G62: Lauren J-G | I62: Decades-Old (Grandma-Approved!) Décor Trends Are Back in 2026 | J62: =VLOOKUP(K62,'Weeks 2026'!A:B,2,false) -> 5 | K62: 46054 | L62: February | M62: February | N62: 46057 | O62: 46057 | P62: Everyday Life | Q62: 1046 | R62: home, living, lifestyle, interior design, home design | S62: Discover decades-old décor trends making a stylish return in 2026. From decorative molding to chintzy wallpaper, give your home a refresh | T62: Trend Hunter B2C (The Curious Optimizer) | U62: https://docs.google.com/document/d/1car73kCaRXQV0ekpP9wjc96E3qTCccQ5yB3vID9xD5U/edit?tab=t.0 | V62: Lauren S | AB62: 265 | AC62: 37 | AD62: 5 | AE62: 199 | AF62: 0 | AG62: 0 | AH62: 0 | AI62: 1 | AO62: Pop Culture
A63: LS-P-062-MMC-C03 | B63: Mod Moms Club | C63: Child-C | D63: LS-P-062 | E63: https://modmomsclubstg.wpenginepowered.com/wp-admin/post.php?post=337149&action=edit | F63: https://modmomsclubstg.wpenginepowered.com/lifestyle-entertainment/your-builder-grade-home-deserves-better-these-comeback-decor-trends-will-add-the-character-youve-been-craving/ | G63: Lauren J-G | I63: Your Builder-Grade Home Deserves Better: These Comeback Décor Trends Will Add the Character You’ve Been Craving | J63: =VLOOKUP(K63,'Weeks 2026'!A:B,2,false) -> 5 | K63: 46054 | L63: February | M63: February | N63: 46057 | O63: 46057 | P63: Everyday Life | Q63: 1272 | R63: home, living, lifestyle, interior design, home design | S63: Old decor trends are making a stylish return this year. Discover vintage, retro, and classic home design looks that are trending again. | T63: Millennial Homeowner | U63: https://docs.google.com/document/d/1car73kCaRXQV0ekpP9wjc96E3qTCccQ5yB3vID9xD5U/edit?tab=t.0 | V63: Lauren S
A64: LS-P-068 | B64: Life & Style | C64: Parent-P | E64: https://www.lifeandstylemag.com/wp-admin/post.php?post=736310&action=edit | F64: https://www.lifeandstylemag.com/posts/what-is-lady-in-waiting-bridgerton-the-royal-role-explained/ | G64: Hanna Wickes | I64: What Exactly Is a Lady-in-Waiting? ‘Bridgerton’ Season 4 Explains the Prestigious Royal Role | J64: =VLOOKUP(K64,'Weeks 2026'!A:B,2,false) -> 5 | K64: 46054 | L64: February | M64: February | N64: 46057 | O64: 46057 | P64: Discover | Q64: 935 | R64: bridgerton season 4, ladies-in-waiting | S64: Bridgerton' Season 4 shines a spotlight on ladies-in-waiting. Here’s what the royal role really meant—and why it matters to the plot. | T64: General Audience | U64: https://docs.google.com/document/d/1e-rixBB936YUmUFTQT9BEIOjbVMiPJxNAS7Hj8Bv1dc/edit?tab=t.0 | V64: Ryan B | AB64: 496 | AC64: 259 | AD64: 11 | AE64: 206 | AF64: 0 | AG64: 0 | AH64: 0 | AI64: 0 | AJ64: LS-P-068 | AK64: 496 | AO64: Careers
A65: LS-P-068-MMC-C02 | B65: Mod Moms Club | C65: Child-C | D65: LS-P-068 | E65: https://modmomsclubstg.wpenginepowered.com/wp-admin/post.php?post=337125&action=edit | F65: https://modmomsclubstg.wpenginepowered.com/lifestyle-entertainment/what-exactly-is-a-lady-in-waiting-in-bridgerton/ | G65: Hanna Wickes | I65: What Exactly Is a Lady-in-Waiting? The Real History Behind Bridgerton’s Royal Companions | J65: =VLOOKUP(K65,'Weeks 2026'!A:B,2,false) -> 5 | K65: 46054 | L65: February | M65: February | N65: 46057 | O65: 46057 | P65: Discover | Q65: 1117 | R65: bridgerton season 4, ladies-in-waiting | S65: Bridgerton Season 4 has viewers questioning the role of a lady-in-waiting. Here’s what history tells us—and where the show takes liberties. | T65: History-Curious Casual Viewer | U65: https://docs.google.com/document/d/1e-rixBB936YUmUFTQT9BEIOjbVMiPJxNAS7Hj8Bv1dc/edit?tab=t.0 | V65: Ryan B
A66: LS-P-070 | B66: Life & Style | C66: Parent-P | E66: https://www.lifeandstylemag.com/wp-admin/post.php?post=736339&action=edit | F66: https://www.lifeandstylemag.com/posts/home-wellness-trends-2026-create-a-sanctuary-at-home/ | G66: Lauren J-G | I66: The Future of Home Wellness: How 2026 Is Transforming Where We Live Into Sanctuaries for Mind, Body, and Soul | J66: =VLOOKUP(K66,'Weeks 2026'!A:B,2,false) -> 5 | K66: 46054 | L66: February | M66: February | N66: 46057 | O66: 46057 | P66: Everyday Life | Q66: 1358 | R66: home, home decor, home trends, lifestyle | S66: Discover the top home wellness trends of 2026, from meditation corners and scent-layered spaces to pet-friendly spa rooms | T66: General Audience | U66: https://docs.google.com/document/d/1o403ZUDBPJETgqSoIk1Mw21Cal-uWXk7oomHlRc_Zdg/edit?tab=t.0 | V66: Lauren S | AB66: 201 | AC66: 51 | AD66: 4 | AE66: 113 | AF66: 0 | AG66: 0 | AH66: 0 | AI66: 0 | AJ66: LS-P-070 | AK66: 201 | AO66: Home & Garden
A67: MMC-P-067 | B67: Mod Moms Club | C67: Parent-P | E67: https://modmomsclubstg.wpenginepowered.com/wp-admin/post.php?post=337139&action=edit | F67: https://modmomsclubstg.wpenginepowered.com/lifestyle-entertainment/your-builder-grade-home-deserves-better-these-comeback-decor-trends-will-add-the-character-youve-been-craving/ | G67: Lauren J-G | I67: How to Design Your Home for Mental Clarity: The 2026 Wellness Trends That Support Consistent Practice | J67: =VLOOKUP(K67,'Weeks 2026'!A:B,2,false) -> 5 | K67: 46054 | L67: February | M67: February | N67: 46057 | O67: 46057 | P67: Everyday Life | Q67: 1272 | R67: home, home decor, home trends, lifestyle | S67: In 2026, home design is focusing more on health and wellness. See what the new trends are, ranging from scent layering to focusing on relaxation rooms. | T67: Wellness-Focused Professional Managing Stress | U67: https://docs.google.com/document/d/1o403ZUDBPJETgqSoIk1Mw21Cal-uWXk7oomHlRc_Zdg/edit?tab=t.0 | V67: Lauren S | AJ67: MMC-P-067
A68: LS-P-072 | B68: Life & Style | C68: Parent-P | E68: https://www.lifeandstylemag.com/wp-admin/post.php?post=736331&action=edit | F68: https://www.lifeandstylemag.com/posts/snow-storm-walk-to-school-parents-nostalgia/ | G68: Ryan Brennan | I68: This College Student’s Walk to Class in a Snow Storm Has Parents Feeling Vindicated | J68: =VLOOKUP(K68,'Weeks 2026'!A:B,2,false) -> 5 | K68: 46054 | L68: February | M68: February | N68: 46057 | O68: 46057 | P68: Discover | Q68: 817 | R68: snow storm, walk to school, walking to school, uphill both ways | S68: This viral snow storm video shows a college student walking to school in a blizzard—and the comments say it’s exactly like parents warned. | T68: Trend Hunter B2C | U68: https://docs.google.com/document/d/1uO7lrbdu9lRm1qg7EgBz7mQNO40QQaXMFbpw936ioVw/edit?usp=sharing | V68: Hanna W | AB68: 134 | AC68: 9 | AD68: 8 | AE68: 105 | AF68: 0 | AG68: 0 | AH68: 0 | AI68: 1 | AJ68: LS-P-072 | AK68: 134 | AO68: Parenting
A69: LS-P-072-MMC-C02 | B69: Mod Moms Club | C69: Child-C | D69: LS-P-072 | E69: https://modmomsclubstg.wpenginepowered.com/wp-admin/post.php?post=337133&action=edit | F69: https://modmomsclubstg.wpenginepowered.com/lifestyle-entertainment/celebrity/student-walk-to-school-snow-storm-nostalgic/ | G69: Ryan Brennan | I69: Why This Viral Snow Storm Video Has Parents Everywhere Saying 'We Told You So' | J69: =VLOOKUP(K69,'Weeks 2026'!A:B,2,false) -> 5 | K69: 46054 | L69: February | M69: February | N69: 46057 | O69: 46057 | P69: Discover | Q69: 906 | R69: snow storm, walk to school, walking to school, uphill both ways | S69: A college student’s walk to school in a snow storm went viral—proving parents may not have lied about walking to school uphill both ways. | T69: Nostalgic Parent/Grandparent | U69: https://docs.google.com/document/d/1uO7lrbdu9lRm1qg7EgBz7mQNO40QQaXMFbpw936ioVw/edit?usp=sharing | V69: Hanna W
A70: LS-P-074 | B70: Life & Style | C70: Parent-P | E70: https://www.lifeandstylemag.com/wp-admin/post.php?post=736351&action=edit | F70: https://www.lifeandstylemag.com/posts/spotifys-page-match-bridges-physical-books-and-audiobooks/ | G70: Lauren Schuster | I70: Spotify Wants to Change How You Read Books — By Letting You Listen and Read at the Same Time | J70: =VLOOKUP(K70,'Weeks 2026'!A:B,2,false) -> 5 | K70: 46054 | L70: February | M70: February | N70: 46057 | O70: 46058 | P70: Experiences | Q70: 1140 | R70: Spotify, Books, audiobooks, | S70: Spotify unveils new features that let readers move seamlessly between physical books and audiobooks, fitting reading into modern life | T70: General Audience | U70: https://docs.google.com/document/d/1OPdOW6dYllTIp4aTEu57jaTY-zTDV_z6YDvdpPD8qSI/edit?tab=t.0 | V70: Lauren JG | AB70: 104 | AC70: 13 | AD70: 12 | AE70: 65 | AF70: 0 | AG70: 0 | AH70: 0 | AI70: 1 | AJ70: LS-P-074 | AK70: 104 | AO70: Technology & Computing
A71: LS-P-074-MMC-C02 | B71: Mod Moms Club | C71: Child-C | D71: LS-P-074 | E71: https://modmomsclubstg.wpenginepowered.com/wp-admin/post.php?post=337148&action=edit | F71: https://modmomsclubstg.wpenginepowered.com/lifestyle-entertainment/new-spotify-features-could-help-your-reluctant-reader-finally-fall-in-love-with-books/ | G71: Lauren Schuster | I71: New Spotify Features Could Help Your Reluctant Reader Finally Fall in Love with Books | J71: =VLOOKUP(K71,'Weeks 2026'!A:B,2,false) -> 5 | K71: 46054 | L71: February | M71: February | N71: 46057 | O71: 46058 | P71: Experiences | Q71: 1123 | R71: Spotify, Books, audiobooks, reading | S71: Spotify’s Page Match blends audiobooks and physical books, giving parents new tools to help reluctant kids and teens build reading habits | T71: Parent of Reluctant Readers | U71: https://docs.google.com/document/d/1OPdOW6dYllTIp4aTEu57jaTY-zTDV_z6YDvdpPD8qSI/edit?tab=t.0 | V71: Lauren JG
A72: LS-P-076 | B72: Life & Style | C72: Parent-P | E72: https://www.lifeandstylemag.com/wp-admin/post.php?post=736334&action=edit | F72: https://www.lifeandstylemag.com/posts/lewis-hamiltons-star-studded-dating-history-as-kim-kardashian-rumors-swirl/ | G72: Hanna Wickes | I72: Lewis Hamilton’s A-List Dating History: From Rihanna to the Kardashians, Inside F1’s Most Star-Studded Love Life | J72: =VLOOKUP(K72,'Weeks 2026'!A:B,2,false) -> 5 | K72: 46054 | L72: February | M72: February | N72: 46057 | O72: 46057 | P72: Discover | Q72: 1778 | R72: lewis hamilton, dating history, kim kardashian | T72: Celebrity Culture Enthusiast | U72: https://docs.google.com/document/d/1pZn4InklZ25eT7FIL1BHPzSKlTHUBEkXXCHg4pMfiNc/edit?tab=t.0 | V72: Ryan B | AB72: 1057 | AC72: 754 | AD72: 9 | AE72: 271 | AF72: 0 | AG72: 0 | AH72: 0 | AI72: 2 | AJ72: LS-P-076 | AK72: 1057 | AO72: Celebrity Relationships
A73: LS-P-076-MMC-C02 | B73: Mod Moms Club | C73: Child-C | D73: LS-P-076 | E73: https://modmomsclubstg.wpenginepowered.com/wp-admin/post.php?post=337137&action=edit | F73: https://modmomsclubstg.wpenginepowered.com/lifestyle-entertainment/lewis-hamiltons-complete-dating-history/ | G73: Hanna Wickes | I73: Lewis Hamilton’s Complete Dating History: Inside the F1 Legend’s Romantic Life Over Two Decades | J73: =VLOOKUP(K73,'Weeks 2026'!A:B,2,false) -> 5 | K73: 46054 | L73: February | M73: February | N73: 46057 | O73: 46057 | P73: Discover | Q73: 1302 | R73: lewis hamilton, dating history, kim kardashian | T73: General Audience | U73: https://docs.google.com/document/d/1pZn4InklZ25eT7FIL1BHPzSKlTHUBEkXXCHg4pMfiNc/edit?tab=t.0 | V73: Ryan B
A74: LS-P-078 | B74: Life & Style | C74: Parent-P | E74: https://www.lifeandstylemag.com/wp-admin/post.php?post=736372&action=edit | F74: https://www.lifeandstylemag.com/posts/these-my-strange-addiction-moments-are-wild-unforgettable/ | G74: Ryan Brennan | I74: ‘My Strange Addiction’ Is Back After 11-Year Hiatus. Let’s Revisit Its Most Viral Moments | J74: =VLOOKUP(K74,'Weeks 2026'!A:B,2,false) -> 5 | K74: 46054 | L74: February | M74: February | N74: 46057 | O74: 46058 | P74: Discover | Q74: 1943 | R74: my strange addiction, new my strange addiction | S74: Before watching the new ‘My Strange Addiction’ season, look back at the most shocking and viral moments from the TLC series’ original run. | T74: Nostalgic Reality TV Enthusiast | U74: https://docs.google.com/document/d/1_3Igp6B2zccHt411ffk8jwj7kwF0PQPqcn-8HhghR3U/edit?usp=sharing | V74: Hanna W | AB74: 169 | AC74: 71 | AD74: 2 | AE74: 83 | AF74: 0 | AG74: 0 | AH74: 0 | AI74: 0 | AJ74: LS-P-078 | AK74: 169 | AO74: Reality TV
A75: LS-P-078-MMC-C02 | B75: Mod Moms Club | C75: Child-C | D75: LS-P-078 | E75: https://modmomsclubstg.wpenginepowered.com/wp-admin/post.php?post=337152&action=edit | F75: https://modmomsclubstg.wpenginepowered.com/lifestyle-entertainment/celebrity/my-strange-addiction-most-viral-moments-tlc/ | G75: Ryan Brennan | I75: ‘My Strange Addiction’ Returns After 11 Years—and So Did the Memories We Tried to Forget | J75: =VLOOKUP(K75,'Weeks 2026'!A:B,2,false) -> 5 | K75: 46054 | L75: February | M75: February | N75: 46057 | O75: 46058 | P75: Discover | Q75: 1723 | R75: my strange addiction, new my strange addiction | S75: My Strange Addiction is back after 11 years. Revisit the wildest moments from 2010–2015 and learn how to watch the new ‘My Strange Addiction’ season. | T75: Trend Hunter B2C | U75: https://docs.google.com/document/d/1_3Igp6B2zccHt411ffk8jwj7kwF0PQPqcn-8HhghR3U/edit?usp=sharing | V75: Hanna W
A76: LS-P-080 | B76: Life & Style | C76: Parent-P | E76: https://www.lifeandstylemag.com/wp-admin/post.php?post=736363&action=edit | F76: https://www.lifeandstylemag.com/posts/why-draco-malfoy-is-everywhere-during-chinas-lunar-new-year/ | G76: Hanna Wickes | I76: Draco Malfoy Is China’s Unlikely Lunar New Year Icon and the Internet Is Losing It | J76: =VLOOKUP(K76,'Weeks 2026'!A:B,2,false) -> 5 | K76: 46054 | L76: February | M76: February | N76: 46057 | O76: 46058 | P76: Discover | Q76: 858 | R76: draco malfoy, lunar new year, harry potter | S76: A linguistic coincidence turned Draco Malfoy into a good luck charm for the Lunar New Year—and Chinese social media is fully embracing it. | T76: Pop Culture & Social Media Trend Watcher | U76: https://docs.google.com/document/d/1OAO9kvCk2C-BRRjvxMFpqD5ts3BxSgLI0KaeW5i9Yts/edit?tab=t.0 | V76: Ryan B | AB76: 238 | AC76: 144 | AD76: 7 | AE76: 61 | AF76: 0 | AG76: 0 | AH76: 0 | AI76: 0 | AJ76: LS-P-080 | AK76: 238 | AO76: Movies
A77: LS-P-080-MMC-C02 | B77: Mod Moms Club | C77: Child-C | D77: LS-P-080 | E77: https://modmomsclubstg.wpenginepowered.com/wp-admin/post.php?post=337150&action=edit | F77: https://modmomsclubstg.wpenginepowered.com/lifestyle-entertainment/celebrity/how-draco-malfoy-became-good-luck-charm-for-lunar-new-year/ | G77: Hanna Wickes | I77: How Draco Malfoy Became China’s Unlikely Good Luck Charm for the Year of the Horse | J77: =VLOOKUP(K77,'Weeks 2026'!A:B,2,false) -> 5 | K77: 46054 | L77: February | M77: February | N77: 46057 | O77: 46058 | P77: Discover | R77: draco malfoy, lunar new year, harry potter | S77: A Mandarin name translation and centuries-old Lunar New Year customs have transformed Draco Malfoy into an unexpected symbol of luck. | T77: General Audience | U77: https://docs.google.com/document/d/1OAO9kvCk2C-BRRjvxMFpqD5ts3BxSgLI0KaeW5i9Yts/edit?tab=t.0 | V77: Ryan B
A78: LS-P-082 | B78: Life & Style | C78: Parent-P | E78: https://www.lifeandstylemag.com/wp-admin/post.php?post=736404&action=edit | F78: https://www.lifeandstylemag.com/posts/why-seasonal-menus-matter-how-to-spot-them-in-restaurants/ | G78: Lauren Schuster | I78: Why the Smartest Food Lovers Are Hunting for Seasonal Menus Right Now | J78: =VLOOKUP(K78,'Weeks 2026'!A:B,2,false) -> 5 | K78: 46054 | L78: February | M78: February | N78: 46058 | O78: 46058 | P78: Experiences | Q78: 986 | R78: dining, restaurants, food, Seasonal food, | S78: Seasonal menus signal fresher ingredients, better flavor, and smarter pricing, indicating restaurants that prioritize craft and value | T78: Local Food Enthusiast & Restaurant Explorer | U78: https://docs.google.com/document/d/1Kl53syiuMxAdRVQYMXm0Y9lDojwt58jwAzxgUj_uJ9A/edit?tab=t.0 | V78: Lauren JG | AB78: 56 | AC78: 1 | AD78: 6 | AE78: 38 | AF78: 0 | AG78: 0 | AH78: 0 | AI78: 0 | AJ78: LS-P-082 | AK78: 56 | AO78: Food & Drink
A79: LS-P-082-MMC-C02 | B79: Mod Moms Club | C79: Child-C | D79: LS-P-082 | E79: https://modmomsclubstg.wpenginepowered.com/wp-admin/post.php?post=337168&action=edit | F79: https://modmomsclubstg.wpenginepowered.com/lifestyle-entertainment/food/how-seasonal-restaurant-menus-can-save-you-money-while-delivering-better-flavor/ | G79: Lauren Schuster | I79: How Seasonal Restaurant Menus Can Save You Money While Delivering Better Flavor | J79: =VLOOKUP(K79,'Weeks 2026'!A:B,2,false) -> 5 | K79: 46054 | L79: February | M79: February | N79: 46058 | O79: 46058 | P79: Experiences | Q79: 1014 | R79: dining, restaurants, food, budget | S79: Seasonal menus help diners save money by offering fresher ingredients, better flavor, and smarter pricing without sacrificing quality | T79: Budget-Conscious Home Cook | U79: https://docs.google.com/document/d/1Kl53syiuMxAdRVQYMXm0Y9lDojwt58jwAzxgUj_uJ9A/edit?tab=t.0 | V79: Lauren JG
A80: LS-P-084 | B80: Life & Style | C80: Parent-P | E80: https://www.lifeandstylemag.com/wp-admin/post.php?post=736396&action=edit | F80: https://www.lifeandstylemag.com/posts/espn-hires-influencer-lily-shimbashi-as-full-time-creator/ | G80: Ryan Brennan | I80: ESPN’s Bet on Female Sports Fandom: How One Creator Is Rewriting the Playbook | J80: =VLOOKUP(K80,'Weeks 2026'!A:B,2,false) -> 5 | K80: 46054 | L80: February | M80: February | N80: 46058 | O80: 46058 | P80: Discover | Q80: 1225 | R80: lily shimbashi, espn, espn creator network, sportsish | S80: ESPN adds influencer Lily Shimbashi to its creator roster, aiming to better connect with female fandom across major sports events. | T80: Trend Hunter B2C | U80: https://docs.google.com/document/d/10mlpItuvvRMK1BFbkGlS2TFRIYXBRN5-VD91sKnrI4A/edit?usp=sharing | V80: Hanna W | AB80: 206 | AC80: 43 | AD80: 9 | AE80: 135 | AF80: 0 | AG80: 0 | AH80: 0 | AI80: 1 | AJ80: LS-P-084 | AK80: 206 | AO80: Sports
A81: LS-P-084-MMC-C02 | B81: Mod Moms Club | C81: Child-C | D81: LS-P-084 | E81: https://modmomsclubstg.wpenginepowered.com/wp-admin/post.php?post=337163&action=edit | F81: https://modmomsclubstg.wpenginepowered.com/lifestyle-entertainment/celebrity/espn-hires-sportsish-founder-lily-shimbashi/ | G81: Ryan Brennan | I81: Lily Shimbashi Is Stepping Into the Spotlight as ESPN Leans Into Female Fandom | J81: =VLOOKUP(K81,'Weeks 2026'!A:B,2,false) -> 5 | K81: 46054 | L81: February | M81: February | N81: 46058 | O81: 46058 | P81: Discover | Q81: 1424 | R81: lily shimbashi, espn, espn creator network, sportsish | S81: ESPN expands its creator strategy by signing influencer Lily Shimbashi to connect with female fandom and lead red carpet coverage at major events. | T81: Young Female Sports Fan | U81: https://docs.google.com/document/d/10mlpItuvvRMK1BFbkGlS2TFRIYXBRN5-VD91sKnrI4A/edit?usp=sharing | V81: Hanna W
A82: LS-P-086 | B82: Life & Style | C82: Parent-P | E82: https://www.lifeandstylemag.com/wp-admin/post.php?post=736398&action=edit | F82: https://www.lifeandstylemag.com/posts/red-velvets-2016-russian-roulette-goes-viral-again-in-2026/ | G82: Hanna Wickes | I82: Red Velvet Just Gave Us the Ultimate 2016 Throwback—And Fans Are Emotional | J82: =VLOOKUP(K82,'Weeks 2026'!A:B,2,false) -> 5 | K82: 46054 | L82: February | M82: February | N82: 46058 | O82: 46058 | P82: Discover | Q82: 852 | R82: red velvet, 2016, russian roulette | S82: Red Velvet brought their 2016 classic 'Russian Roulette' back to TikTok, reminding fans why the era remains so iconic. | T82: Dedicated K-Pop Fan (Gen Z/Millennial) | U82: https://docs.google.com/document/d/10D-sQXDyxDd-n63nPDjiGaLXyNH9NUbIGVjIFVzPi5I/edit?tab=t.0 | V82: Ryan B | AB82: 166 | AC82: 70 | AD82: 5 | AE82: 69 | AF82: 0 | AG82: 0 | AH82: 0 | AI82: 1 | AJ82: LS-P-086 | AK82: 166 | AO82: Pop Culture
A83: LS-P-086-MMC-C02 | B83: Mod Moms Club | C83: Child-C | D83: LS-P-086 | E83: https://modmomsclubstg.wpenginepowered.com/wp-admin/post.php?post=337166&action=edit | F83: https://modmomsclubstg.wpenginepowered.com/lifestyle-entertainment/celebrity/red-velvet-brings-back-2016-with-russian-roulette-tiktok/ | G83: Hanna Wickes | I83: Red Velvet Brings Back the Magic of 2016 with Nostalgic 'Russian Roulette' TikTok Dance | J83: =VLOOKUP(K83,'Weeks 2026'!A:B,2,false) -> 5 | K83: 46054 | L83: February | M83: February | N83: 46058 | O83: 46058 | P83: Discover | Q83: 975 | R83: red velvet, 2016, russian roulette | S83: Nearly a decade after its release, Red Velvet’s “Russian Roulette” is trending again thanks to a nostalgic TikTok from the group’s members. | T83: General Audience | U83: https://docs.google.com/document/d/10D-sQXDyxDd-n63nPDjiGaLXyNH9NUbIGVjIFVzPi5I/edit?tab=t.0 | V83: Ryan B
A84: LS-P-088 | B84: Life & Style | C84: Parent-P | E84: https://www.lifeandstylemag.com/wp-admin/post.php?post=736427&action=edit | F84: https://www.lifeandstylemag.com/posts/food-halls-explained-why-this-dining-trend-is-booming/ | G84: Lauren Schuster | I84: Food Halls Are Quietly Reshaping How Americans Eat Out—Here’s What’s Driving the Shift | J84: =VLOOKUP(K84,'Weeks 2026'!A:B,2,false) -> 5 | K84: 46054 | L84: February | M84: February | N84: 46058 | O84: 46058 | P84: Experiences | Q84: 793 | R84: food, dining, restaurants, food halls | S84: Food halls are booming nationwide, offering curated, chef-driven dining that solves group indecision and brings diverse menus under one roof | T84: Trend Hunter B2C (The Curious Optimizer) | U84: https://docs.google.com/document/d/1Sm0jz7HCRt_5JeDlI6UHmM3UQlz4VwIc4mbE8-D27Ms/edit?tab=t.0 | V84: Lauren JG | AB84: 73 | AC84: 16 | AD84: 3 | AE84: 43 | AF84: 0 | AG84: 0 | AH84: 0 | AI84: 0 | AJ84: LS-P-088 | AK84: 73 | AO84: Food & Drink
A85: LS-P-088-MMC-C02 | B85: Mod Moms Club | C85: Child-C | D85: LS-P-088 | E85: https://modmomsclubstg.wpenginepowered.com/wp-admin/post.php?post=337178&action=edit | F85: https://modmomsclubstg.wpenginepowered.com/lifestyle-entertainment/food/food-halls-your-secret-weapon-for-group-dining-without-the-drama/ | G85: Lauren Schuster | I85: Food Halls: Your Secret Weapon for Group Dining Without the Drama | J85: =VLOOKUP(K85,'Weeks 2026'!A:B,2,false) -> 5 | K85: 46054 | L85: February | M85: February | N85: 46058 | O85: 46059 | P85: Experiences | Q85: 1007 | R85: food, dining, restaurants, food halls | S85: Food halls solve group dining drama by offering multiple cuisines, budgets, and diets in one place—no compromises, no endless debates | T85: Social Dining Coordinator | U85: https://docs.google.com/document/d/1Sm0jz7HCRt_5JeDlI6UHmM3UQlz4VwIc4mbE8-D27Ms/edit?tab=t.0 | V85: Lauren JG
A86: LS-P-090 | B86: Life & Style | C86: Parent-P | E86: https://www.lifeandstylemag.com/wp-admin/post.php?post=736432&action=edit | F86: https://www.lifeandstylemag.com/posts/how-to-make-your-home-feel-more-open/ | G86: Lauren J-G | I86: Simple Design Tricks That Make Any Home Feel Bigger and Brighter | J86: 5 | K86: 46054 | L86: February | M86: February | N86: 46058 | O86: 45693 | P86: Everyday Life | Q86: 1065 | R86: home, home interior design, home decor, home trends, lifestyle | S86: Learn simple, designer-backed tips to make your home feel brighter, bigger, and more open — no renovation required | T86: General Audience | U86: https://docs.google.com/document/d/1KBVwbzeOfILGY_FmHaDgXIqNwUVvriTUMHmXeN7jrSY/edit?tab=t.0 | V86: Lauren S | AB86: 106 | AC86: 6 | AD86: 4 | AE86: 74 | AF86: 0 | AG86: 0 | AH86: 0 | AI86: 1 | AJ86: LS-P-090 | AK86: 106
A87: LS-P-090-MMC-C02 | B87: Mod Moms Club | C87: Child-C | D87: LS-P-090 | E87: https://modmomsclubstg.wpenginepowered.com/wp-admin/post.php?post=337179&action=edit | F87: https://modmomsclubstg.wpenginepowered.com/lifestyle-entertainment/simple-design-tricks-to-make-your-first-place-feel-bigger/ | G87: Lauren J-G | I87: Simple Design Tricks to Make Your First Place Feel Bigger | J87: 5 | K87: 46054 | L87: February | M87: February | N87: 46058 | O87: 46059 | P87: Everyday Life | Q87: 1287 | R87: home, home interior design, home decor, home trends, lifestyle | S87: Discover simple, designer-approved ways to make your home feel bigger, brighter, and more open — no renovation required. | T87: First-Time Homeowner or Renter | U87: https://docs.google.com/document/d/1KBVwbzeOfILGY_FmHaDgXIqNwUVvriTUMHmXeN7jrSY/edit?tab=t.0 | V87: Lauren S
A88: LS-P-092 | B88: Life & Style | C88: Parent-P | E88: https://www.lifeandstylemag.com/wp-admin/post.php?post=736474&action=edit | F88: https://www.lifeandstylemag.com/posts/create-a-cozy-winter-retreat-at-home/ | G88: Lauren J-G | I88: Simple Ways to Transform Your Home Into a Cozy Winter Retreat | J88: 5 | K88: 46054 | L88: February | M88: February | N88: 46058 | O88: 46059 | P88: Everyday Life | Q88: 1218 | R88: home, interior design, home decor, home trends, lifestyle | S88: Turn your home into a cozy winter retreat with easy tips for warmer lighting, scents, and simple touches that make your space feel inviting | T88: General Audience | U88: https://docs.google.com/document/d/1n-67y4SJw3ZvzdbgeAYs4hSfq-1fJe6_tvXP2A9zWXM/edit?tab=t.0 | V88: Lauren S | AB88: 79 | AC88: 7 | AD88: 6 | AE88: 59 | AF88: 0 | AG88: 0 | AH88: 0 | AI88: 0 | AJ88: LS-P-092 | AK88: 79
A89: LS-P-092-MMC-C02 | B89: Mod Moms Club | C89: Child-C | D89: LS-P-092 | E89: https://modmomsclubstg.wpenginepowered.com/wp-admin/post.php?post=337202&action=edit | F89: https://modmomsclubstg.wpenginepowered.com/lifestyle-entertainment/how-to-make-your-home-feel-cozier-this-winter-without-losing-your-mind-or-your-budget/ | G89: Lauren J-G | I89: How to Make Your Home Feel Cozier This Winter (Without Losing Your Mind or Your Budget) | J89: 5 | K89: 46054 | L89: February | M89: February | N89: 46059 | O89: 46059 | P89: Everyday Life | Q89: 1515 | R89: home, home decor, home trends, lifestyle | S89: Make your home warm and inviting this winter with simple tips for better lighting, cozy textures, comforting scents, and clutter-free spaces that boost comfort and brightness all season long. | T89: Budget-Conscious Young Parent or Family Caregiver | U89: https://docs.google.com/document/d/1n-67y4SJw3ZvzdbgeAYs4hSfq-1fJe6_tvXP2A9zWXM/edit?tab=t.0 | V89: Lauren S
A90: LS-P-094 | B90: Life & Style | C90: Parent-P | E90: https://www.lifeandstylemag.com/wp-admin/post.php?post=736418&action=edit | F90: https://www.lifeandstylemag.com/posts/the-2016-songs-we-cant-stop-playing-in-2026/ | G90: Hanna Wickes | J90: 5 | K90: 46054 | L90: February | M90: February | N90: 46058 | O90: 46058 | P90: Discover | Q90: 1407 | R90: 2016, music, nostalgic, songs | S90: From Rihanna and Ariana Grande to The Weeknd and Justin Bieber, these 2016 songs still hit just as hard nearly a decade later. | T90: Nostalgic Millennial Professional | U90: https://docs.google.com/document/d/1jTsAJZvmR7m2iJFkcbUFL03PB18sn5f49jKgN02pwCU/edit?tab=t.0 | V90: Sara V | AB90: 176 | AC90: 63 | AD90: 5 | AE90: 93 | AF90: 0 | AG90: 0 | AH90: 0 | AI90: 2 | AJ90: LS-P-094 | AK90: 176 | AO90: Pop Culture
A91: LS-P-094-MMC-C02 | B91: Mod Moms Club | C91: Child-C | D91: LS-P-094 | E91: https://modmomsclubstg.wpenginepowered.com/wp-admin/post.php?post=337174&action=edit | F91: https://modmomsclubstg.wpenginepowered.com/lifestyle-entertainment/why-we-cant-stop-listening-to-2016-musi/ | G91: Hanna Wickes | J91: 5 | K91: 46054 | L91: February | M91: February | N91: 46058 | O91: 46058 | P91: Discover | Q91: 1375 | R91: 2016, music, nostalgic, songs | S91: From Rihanna to The Weeknd, these six standout songs from 2016 continue to resonate nearly a decade later. | T91: General Audience | U91: https://docs.google.com/document/d/1jTsAJZvmR7m2iJFkcbUFL03PB18sn5f49jKgN02pwCU/edit?tab=t.0 | V91: Sara V
A92: LS-P-096 | B92: Life & Style | C92: Parent-P | E92: https://www.lifeandstylemag.com/wp-admin/post.php?post=736449&action=edit | F92: https://www.lifeandstylemag.com/posts/10-k-dramas-every-beginner-should-watch-first/ | G92: Hanna Wickes | I92: Your Gateway to Korean Drama: 10 Essential K-Dramas Perfect for First-Time Viewers | J92: 5 | K92: 46054 | L92: February | M92: February | N92: 46058 | O92: 46060 | P92: Discover | Q92: 1412 | R92: k-drama, beginners, top 10 | S92: From 'Crash Landing on You' to 'Goblin,' these 10 K-dramas are must-watch picks for anyone new to Korean television. | T92: General Audience | U92: https://docs.google.com/document/d/1BVjnVyRL_hA3xW-Pu8Ntqb3hk5oogXbfHl3rftVjuFE/edit?tab=t.0 | V92: Ryan B | AB92: 4455 | AC92: 3964 | AD92: 2 | AE92: 470 | AF92: 0 | AG92: 0 | AH92: 0 | AI92: 6 | AJ92: LS-P-096 | AK92: 4455 | AO92: Movies
A93: LS-P-096-MMC-C02 | B93: Mod Moms Club | C93: Child-C | D93: LS-P-096 | E93: https://modmomsclubstg.wpenginepowered.com/wp-admin/post.php?post=337182&action=edit | F93: https://modmomsclubstg.wpenginepowered.com/lifestyle-entertainment/10-best-k-dramas-for-beginners/ | G93: Hanna Wickes | I93: Your K-Drama Starter Kit: A Friendly Guide to Finding Your First Korean Drama Obsession | J93: 5 | K93: 46054 | L93: February | M93: February | N93: 46058 | O93: 46060 | P93: Discover | Q93: 1684 | R93: k-drama, beginners, top 10 | S93: New to K-dramas and not sure where to start? This beginner-friendly guide breaks down the best shows by genre, time commitment, and tone. | T93: Curious Entertainment Newcomer | U93: https://docs.google.com/document/d/1BVjnVyRL_hA3xW-Pu8Ntqb3hk5oogXbfHl3rftVjuFE/edit?tab=t.0 | V93: Ryan B
A94: LS-P-098 | B94: Life & Style | C94: Parent-P | E94: https://www.lifeandstylemag.com/wp-admin/post.php?post=736527&action=edit | F94: https://www.lifeandstylemag.com/posts/smart-carry-on-essentials-that-make-flights-more-comfortable/ | G94: Lauren Schuster | I94: The Carry-On Upgrades Frequent Flyers Swear By (That You Probably Haven’t Tried Yet) | J94: 5 | K94: 46054 | L94: February | M94: February | N94: 46058 | O94: 46059 | P94: Experiences | Q94: 785 | R94: Travel, flights, packing, carry-on | S94: These smart carry-on essentials solve common flight frustrations, from dead devices to cold cabins, helping travelers fly calmer and more prepared | T94: Trend Hunter B2C (The Curious Optimizer) | U94: https://docs.google.com/document/d/1wPQTPvgZfQkfu7aQrrpMl2n5mMeMqSaKr3Djtrcj1U0/edit?tab=t.0 | V94: Lauren JG | AB94: 143 | AC94: 19 | AD94: 5 | AE94: 70 | AF94: 0 | AG94: 0 | AH94: 0 | AI94: 0 | AJ94: LS-P-098 | AK94: 143 | AO94: Travel
A95: LS-P-098-MMC-C02 | B95: Mod Moms Club | C95: Child-C | D95: LS-P-098 | E95: https://modmomsclubstg.wpenginepowered.com/wp-admin/post.php?post=337233&action=edit | F95: https://modmomsclubstg.wpenginepowered.com/lifestyle-entertainment/the-budget-savvy-family-travelers-secret-weapons-these-carry-on-items-can-save-you-money-frustration/ | G95: Lauren Schuster | I95: The Budget-Savvy Family Traveler’s Secret Weapons: These Carry-On Items Can Save You Money & Frustration | J95: 5 | K95: 46054 | L95: February | M95: February | N95: 46058 | O95: 46062 | P95: Experiences | Q95: 1099 | R95: family trip, flying with kids, traveling with kids, travel | S95: Flying with kids is pricey enough; this simple carry-on essential helps families skip airport water costs and stay hydrated without extra spending | T95: Budget-Conscious Family Vacation Planner | U95: https://docs.google.com/document/d/1wPQTPvgZfQkfu7aQrrpMl2n5mMeMqSaKr3Djtrcj1U0/edit?tab=t.0 | V95: Lauren JG
A96: MMC-P-100 | B96: Mod Moms Club | C96: Parent-P | E96: https://modmomsclubstg.wpenginepowered.com/wp-admin/post.php?post=337025&action=edit | F96: https://modmomsclubstg.wpenginepowered.com/parenting/your-first-family-trip-to-broadway-a-parents-guide-to-choosing-the-perfect-show-for-kids/ | G96: Lauren Schuster | I96: Your First Family Trip to Broadway: A Parent’s Guide to Choosing the Perfect Show for Kids | J96: 5 | K96: 46054 | L96: February | M96: February | N96: 46055 | O96: 46055 | P96: Experiences | Q96: 1065 | R96: activites for kids, broadway, parenting | S96: Not sure if your child is ready for Broadway? This guide helps parents pick the best first show based on age, maturity, and interests | T96: First-Time Theatre Parent | U96: https://docs.google.com/document/d/1k-wJDjsq7YidLBz_3pVzonslDOvyDgRZV2P-tGgwROU/edit?tab=t.0 | V96: Sara V | AJ96: MMC-P-100 | AK96: 70
A97: MMC-P-100-LS-C02 | B97: Life & Style | C97: Child-C | D97: MMC-P-100 | E97: https://www.lifeandstylemag.com/wp-admin/post.php?post=736084&action=edit | F97: https://www.lifeandstylemag.com/posts/the-best-family-friendly-broadways-shows-for-young-kids/ | G97: Lauren Schuster | I97: The Best Broadway Shows for Kids: A Guide to Magical First Theatre Experiences | J97: 5 | K97: 46054 | L97: February | M97: February | N97: 46055 | O97: 46055 | P97: Experiences | Q97: 837 | R97: Broadway, family, kids, musicals | S97: These family-friendly Broadway shows are the perfect way to introduce kids to live theater and enjoy a family outing together | T97: Trend Hunter B2C (The Curious Optimizer) | U97: https://docs.google.com/document/d/1k-wJDjsq7YidLBz_3pVzonslDOvyDgRZV2P-tGgwROU/edit?tab=t.0 | V97: Sara V | AB97: 70 | AC97: 9 | AD97: 9 | AE97: 39 | AF97: 0 | AG97: 0 | AH97: 0 | AI97: 3 | AO97: Theater
A98: LS-P-102 | B98: Life & Style | C98: Parent-P | E98: https://www.lifeandstylemag.com/wp-admin/post.php?post=736464&action=edit | G98: Ryan Brennan | I98: A 4-Foot Snake Killed by a Hiker Turned Out to Be Something Scientists Had Never Seen Before | J98: 5 | K98: 46054 | L98: February | M98: February | N98: 46059 | P98: Discover | Q98: 787 | R98: vine snake, oxybelis inkaterra, bolivia | S98: Scientists surveying wildlife in Bolivia made a shocking discovery after a hiking accident revealed the country’s first Inkaterra vine snake. | T98: Trend Hunter B2C (The Curious Optimizer) | U98: https://docs.google.com/document/d/1wWjnqy9RUISQXvCHYzcfrweHfJwKBMyVxE7Da5CL0c0/edit?tab=t.0 | V98: Hanna W | AJ98: LS-P-102
A99: LS-P-102-MMC-C02 | B99: Mod Moms Club | C99: Child-C | D99: LS-P-102 | E99: https://modmomsclubstg.wpenginepowered.com/wp-admin/post.php?post=337194&action=edit | G99: Ryan Brennan | I99: A Hiker’s Deadly Encounter With a 4-Foot Snake Led to a Rare and Unprecedented Discovery | J99: 5 | K99: 46054 | L99: February | M99: February | N99: 46059 | P99: Discover | Q99: 1066 | R99: vine snake, oxybelis inkaterra, bolivia | S99: A wildlife guide ‘accidentally severed’ a snake in Bolivia—only for it to turn out to be the country’s first recorded Inkaterra vine snake. | T99: General Audience | U99: https://docs.google.com/document/d/1wWjnqy9RUISQXvCHYzcfrweHfJwKBMyVxE7Da5CL0c0/edit?tab=t.0 | V99: Hanna W
A100: LS-P-104 | B100: Life & Style | C100: Parent-P | E100: https://www.lifeandstylemag.com/wp-admin/post.php?post=736506&action=edit | F100: https://www.lifeandstylemag.com/posts/your-free-guide-to-a-clutter-free-home/ | G100: Lauren J-G | I100: Your Free Guide to Having A Clutter Free Home | J100: 5 | K100: 46054 | L100: February | M100: February | N100: 46059 | O100: 46059 | P100: Everyday Life | Q100: 1136 | R100: organizing tips, home, life, lifestyle. clutter-free home, interior design | S100: Learn how to declutter your home for free with simple, realistic steps that reduce stress, create calm, and keep clutter from coming back | T100: General Audience | U100: https://docs.google.com/document/d/1CXe25DT24Krr-v7uN-Evc9p466eWx9d6EFv_gaEa4bo/edit?tab=t.0 | V100: Lauren S | AB100: 152 | AC100: 19 | AD100: 12 | AE100: 71 | AF100: 0 | AG100: 0 | AH100: 0 | AI100: 0 | AJ100: LS-P-104 | AK100: 152 | AO100: Home Improvement
...

Sheet Trends
A1: Week # | B1: Article Hits | C1: Article Misses | D1: Article Hit Rate | E1: Cluster Hits | F1: Cluster Misses | G1: Cluster Hit Rate | H1: Target (1-in-4) | J1: Author | K1: Articles | L1: Avg Weekly Output | M1: Avg PVs | N1: Cluster Diversity | O1: Avg Sim (Desc) | P1: Avg Sim (Body 400w) | Q1: Hit Rate
A2: 6 | B2: 16 | C2: 26 | D2: 0.38095238 | E2: 9 | F2: 12 | G2: 0.42857143 | H2: 0.25 | J2: Hanna WIckes | K2: 4 | L2: 4 | M2: 17529 | N2: 3 | O2: 0.9484 | P2: 0.8653 | Q2: 0.5
A3: 7 | B3: 32 | C3: 70 | D3: 0.31372549 | E3: 17 | F3: 21 | G3: 0.44736842 | H3: 0.25 | J3: Lauren JG | K3: 2 | L3: 2 | M3: 1496 | N3: 2 | Q3: 0.5
A4: 8 | B4: 34 | C4: 88 | D4: 0.27868852 | E4: 19 | F4: 27 | G4: 0.41304348 | H4: 0.25 | J4: Ryan Brennan | K4: 620 | L4: 56.36 | M4: 4190 | N4: 203 | O4: 0.9121 | P4: 0.7267 | Q4: 0.28
A5: 9 | B5: 25 | C5: 112 | D5: 0.18248175 | E5: 11 | F5: 38 | G5: 0.2244898 | H5: 0.25 | J5: Hanna Wickes | K5: 612 | L5: 55.64 | M5: 2818 | N5: 204 | O5: 0.9293 | P5: 0.7609 | Q5: 0.2574
A6: 10 | B6: 32 | C6: 110 | D6: 0.22535211 | E6: 15 | F6: 35 | G6: 0.3 | H6: 0.25 | J6: Samantha Agate | K6: 189 | L6: 47.25 | M6: 995 | N6: 63 | O6: 0.9039 | P6: 0.7929 | Q6: 0.1528
A7: 11 | B7: 36 | C7: 77 | D7: 0.31858407 | E7: 18 | F7: 22 | G7: 0.45 | H7: 0.25 | J7: Allison Palmer | K7: 144 | L7: 18 | M7: 3134 | N7: 50 | O7: 0.9023 | P7: 0.7973 | Q7: 0.1301
A8: 12 | B8: 29 | C8: 136 | D8: 0.17575758 | E8: 21 | F8: 49 | G8: 0.3 | H8: 0.25 | J8: Lauren Schuster | K8: 133 | L8: 12.09 | M8: 649 | N8: 64 | O8: 0.9248 | P8: 0.7891 | Q8: 0.0891
A9: 13 | B9: 36 | C9: 179 | D9: 0.16744186 | E9: 20 | F9: 66 | G9: 0.23255814 | H9: 0.25 | J9: Lauren J-G | K9: 182 | L9: 16.55 | M9: 737 | N9: 70 | O9: 0.8939 | P9: 0.6737 | Q9: 0.0286
A10: 14 | B10: 34 | C10: 181 | D10: 0.15813953 | E10: 21 | F10: 57 | G10: 0.26923077 | H10: 0.25
A11: 15 | B11: 27 | C11: 142 | D11: 0.15976331 | E11: 17 | F11: 43 | G11: 0.28333333 | H11: 0.25

Sheet Ranges
A1: Properties | C1: Content_Type | E1: Content Types | G1: Type of Asset | I1: Author | K1: Smart News
A2: Us Weekly | C2: Parent-P | E2: Explainer | G2: Trend Unit | I2: Hanna Wickes | K2: MSN
A3: Us Weekly Español | C3: Child-C | E3: Everything to Know | G3: Core | I3: Ryan Brennan | K3: Apple
A4: Woman's World | G4: Bridge | I4: Lauren J-G | K4: Newsbreak
A5: Life & Style | G5: Discover | I5: Lauren Schuster | K5: Yahoo!
A6: In Touch | G6: Version | I6: Allison Palmer | K6: Google News
A7: Closer
A8: J-14
A9: Soaps in Depth
A10: First for Women
A11: OK! Magazine
A12: Mod Moms Club
A13: Miami Herald
A14: Kansas City Star
A15: Sacramento Bee
A16: Charlotte Observer
A17: Raleigh N&O
A18: Fort Worth Star-Telegram
... A34: Mirmar

Sheet By Month

Sheet By Author

Sheet By Vertical

Sheet Weeks 2026
A1: Date of week start (Sunday) | B1: Week #
A2: 46026 | B2: 1
A3: 46033 | B3: 2
A4: 46040 | B4: 3
A5: 46047 | B5: 4
A6: 46054 | B6: 5
A7: 46061 | B7: 6
A8: 46068 | B8: 7
A9: 46075 | B9: 8
A10: 46082 | B10: 9
A11: 46089 | B11: 10
A12: 46096 | B12: 11
A13: 46103 | B13: 12
... A53: 46383 | B53: 52

Sheet By Site

Sheet Pivot

Sheet Content Calendar
A1: Month | B1: Target Date | C1: Content Title/Idea | D1: Content Type | E1: Status | F1: Priority | G1: Owner | H1: Peer Reviewer | L1: Vertical | M1: Homebase | N1: Platform | O1: Campaign/Series | P1: SEO Keywords | Q1: Notes
A2: 46054 | B2: 46071 | C2: Condo or Single-Family Home | D2: Article | E2: Published | F2: High | G2: Allison | L2: Everyday Living | M2: Miami | N2: CUE | O2: Homebuyers Guide | Q2: Miami Moving Companies
A3: 46055 | B3: 46072 | C3: Condo or Single-Family Home | D3: Article | E3: Published | F3: High | G3: Allison | L3: Everyday Living | M3: Miami | N3: CUE | O3: Homebuyers Guide | Q3: Miami Security Systems
A4: 46056 | B4: 46071 | C4: KCM Homebuyers Initial Content Plan | D4: Article | E4: Published | F4: High | G4: Allison | K4: https://www.kansascity.com/news/business/home-buyers-guide/article314746910.html | L4: Everyday Living | M4: KC | N4: CUE | O4: Homebuyers Guide | Q4: KC Neighborhoods
A5: 46057 | B5: 46072 | C5: KCM Homebuyers Initial Content Plan | D5: Article | E5: Published | F5: High | G5: Allison | K5: https://www.kansascity.com/news/business/home-buyers-guide/article314749321.html | L5: Everyday Living | M5: KC | N5: CUE | O5: Homebuyers Guide | Q5: KC Condo or Single Family
A6: 46058 | B6: 46073 | C6: KCM Homebuyers Initial Content Plan | D6: Article | E6: Published | F6: High | G6: Allison | K6: https://www.kansascity.com/news/business/home-buyers-guide/article314760348.html | L6: Everyday Living | M6: KC | N6: CUE | O6: Homebuyers Guide | Q6: KC Home Inspections
A7: 46059 | B7: 46071 | C7: KCM Homebuyers Initial Content Plan | D7: Article | E7: Published | F7: High | G7: Allison | K7: https://www.kansascity.com/news/business/home-buyers-guide/article314776069.html | L7: Everyday Living | M7: KC | N7: CUE | O7: Homebuyers Guide | Q7: KC Property Taxes
A8: 46060 | B8: 46072 | C8: KCM Homebuyers Initial Content Plan | D8: Article | E8: Published | F8: High | G8: Allison | K8: https://www.kansascity.com/news/business/home-buyers-guide/article314807018.html | L8: Everyday Living | M8: KC | N8: CUE | O8: Homebuyers Guide | Q8: KC Competitive Offers
A9: 46061 | B9: 46071 | C9: World Cup Guide: Miami | D9: Article | E9: Published | F9: High | G9: Taylor (FL) | K9: https://www.miamiherald.com/sports/fifa-world-cup/article314387069.html | L9: Experiences | M9: Miami | N9: CUE | O9: FIFA | Q9: World Cup Miami: Main
A10: 46062 | B10: 46078 | C10: World Cup Guide: Miami | D10: Article | E10: In Progress | F10: Medium | G10: Taylor (FL) | J10: https://cue.gcp.misitemgr.com/cue-web/#/main?uri=https:%2F%2Fcue.gcp.misitemgr.com%2Fwebservice%2Fescenic%2Fcontent%2F314820016&mimetype=x-ece%2Fstory&extra=%7B%22package%22:%2278cca8ea-79f6-4703-9cb0-143ff11dc5d9%22%7D&name=Florida_s_Largest_Urban_Park_Offers_World_Cup_Visitors_a_Hidden_Escape_Just_Minutes_From_the_Action | K10: https://www.miamiherald.com/sports/fifa-world-cup/article314820016.html | L10: Experiences | M10: Miami | N10: CUE | O10: FIFA | Q10: World Cup Miami: Oleta River State Park
A11: 46063 | B11: 46073 | C11: World Cup Guide: Miami | D11: Article | E11: Published | F11: High | G11: Taylor (FL) | K11: https://www.miamiherald.com/sports/fifa-world-cup/article314760602.html | L11: Experiences | M11: Miami | N11: CUE | O11: FIFA | Q11: World Cup Miami: Aventura Mall
A12: 46064 | B12: 46078 | C12: World Cup Guide: Miami | D12: Article | E12: In Progress | F12: Medium | G12: Taylor (FL) | J12: https://cue.gcp.misitemgr.com/cue-web/#/main?uri=https:%2F%2Fcue.gcp.misitemgr.com%2Fwebservice%2Fescenic%2Fcontent%2F314819835&mimetype=x-ece%2Fstory&extra=%7B%22package%22:%22f7c88ff0-85bc-424f-9b6e-0883c92a21f5%22%7D&name=Gulfstream_Park_Village_Guide_Where_World_Cup_2026_Fans_Can_Keep_the_Celebration_Going | K12: https://www.miamiherald.com/sports/fifa-world-cup/article314819835.html | L12: Experiences | M12: Miami | N12: CUE | O12: FIFA | Q12: World Cup Miami: Gulfstream Park Village
A13: 46065 | B13: 46077 | C13: World Cup Guide: Miami | D13: Article | E13: In Progress | F13: Medium | G13: Taylor (FL) | K13: https://www.miamiherald.com/sports/fifa-world-cup/article314909198.html | L13: Experiences | M13: Miami | N13: CUE | O13: FIFA | Q13: World Cup Miami: Dining Options
A14: 46066 | B14: 46078 | C14: World Cup Guide: Miami | D14: Article | E14: In Progress | F14: Medium | G14: Taylor (FL) | K14: https://www.miamiherald.com/sports/fifa-world-cup/article314909347.html | L14: Experiences | M14: Miami | N14: CUE | O14: FIFA | Q14: World Cup Miami: Rolling Oaks Park
A15: 46067 | B15: 46077 | C15: World Cup Guide: Miami | D15: Article | E15: In Progress | F15: Medium | G15: Taylor (FL) | K15: https://www.miamiherald.com/sports/fifa-world-cup/article314909388.html | L15: Experiences | M15: Miami | N15: CUE | O15: FIFA | Q15: World Cup Miami: Snake Creek Trail
A16: 46068 | B16: 46078 | C16: World Cup Guide: Miami | D16: Article | E16: In Progress | F16: Medium | G16: Taylor (FL) | K16: https://www.miamiherald.com/sports/fifa-world-cup/article314909666.html | L16: Experiences | M16: Miami | N16: CUE | O16: FIFA | Q16: World Cup Miami: Calder Casino
A17: 46068 | B17: 46078 | C17: World Cup Guide: Miami | D17: Article | E17: In Progress | F17: Medium | G17: Taylor (FL) | K17: https://www.miamiherald.com/sports/fifa-world-cup/article314909729.html | L17: Experiences | M17: Miami | N17: CUE | O17: FIFA | Q17: World Cup Miami: Miami Beach
A18: 46069 | B18: 46079 | C18: World Cup Guide: Kansas City | D18: Article | E18: In Progress | F18: Medium | G18: Taylor (FL) | L18: Experiences | M18: KC | N18: CUE | O18: FIFA | Q18: World Cup KC: Mainbar
A19: 46070 | B19: 46079 | C19: World Cup Guide: Kansas City | D19: Article | E19: In Progress | F19: Medium | G19: Taylor (FL) | L19: Experiences | M19: KC | N19: CUE | O19: FIFA | Q19: World Cup KC: FIFA Fest
A20: 46071 | B20: 46078 | C20: World Cup Guide: Kansas City | D20: Article | E20: In Progress | F20: Medium | G20: Taylor (FL) | L20: Experiences | M20: KC | N20: CUE | O20: FIFA | Q20: World Cup KC: Truman Sports Complex
A21: 46072 | B21: 46079 | C21: World Cup Guide: Kansas City | D21: Article | E21: In Progress | F21: Medium | G21: Taylor (FL) | L21: Experiences | M21: KC | N21: CUE | O21: FIFA | Q21: World Cup KC: 18th Vine District
A22: 46073 | B22: 46079 | C22: World Cup Guide: Kansas City | D22: Article | E22: In Progress | F22: Medium | G22: Taylor (FL) | L22: Experiences | M22: KC | N22: CUE | O22: FIFA | Q22: World Cup KC: Zoo
A23: 46074 | B23: 46079 | C23: World Cup Guide: Kansas City | D23: Article | E23: In Progress | F23: Medium | G23: Taylor (FL) | L23: Experiences | M23: KC | N23: CUE | O23: FIFA | Q23: World Cup KC: Boulevard
A24: 46075 | B24: 46080 | C24: World Cup Guide: Kansas City | D24: Article | E24: In Progress | F24: Medium | G24: Taylor (FL) | L24: Experiences | M24: KC | N24: CUE | O24: FIFA | Q24: World Cup KC: Crown Center
A25: 46076 | B25: 46080 | C25: World Cup Guide: Kansas City | D25: Article | E25: In Progress | F25: Medium | G25: Taylor (FL) | L25: Experiences | M25: KC | N25: CUE | O25: FIFA | Q25: World Cup KC: Plaza
A26: 46077 | B26: 46080 | C26: World Cup Guide: Kansas City | D26: Article | E26: In Progress | F26: Medium | G26: Taylor (FL) | L26: Experiences | M26: KC | N26: CUE | O26: FIFA | Q26: World Cup KC: Nelson Atkins
A27: 46078 | B27: 46080 | C27: World Cup Guide: Kansas City | D27: Article | E27: In Progress | F27: Medium | G27: Taylor (FL) | L27: Experiences | M27: KC | N27: CUE | O27: FIFA | Q27: World Cup KC: Worlds of Fun
A28: 46079 | B28: 46079 | C28: World Cup Guide: Kansas City | D28: Article | E28: In Progress | F28: Medium | G28: Taylor (FL) | L28: Experiences | M28: KC | N28: CUE | O28: FIFA | Q28: World Cup KC: Barbecue
A29: 46080 | B29: 46079 | C29: World Cup Guide: Fort Worth | D29: Article | E29: In Progress | F29: Medium | G29: Taylor (FL) | L29: Experiences | M29: FTW | N29: CUE | O29: FIFA | Q29: World Cup FTW: Main
... A42: 46088 | B42: 46090 | C42: World Cup Guide: Bay Area | D42: Article | E42: Approved | F42: Medium | G42: Allison | L42: Experiences | M42: SAC | N42: CUE | O42: FIFA | Q42: World Cup Bay Area: Family Attractions
A43: 46081 | B43: 46080 | C43: What Happens to Your Portfolio If Markets Drop 30% at Retirement? | D43: Article | E43: In Progress | F43: High | N43: CUE
A44: 46081 | B44: 46080 | C44: How to Build an Income Floor That Lasts 30 Years | D44: Article | E44: Published | F44: High | G44: Lauran J-G | H44: SV | I44: https://cue.gcp.misitemgr.com/cue-web/#/main?escenicid=314820042&extra=%7B%22package%22:%22ece-auto-gen-c52c6585-3f62-42e4-b48a-9a64fb1f202c%22%7D&filter=%7B%22searchCriteria%22:%7B%22name%22:%22%22,%22searchTerm%22:%22%22,%22contentType%22:%22%2Fwebservice%2Fescenic%2Fpublication%2Fbnd%2Fmodel%2Fcontent-type%2Fstoryline%22,%22labels%22:%7B%22%2Fwebservice%2Fescenic%2Fpublication%2Fbnd%2Fmodel%2Fcontent-type%2Fstoryline%22:%7B%22title%22:%22Story%22%7D,%22org_unit:8a8f26f5-63f5-11f0-ae19-959fd20885e0%22:%7B%22title%22:%22KansasCity%22%7D,%22%2Fwebservice%2Fescenic%2Fcontent%2Fstate%2Fpublished%22:%7B%22title%22:%22Published%22%7D,%22creationdate%22:%22In%20the%20last%20year%22%7D,%22createdAt%22:%222026-02-24T17:45:40.473Z%22,%22dateRange%22:%7B%22creationdate%22:%7B%22start%22:%222025-02-24T07:00:00Z%22,%22end%22:%222027-02-25T07:00:00Z%22%7D%7D,%22daysBefore%22:%7B%22creationdate%22:%22365%22%7D,%22facetSummary%22:%22Document%20Type:%20Story,%20Time-span%20(creationdate):%20In%20the%20last%20year,%20States:%20Published%22,%22priority%22:-1,%22panelName%22:%22Search%22,%22presentation%22:%22%22,%22sorting%22:%22%22,%22customFilters%22:%5B%5D,%22customFacetStrings%22:%7B%7D,%22state%22:%22%2Fwebservice%2Fescenic%2Fcontent%2Fstate%2Fpublished%22,%22orgUnit%22:%22org_unit:8a8f26f5-63f5-11f0-ae19-959fd20885e0%22%7D%7D | K44: https://www.miamiherald.com/living/article314820042.html | L44: Everyday Living | M44: MIA | N44: CUE | O44: API | P44: retirement income floor, guaranteed income retirement | Q44: Educational | R44: Pillar content. Embed white paper Braze card.
A45: 46081 | B45: 46080 | C45: Is It Too Late to Refinance? What Pre-Retirees Need to Know in 2026 | D45: Article | E45: Published | F45: High | G45: Lauran J-G | H45: CP | I45: https://cue.gcp.misitemgr.com/cue-web/#/main?escenicid=314821467&extra=%7B%22package%22:%22ece-auto-gen-47a3210a-4e56-4c1e-a5fc-5fcb022d51f1%22%7D&filter=%7B%22searchCriteria%22:%7B%22name%22:%22%22,%22searchTerm%22:%22%22,%22labels%22:%7B%22org_unit:8a8f26f5-63f5-11f0-ae19-959fd20885e0%22:%7B%22title%22:%22KansasCity%22%7D,%22creationdate%22:%22In%20the%20last%20year%22%7D,%22createdAt%22:%222026-02-24T18:47:47.404Z%22,%22dateRange%22:%7B%22creationdate%22:%7B%22start%22:%222025-02-24T07:00:00Z%22,%22end%22:%222027-02-25T07:00:00Z%22%7D%7D,%22daysBefore%22:%7B%22creationdate%22:%22365%22%7D,%22facetSummary%22:%22Time-span%20(creationdate):%20In%20the%20last%20year%22,%22priority%22:-1,%22panelName%22:%22Search%22,%22presentation%22:%22%22,%22sorting%22:%22%22,%22customFilters%22:%5B%5D,%22customFacetStrings%22:%7B%7D,%22orgUnit%22:%22org_unit:8a8f26f5-63f5-11f0-ae19-959fd20885e0%22%7D%7D | K45: https://www.miamiherald.com/living/article314821467.html | L45: Everyday Living | M45: MIA | N45: CUE | O45: API | P45: refinancing a house 2026, mortgage refinance pre-retirement | Q45: Decision-Trigger | R45: Timely + evergreen. Surfaces complexity → WP conversion.
A46: 46081 | B46: 46080 | C46: Roth Conversion Strategy: A Step-by-Step Guide for Ages 55–65 | D46: Article | E46: In Progress | F46: High | L46: Everyday Living | M46: MIA | N46: CUE
A47: 46081 | B47: 46080 | C47: The Inflation Risk Most Retirees Are Ignoring | D47: Article | E47: In Progress | F47: High | G47: Lauran J-G | H47: SV | I47: https://cue.gcp.misitemgr.com/cue-web/#/main?escenicid=314823045&extra=%7B%22package%22:%22ece-auto-gen-3a9cbd0f-3685-408c-80e3-2fe256852605%22%7D&filter=%7B%22searchCriteria%22:%7B%22name%22:%22%22,%22searchTerm%22:%22money%22,%22labels%22:%7B%22creationdate%22:%22In%20the%20last%20year%22%7D,%22createdAt%22:%222026-02-24T20:07:02.325Z%22,%22dateRange%22:%7B%22creationdate%22:%7B%22start%22:%222025-02-24T07:00:00Z%22,%22end%22:%222027-02-25T07:00:00Z%22%7D%7D,%22daysBefore%22:%7B%22creationdate%22:%22365%22%7D,%22facetSummary%22:%22Time-span%20(creationdate):%20In%20the%20last%20year%22,%22priority%22:-1,%22panelName%22:%22Search%22,%22presentation%22:%22%22,%22sorting%22:%22%22,%22customFilters%22:%5B%5D,%22customFacetStrings%22:%7B%7D%7D%7D | K47: https://www.miamiherald.com/living/article314823045.html | L47: Everyday Living | M47: MIA | N47: CUE | O47: API | P47: inflation retirement risk, TIPS bonds retirement | Q47: Educational | R47: Pillar content. Pairs with Roth Conversion article for nurture sequence.
A48: 46081 | B48: 46080 | C48: How Much Does Your 401(k) Factor Into Your Mortgage Qualification? | D48: Article | E48: In Progress | F48: High | L48: Everyday Living | M48: MIA | N48: CUE
A49: 46081 | B49: 46080 | C49: HSA Pitfalls That Could Cost You in Retirement | D49: Article | E49: In Progress | F49: High | G49: Lauren S | H49: SV (has CTA) | I49: https://cue.gcp.misitemgr.com/cue-web/#/main?escenicid=314840223&extra=%7B%22package%22:%22ece-auto-gen-52b0740e-cacd-4c31-999f-4c9d3df5bc16%22%7D&filter=%7B%22searchCriteria%22:%7B%22name%22:%22%22,%22searchTerm%22:%22retire%22,%22contentType%22:%22%2Fwebservice%2Fescenic%2Fpublication%2Fbnd%2Fmodel%2Fcontent-type%2Fstoryline%22,%22labels%22:%7B%22%2Fwebservice%2Fescenic%2Fpublication%2Fbnd%2Fmodel%2Fcontent-type%2Fstoryline%22:%7B%22title%22:%22Story%22%7D,%22%2Fwebservice%2Fescenic%2Fcontent%2Fstate%2Fpublished%22:%7B%22title%22:%22Published%22%7D,%22org_unit:8acc2ff9-63f5-11f0-ae19-959fd20885e0%22:%7B%22title%22:%22Miami%22%7D,%22creationdate%22:%22In%20the%20last%20year%22%7D,%22createdAt%22:%222026-02-25T21:27:58.454Z%22,%22dateRange%22:%7B%22creationdate%22:%7B%22start%22:%222025-02-25T05:00:00Z%22,%22end%22:%222027-02-26T05:00:00Z%22%7D%7D,%22daysBefore%22:%7B%22creationdate%22:%22365%22%7D,%22facetSummary%22:%22Document%20Type:%20Story,%20Time-span%20(creationdate):%20In%20the%20last%20year,%20States:%20Published%22,%22priority%22:-1,%22panelName%22:%22Search%22,%22presentation%22:%22%22,%22sorting%22:%22%22,%22customFilters%22:%5B%5D,%22customFacetStrings%22:%7B%7D,%22state%22:%22%2Fwebservice%2Fescenic%2Fcontent%2Fstate%2Fpublished%22,%22orgUnit%22:%22org_unit:8acc2ff9-63f5-11f0-ae19-959fd20885e0%22%7D%7D | K49: https://www.miamiherald.com/living/article314824437.html | L49: Everyday Living | M49: MIA | N49: CUE | O49: API | P49: HSA mistakes, health savings account retirement pitfalls | Q49: Decision-Trigger | R49: High search volume. Emotional hook. Surfaces WP as solution.
A50: 46081 | B50: 46080 | C50: The Triple Tax Advantage: How to Maximize Your HSA Before Retirement | D50: Article | E50: In Progress | F50: High | L50: Everyday Living | M50: MIA | N50: CUE
A51: 46081 | B51: 46080 | C51: 2025 401(k) Contribution Limit Increase: What It Means for Your Retirement Timeline | D51: Article | E51: In Progress | F51: High | L51: Everyday Living | M51: MIA | N51: CUE
A52: 46081 | B52: 46080 | C52: How to Choose the Best Financial Planner for Pre-Retirement | D52: Article | E52: Published | F52: High | G52: Lauren S | H52: SV (has CTA) | I52: https://cue.gcp.misitemgr.com/cue-web/#/main?escenicid=314835931&extra=%7B%22package%22:%22ece-auto-gen-22c16a41-010f-4e80-a72a-32f8fa36e3a3%22%7D&filter=%7B%22searchCriteria%22:%7B%22name%22:%22%22,%22searchTerm%22:%22%22,%22contentType%22:%22%2Fwebservice%2Fescenic%2Fpublication%2Fbnd%2Fmodel%2Fcontent-type%2Fstoryline%22,%22labels%22:%7B%22%2Fwebservice%2Fescenic%2Fpublication%2Fbnd%2Fmodel%2Fcontent-type%2Fstoryline%22:%7B%22title%22:%22Story%22%7D,%22%2Fwebservice%2Fescenic%2Fcontent%2Fstate%2Fpublished%22:%7B%22title%22:%22Published%22%7D,%22org_unit:8acc2ff9-63f5-11f0-ae19-959fd20885e0%22:%7B%22title%22:%22Miami%22%7D,%22%2Fwebservice%2Fescenic%2Fsection%2F102662%22:%7B%22pathInfo%22:%22mia-tab%22,%22title%22:%22Business%22%7D,%22creationdate%22:%22In%20the%20last%20year%22%7D,%22createdAt%22:%222026-02-25T19:29:49.051Z%22,%22dateRange%22:%7B%22creationdate%22:%7B%22start%22:%222025-02-25T05:00:00Z%22,%22end%22:%222027-02-26T05:00:00Z%22%7D%7D,%22daysBefore%22:%7B%22creationdate%22:%22365%22%7D,%22facetSummary%22:%22Document%20Type:%20Story,%20Time-span%20(creationdate):%20In%20the%20last%20year,%20States:%20Published,%20Sections:%20Business%22,%22priority%22:-1,%22panelName%22:%22Search%22,%22presentation%22:%22%22,%22sorting%22:%22%22,%22customFilters%22:%5B%5D,%22customFacetStrings%22:%7B%7D,%22state%22:%22%2Fwebservice%2Fescenic%2Fcontent%2Fstate%2Fpublished%22,%22sections%22:%22%2Fwebservice%2Fescenic%2Fsection%2F102662%22,%22orgUnit%22:%22org_unit:8acc2ff9-63f5-11f0-ae19-959fd20885e0%22%7D%7D | J52: https://www.womansworld.com/life/money/how-to-find-the-right-financial-planner-when-retirement-is-around-the-corner | K52: https://www.miamiherald.com/living/article314835931.html | L52: Everyday Living | M52: MIA/WW | N52: CUE | O52: API | P52: best financial planners for retirement, how to choose financial advisor | Q52: Educational | R52: High commercial intent. Fisher Investments brand alignment opportunity.
A53: 46081 | B53: 46080 | C53: What Your 401(k) Can (and Can't) Do for Your Retirement Income | D53: Article | E53: Published | F53: High | G53: Lauren S | H53: SV (has CTA) | I53: https://cue.gcp.misitemgr.com/cue-web/#/main?escenicid=314824277&extra=%7B%22package%22:%22ece-auto-gen-df6ab75a-4f6d-4ddf-aba3-a2d04f0e4ce3%22%7D&filter=%7B%22searchCriteria%22:%7B%22name%22:%22%22,%22searchTerm%22:%22%22,%22contentType%22:%22%2Fwebservice%2Fescenic%2Fpublication%2Fbnd%2Fmodel%2Fcontent-type%2Fstoryline%22,%22labels%22:%7B%22%2Fwebservice%2Fescenic%2Fpublication%2Fbnd%2Fmodel%2Fcontent-type%2Fstoryline%22:%7B%22title%22:%22Story%22%7D,%22org_unit:8acc2ff9-63f5-11f0-ae19-959fd20885e0%22:%7B%22title%22:%22Miami%22%7D,%22%2Fwebservice%2Fescenic%2Fcontent%2Fstate%2Fpublished%22:%7B%22title%22:%22Published%22%7D,%22creationdate%22:%22In%20the%20last%20year%22%7D,%22createdAt%22:%222026-02-24T21:19:44.392Z%22,%22dateRange%22:%7B%22creationdate%22:%7B%22start%22:%222025-02-24T05:00:00Z%22,%22end%22:%222027-02-25T05:00:00Z%22%7D%7D,%22daysBefore%22:%7B%22creationdate%22:%22365%22%7D,%22facetSummary%22:%22Document%20Type:%20Story,%20Time-span%20(creationdate):%20In%20the%20last%20year,%20States:%20Published%22,%22priority%22:-1,%22panelName%22:%22Search%22,%22presentation%22:%22%22,%22sorting%22:%22%22,%22customFilters%22:%5B%5D,%22customFacetStrings%22:%7B%7D,%22state%22:%22%2Fwebservice%2Fescenic%2Fcontent%2Fstate%2Fpublished%22,%22orgUnit%22:%22org_unit:8acc2ff9-63f5-11f0-ae19-959fd20885e0%22%7D%7D | K53: https://www.miamiherald.com/living/article314824277.html | L53: Everyday Living | M53: MIA | N53: CUE | O53: API | P53: 401k retirement income, 401k withdrawal strategy | Q53: Educational | R53: TIER 2 LAUNCH. Repurpose Tier 1 learnings. Watch CPL vs. Tier 1.
A54: 46081 | B54: 46080 | C54: Should You Pay Off Your Mortgage Before Retiring? A Pre-Retiree's Decision Guide | D54: Article | E54: Published | F54: High | G54: Lauren S | H54: SV | I54: https://cue.gcp.misitemgr.com/cue-web/#/main?escenicid=314821839&extra=%7B%22package%22:%22ece-auto-gen-eb111972-e99b-4db3-9f62-e4d2a883ced6%22%7D&filter=%7B%22searchCriteria%22:%7B%22name%22:%22%22,%22searchTerm%22:%22%22,%22contentType%22:%22%2Fwebservice%2Fescenic%2Fpublication%2Fbnd%2Fmodel%2Fcontent-type%2Fstoryline%22,%22labels%22:%7B%22%2Fwebservice%2Fescenic%2Fpublication%2Fbnd%2Fmodel%2Fcontent-type%2Fstoryline%22:%7B%22title%22:%22Story%22%7D,%22%2Fwebservice%2Fescenic%2Fcontent%2Fstate%2Fpublished%22:%7B%22title%22:%22Published%22%7D,%22org_unit:8acc2ff9-63f5-11f0-ae19-959fd20885e0%22:%7B%22title%22:%22Miami%22%7D,%22%2Fwebservice%2Fescenic%2Fsection%2F4990%22:%7B%22pathInfo%22:%22miamiherald%22,%22title%22:%22Living%22%7D,%22creationdate%22:%22In%20the%20last%20year%22%7D,%22createdAt%22:%222026-02-24T18:23:44.986Z%22,%22dateRange%22:%7B%22creationdate%22:%7B%22start%22:%222025-02-24T05:00:00Z%22,%22end%22:%222027-02-25T05:00:00Z%22%7D%7D,%22daysBefore%22:%7B%22creationdate%22:%22365%22%7D,%22facetSummary%22:%22Document%20Type:%20Story,%20Time-span%20(creationdate):%20In%20the%20last%20year,%20States:%20Published,%20Sections:%20Living%22,%22priority%22:-1,%22panelName%22:%22Search%22,%22presentation%22:%22%22,%22sorting%22:%22%22,%22customFilters%22:%5B%5D,%22customFacetStrings%22:%7B%7D,%22state%22:%22%2Fwebservice%2Fescenic%2Fcontent%2Fstate%2Fpublished%22,%22sections%22:%22%2Fwebservice%2Fescenic%2Fsection%2F4990%22,%22orgUnit%22:%22org_unit:8acc2ff9-63f5-11f0-ae19-959fd20885e0%22%7D%7D | K54: https://www.miamiherald.com/living/article314821839.html | L54: Everyday Living | M54: MIA | N54: CUE | O54: API | P54: pay off mortgage before retirement, mortgage retirement decision | Q54: Decision-Trigger | R54: Strong emotional resonance. Surfaces financial complexity for WP.
A55: 46081 | B55: 46080 | C55: HSA vs. FSA in Retirement: Which One Actually Helps You More? | D55: Article | E55: Published | F55: High | G55: Lauran J-G | H55: SV (has CTA) | I55: https://cue.gcp.misitemgr.com/cue-web/#/main?escenicid=314824437&extra=%7B%22package%22:%22ece-auto-gen-d2b38abb-b9a4-4378-9a8c-e3a9a353c947%22%7D&filter=%7B%22searchCriteria%22:%7B%22name%22:%22%22,%22searchTerm%22:%22money%22,%22contentType%22:%22%2Fwebservice%2Fescenic%2Fpublication%2Fbnd%2Fmodel%2Fcontent-type%2Fstoryline%22,%22labels%22:%7B%22%2Fwebservice%2Fescenic%2Fcontent%2Fstate%2Fpublished%22:%7B%22title%22:%22Published%22%7D,%22org_unit:8a8f26f5-63f5-11f0-ae19-959fd20885e0%22:%7B%22title%22:%22KansasCity%22%7D,%22%2Fwebservice%2Fescenic%2Fpublication%2Fbnd%2Fmodel%2Fcontent-type%2Fstoryline%22:%7B%22title%22:%22Story%22%7D,%22creationdate%22:%22In%20the%20last%20year%22%7D,%22createdAt%22:%222026-02-25T19:30:10.602Z%22,%22dateRange%22:%7B%22creationdate%22:%7B%22start%22:%222025-02-25T07:00:00Z%22,%22end%22:%222027-02-26T07:00:00Z%22%7D%7D,%22daysBefore%22:%7B%22creationdate%22:%22365%22%7D,%22facetSummary%22:%22Document%20Type:%20Story,%20Time-span%20(creationdate):%20In%20the%20last%20year,%20States:%20Published%22,%22priority%22:-1,%22panelName%22:%22Search%22,%22presentation%22:%22%22,%22sorting%22:%22%22,%22customFilters%22:%5B%5D,%22customFacetStrings%22:%7B%7D,%22state%22:%22%2Fwebservice%2Fescenic%2Fcontent%2Fstate%2Fpublished%22,%22orgUnit%22:%22org_unit:8a8f26f5-63f5-11f0-ae19-959fd20885e0%22%7D%7D | K55: https://www.miamiherald.com/living/article314824437.html | L55: Everyday Living | M55: MIA/WW | N55: CUE | O55: API | P55: HSA vs FSA retirement, flexible spending account retirement | Q55: Educational | R55: Evergreen. Strong search volume. Completes HSA content cluster.
A56: 46081 | B56: 46080 | C56: The 3 Ingredients Every Woman 50+ Needs in Her Skincare Routine | D56: Article | E56: In Progress | F56: High | G56: Allison | N56: CUE
A57: 46081 | B57: 46080 | C57: Retinol vs. Retinoid vs. Retinaldehyde: A Clear, No-Jargon Guide | D57: Article | E57: Approved | F57: High | G57: Allison | H57: SV | I57: https://cue.gcp.misitemgr.com/cue-web/#/main?escenicid=314819881&extra=%7B%22package%22:%22ece-auto-gen-03aedcca-77bd-4be4-b227-125199c0c902%22%7D | J57: https://www.womansworld.com/wp-admin/post.php?post=607374&action=edit | K57: https://www.miamiherald.com/living/wellness/article314819881.htmlhttps://www.miamiherald.com/living/wellness/article314819881.html | L57: Mindbody | M57: WW | N57: CUE | O57: API | P57: retinol vs retinoid, retinaldehyde skincare | Q57: Educational | R57: Premium Skincare
A58: 46081 | B58: 46080 | C58: How to Build a Skincare Routine That Actually Works After 50 | D58: Article | E58: Approved | F58: High | G58: Allison | H58: SV | I58: https://cue.gcp.misitemgr.com/cue-web/#/main?escenicid=314820213&extra=%7B%22package%22:%22ece-auto-gen-dd7f925b-587c-445d-962b-b1ac5ee3dc69%22%7D | J58: https://www.womansworld.com/beauty/skin/how-to-build-a-skincare-routine-that-actually-works-after-50 | K58: https://www.miamiherald.com/living/wellness/article314820213.html | L58: Mindbody | M58: WW | N58: CUE | O58: API | P58: skincare routine over 50, anti-aging skincare routine | Q58: How-To Guide | R58: Premium Skincare
A59: 46081 | B59: 46080 | C59: Best Retinol Serums for Aging Skin: Tested & Ranked Under $100 | D59: Article | E59: Published | F59: High | G59: Allison | H59: Has products but need swaps for Amazon | I59: https://www.womansworld.com/wp-admin/post.php?post=607252&action=edit | K59: https://www.womansworld.com/beauty/skin/best-retinol-products-for-mature-skin-moisturizers-serums-more | L59: Mindbody | M59: WW | N59: CUE | O59: API | P59: best retinol serums, retinol serum for aging skin | Q59: Commerce Guide | R59: Premium Skincare
A60: 46081 | B60: 46080 | C60: Collagen After 45: What the Science Actually Says | D60: Article | E60: In Progress | F60: High | G60: Allison | M60: WW | N60: CUE | O60: API
A61: 46081 | B61: 46080 | C61: The Truth About Hair Thinning After 50 (And What to Do About It) | D61: Article | E61: Published | F61: High | G61: Allison | H61: Products added | I61: https://www.womansworld.com/wp-admin/post.php?post=607448&action=edit | L61: Mindbody | M61: WW | N61: CUE | O61: API | P61: hair thinning after 50, hair loss menopause | Q61: How-To Guide | R61: Haircare
A62: 46081 | B62: 46080 | C62: The Dirty Dozen: Skincare Ingredients to Avoid After 50 | D62: Article | E62: Published | F62: High | G62: Allison | H62: Products added | I62: https://www.womansworld.com/wp-admin/post.php?post=607404&action=edit | L62: Mindbody | M62: WW | N62: CUE | O62: API | P62: toxic skincare ingredients, ingredients to avoid skincare | Q62: Educational | R62: Clean Beauty
A63: 46081 | B63: 46080 | C63: 5-Minute Makeup for Mature Skin: A Step-by-Step Morning Routine | D63: Article | E63: Published | F63: High | G63: Allison | H63: SV, Products added | I63: https://www.womansworld.com/wp-admin/post.php?post=607466&action=edit | K63: https://www.womansworld.com/beauty/skin/your-5-minute-makeup-routine-after-50-that-actually-works-better-than-your-old-one | L63: Mindbody | M63: WW | N63: CUE | O63: API | P63: makeup for mature skin, 5 minute makeup over 50 | Q63: How-To Guide | R63: Premium Skincare
A64: 46081 | B64: 46080 | C64: Is 'Natural' Really Better? A Dermatologist's Honest Answer | D64: Article | E64: In Progress | F64: High | G64: Allison | M64: WW | N64: CUE | O64: API
A65: 46081 | B65: 46080 | C65: Best Shampoos for Fine, Thinning Hair: What Actually Works | D65: Article | E65: Published | F65: High | G65: Allison | H65: SV, Products added | I65: https://www.womansworld.com/wp-admin/post.php?post=607506&action=edit | K65: https://www.womansworld.com/beauty/hair/the-best-shampoos-for-thinning-hair-these-5-formulas-actually-deliver | L65: Mindbody | M65: WW | N65: CUE | O65: API | P65: best shampoo for thinning hair, shampoo for fine hair women | Q65: Commerce Guide | R65: Haircare
A66: 46081 | B66: 46080 | C66: Purple Shampoo for Gray Hair: How to Use It Without Mistakes | D66: Article | E66: In Progress | F66: High | G66: Allison | M66: WW | N66: CUE | O66: API
A67: 46081 | B67: 46080 | C67: How to Read a Skincare Label: Greenwashing vs. Genuinely Clean | D67: Article | E67: Published | F67: High | G67: Allison | H67: SV, Products added | I67: https://www.womansworld.com/wp-admin/post.php?post=607562&action=edit | K67: https://www.womansworld.com/beauty/how-to-read-a-skincare-label-clean-beauty-greenwashing | L67: Mindbody | M67: WW | N67: CUE | O67: API | P67: how to read skincare ingredients, greenwashing skincare | Q67: How-To Guide | R67: Clean Beauty
A68: 46081 | B68: 46080 | C68: EWG Verified Products That Actually Deliver Results: 2025 Guide | D68: Article | E68: In Progress | F68: High | N68: CUE
A69: 46081 | B69: 46080 | C69: Top Eye Creams for Fine Lines & Puffiness: Ranked by Real Results | D69: Article | E69: In Progress | F69: High | N69: CUE
A70: 46081 | B70: 46080 | C70: K18 vs. Olaplex: Which Hair Bond Treatment Is Worth It? | D70: Article | E70: In Progress | F70: High | N70: CUE
A71: 46081 | B71: 46080 | C71: Clean Beauty Gift Guide: Products That Actually Work (Q4 2025) | D71: Article | E71: In Progress | F71: High | N71: CUE
A72: 46082 | B72: 46093 | C72: Hair Texture 101 and what the means for your thinning hair (KW: Hair Types) | D72: Article | E72: In Progress | F72: High | G72: Allison | I72: https://www.womansworld.com/beauty/hair/hair-thinning-your-hair-texture-is-a-key-factor-heres-what-to-look-for | J72: https://cue.gcp.misitemgr.com/cue-web/#/main?escenicid=315011131&extra=%7B%22package%22:%22ece-auto-gen-2970879b-9913-4812-8434-d2ff9b2b847d%22%7D&filter=%7B%22searchCriteria%22:%7B%22name%22:%22%22,%22searchTerm%22:%22beauty%22,%22labels%22:%7B%22creationdate%22:%22From%2003%2F11%2F2025%20to%2003%2F12%2F2027%22%7D,%22createdAt%22:%222026-03-11T15:05:42.115Z%22,%22dateRange%22:%7B%22creationdate%22:%7B%22start%22:%222025-03-11T04:00:00Z%22,%22end%22:%222027-03-12T05:00:00Z%22%7D%7D,%22daysBefore%22:%7B%22creationdate%22:%22365%22%7D,%22facetSummary%22:%22Time-span%20(creationdate):%20From%2003%2F11%2F2025%20to%2003%2F12%2F2027%22,%22priority%22:-1,%22panelName%22:%22Search%22,%22presentation%22:%22%22,%22sorting%22:%22%22,%22customFilters%22:%5B%5D,%22customFacetStrings%22:%7B%7D%7D%7D | K72: https://cue.gcp.misitemgr.com/cue-web/#/main?escenicid=315010715&extra=%7B%22package%22:%22ece-auto-gen-28793f69-2d6a-43ec-ae15-846be53cd623%22%7D&filter=%7B%22searchCriteria%22:%7B%22name%22:%22%22,%22searchTerm%22:%22beauty%22,%22labels%22:%7B%22creationdate%22:%22In%20the%20last%20year%22%7D,%22createdAt%22:%222026-03-11T14:31:01.823Z%22,%22dateRange%22:%7B%22creationdate%22:%7B%22start%22:%222025-03-11T04:00:00Z%22,%22end%22:%222027-03-12T05:00:00Z%22%7D%7D,%22daysBefore%22:%7B%22creationdate%22:%22365%22%7D,%22facetSummary%22:%22Time-span%20(creationdate):%20In%20the%20last%20year%22,%22priority%22:-1,%22panelName%22:%22Search%22,%22presentation%22:%22%22,%22sorting%22:%22%22,%22customFilters%22:%5B%5D,%22customFacetStrings%22:%7B%7D%7D%7D | N72: CUE | O72: API
A73: 46082 | B73: 46093 | C73: What Is A Roth IRA? How They Work, How To Open One (KW: Roth IRA) | D73: Article | E73: In Progress | F73: High | G73: Allison | I73: https://www.miamiherald.com/news/business/retirement-planning/article315012235.html | J73: https://www.star-telegram.com/entertainment/living/article315013065.html | K73: https://www.kansascity.com/living/article315013958.html | N73: CUE | O73: API
A74: 46082 | B74: 46093 | C74: Best Thinning Hair Products (KW: Thin Hair) | D74: Article | E74: In Progress | F74: High | G74: Lauran J-G | I74: ww:https://www.womansworld.com/wp-admin/post.php?post=609800&action=edit | J74: KCM: https://cue.gcp.misitemgr.com/cue-web/#/main?escenicid=315014313&extra=%7B%22package%22:%22ece-auto-gen-77620243-d465-4b83-881d-02ba821b50ae%22%7D&filter=%7B%22searchCriteria%22:%7B%22name%22:%22%22,%22searchTerm%22:%22lauren%22,%22contentType%22:%22%2Fwebservice%2Fescenic%2Fpublication%2Fbnd%2Fmodel%2Fcontent-type%2Fstoryline%22,%22labels%22:%7B%22%2Fwebservice%2Fescenic%2Fpublication%2Fbnd%2Fmodel%2Fcontent-type%2Fstoryline%22:%7B%22title%22:%22Story%22%7D,%22%2Fwebservice%2Fescenic%2Fcontent%2Fstate%2Fpublished%22:%7B%22title%22:%22Published%22%7D,%22org_unit:8a8f26f5-63f5-11f0-ae19-959fd20885e0%22:%7B%22title%22:%22KansasCity%22%7D,%22creationdate%22:%22In%20the%20last%20year%22%7D,%22createdAt%22:%222026-03-11T17:49:24.116Z%22,%22dateRange%22:%7B%22creationdate%22:%7B%22start%22:%222025-03-10T06:00:00Z%22,%22end%22:%222027-03-11T07:00:00Z%22%7D%7D,%22daysBefore%22:%7B%22creationdate%22:%22365%22%7D,%22facetSummary%22:%22Document%20Type:%20Story,%20Time-span%20(creationdate):%20In%20the%20last%20year,%20States:%20Published%22,%22priority%22:-1,%22panelName%22:%22Search%22,%22presentation%22:%22%22,%22sorting%22:%22%22,%22customFilters%22:%5B%5D,%22customFacetStrings%22:%7B%7D,%22state%22:%22%2Fwebservice%2Fescenic%2Fcontent%2Fstate%2Fpublished%22,%22orgUnit%22:%22org_unit:8a8f26f5-63f5-11f0-ae19-959fd20885e0%22%7D%7D | K74: MIA: https://cue.gcp.misitemgr.com/cue-web/#/main?escenicid=314998168&extra=%7B%22package%22:%22ece-auto-gen-b400a833-09ea-4854-b2f7-7c3e2ee7a30b%22%7D&filter=%7B%22searchCriteria%22:%7B%22name%22:%22%22,%22searchTerm%22:%22%22,%22contentType%22:%22%2Fwebservice%2Fescenic%2Fpublication%2Fbnd%2Fmodel%2Fcontent-type%2Fpicture%22,%22labels%22:%7B%22org_unit:8a8f26f5-63f5-11f0-ae19-959fd20885e0%22:%7B%22title%22:%22KansasCity%22%7D,%22%2Fwebservice%2Fescenic%2Fpublication%2Fbnd%2Fmodel%2Fcontent-type%2Fpicture%22:%7B%22title%22:%22Photo%22%7D,%22creationdate%22:%22In%20the%20last%20year%22%7D,%22createdAt%22:%222026-03-10T17:41:57.403Z%22,%22dateRange%22:%7B%22creationdate%22:%7B%22start%22:%222025-03-10T06:00:00Z%22,%22end%22:%222027-03-11T07:00:00Z%22%7D%7D,%22daysBefore%22:%7B%22creationdate%22:%22365%22%7D,%22facetSummary%22:%22Document%20Type:%20Photo,%20Time-span%20(creationdate):%20In%20the%20last%20year%22,%22priority%22:-1,%22panelName%22:%22Search%22,%22presentation%22:%22%22,%22sorting%22:%22%22,%22customFilters%22:%5B%5D,%22customFacetStrings%22:%7B%7D,%22orgUnit%22:%22org_unit:8a8f26f5-63f5-11f0-ae19-959fd20885e0%22%7D%7D | L74: Mindbody | M74: WW | N74: CUE | O74: API
A75: 46082 | B75: 46093 | C75: What are some tax tips for retirement? (KW: Income Tax) | D75: Article | E75: In Progress | F75: High | G75: Lauran J-G | I75: FW: https://cue.gcp.misitemgr.com/cue-web/#/main?escenicid=315102013&extra=%7B%22package%22:%22ece-auto-gen-d9309a88-1560-4679-97ed-1677b44843cc%22%7D&filter=%7B%22searchCriteria%22:%7B%22name%22:%22%22,%22searchTerm%22:%22%22,%22contentType%22:%22%2Fwebservice%2Fescenic%2Fpublication%2Fbnd%2Fmodel%2Fcontent-type%2Fstoryline%22,%22labels%22:%7B%22%2Fwebservice%2Fescenic%2Fpublication%2Fbnd%2Fmodel%2Fcontent-type%2Fstoryline%22:%7B%22title%22:%22Story%22%7D,%22org_unit:8a8f26f5-63f5-11f0-ae19-959fd20885e0%22:%7B%22title%22:%22KansasCity%22%7D,%22%2Fwebservice%2Fescenic%2Fcontent%2Fstate%2Fpublished%22:%7B%22title%22:%22Published%22%7D,%22creationdate%22:%22In%20the%20last%20year%22%7D,%22createdAt%22:%222026-03-18T17:26:44.598Z%22,%22dateRange%22:%7B%22creationdate%22:%7B%22start%22:%222025-03-17T06:00:00Z%22,%22end%22:%222027-03-18T06:00:00Z%22%7D%7D,%22daysBefore%22:%7B%22creationdate%22:%22365%22%7D,%22facetSummary%22:%22Document%20Type:%20Story,%20Time-span%20(creationdate):%20In%20the%20last%20year,%20States:%20Published%22,%22priority%22:-1,%22panelName%22:%22Search%22,%22presentation%22:%22%22,%22sorting%22:%22%22,%22customFilters%22:%5B%5D,%22customFacetStrings%22:%7B%7D,%22state%22:%22%2Fwebservice%2Fescenic%2Fcontent%2Fstate%2Fpublished%22,%22orgUnit%22:%22org_unit:8a8f26f5-63f5-11f0-ae19-959fd20885e0%22%7D%7D | J75: KCM: https://cue.gcp.misitemgr.com/cue-web/#/main?escenicid=315100301&extra=%7B%22package%22:%22ece-auto-gen-dfee5429-5e62-4091-8eec-788a550920d3%22%7D&filter=%7B%22searchCriteria%22:%7B%22name%22:%22%22,%22searchTerm%22:%22%22,%22contentType%22:%22%2Fwebservice%2Fescenic%2Fpublication%2Fbnd%2Fmodel%2Fcontent-type%2Fstoryline%22,%22labels%22:%7B%22%2Fwebservice%2Fescenic%2Fpublication%2Fbnd%2Fmodel%2Fcontent-type%2Fstoryline%22:%7B%22title%22:%22Story%22%7D,%22%2Fwebservice%2Fescenic%2Fcontent%2Fstate%2Fpublished%22:%7B%22title%22:%22Published%22%7D,%22org_unit:8a8f26f5-63f5-11f0-ae19-959fd20885e0%22:%7B%22title%22:%22KansasCity%22%7D,%22creationdate%22:%22In%20the%20last%20year%22%7D,%22createdAt%22:%222026-03-18T15:44:12.604Z%22,%22dateRange%22:%7B%22creationdate%22:%7B%22start%22:%222025-03-18T06:00:00Z%22,%22end%22:%222027-03-19T06:00:00Z%22%7D%7D,%22daysBefore%22:%7B%22creationdate%22:%22365%22%7D,%22facetSummary%22:%22Document%20Type:%20Story,%20Time-span%20(creationdate):%20In%20the%20last%20year,%20States:%20Published%22,%22priority%22:-1,%22panelName%22:%22Search%22,%22presentation%22:%22%22,%22sorting%22:%22%22,%22customFilters%22:%5B%5D,%22customFacetStrings%22:%7B%7D,%22state%22:%22%2Fwebservice%2Fescenic%2Fcontent%2Fstate%2Fpublished%22,%22orgUnit%22:%22org_unit:8a8f26f5-63f5-11f0-ae19-959fd20885e0%22%7D%7D | K75: MIA: https://cue.gcp.misitemgr.com/cue-web/#/main?escenicid=315089741&extra=%7B%22package%22:%22ece-auto-gen-3f374a4c-967a-413d-8f71-0c7c0507e400%22%7D&filter=%7B%22searchCriteria%22:%7B%22name%22:%22%22,%22searchTerm%22:%22%22,%22labels%22:%7B%22%2Fwebservice%2Fescenic%2Fcontent%2Fstate%2Fpublished%22:%7B%22title%22:%22Published%22%7D,%22org_unit:8a8f26f5-63f5-11f0-ae19-959fd20885e0%22:%7B%22title%22:%22KansasCity%22%7D,%22creationdate%22:%22In%20the%20last%20year%22%7D,%22createdAt%22:%222026-03-17T19:56:28.105Z%22,%22dateRange%22:%7B%22creationdate%22:%7B%22start%22:%222025-03-17T06:00:00Z%22,%22end%22:%222027-03-18T06:00:00Z%22%7D%7D,%22daysBefore%22:%7B%22creationdate%22:%22365%22%7D,%22facetSummary%22:%22Time-span%20(creationdate):%20In%20the%20last%20year,%20States:%20Published%22,%22priority%22:-1,%22panelName%22:%22Search%22,%22presentation%22:%22%22,%22sorting%22:%22%22,%22customFilters%22:%5B%5D,%22customFacetStrings%22:%7B%7D,%22state%22:%22%2Fwebservice%2Fescenic%2Fcontent%2Fstate%2Fpublished%22,%22orgUnit%22:%22org_unit:8a8f26f5-63f5-11f0-ae19-959fd20885e0%22%7D%7D | L75: Everyday Living | N75: CUE | O75: API
A76: 46082 | B76: 46093 | C76: Best Anti-Aging Creams that Are Cost-Effective (KW: Anti Aging) | D76: Article | E76: In Progress | F76: High | G76: Lauran J-G | I76: ww:https://www.womansworld.com/wp-admin/post.php?post=609856&action=edit | J76: KCM: https://cue.gcp.misitemgr.com/cue-web/#/main?escenicid=315011740&extra=%7B%22package%22:%22ece-auto-gen-facd6046-42d6-4868-be47-5c998e9e99a0%22%7D&filter=%7B%22searchCriteria%22:%7B%22name%22:%22%22,%22searchTerm%22:%22%22,%22labels%22:%7B%22org_unit:8a8f26f5-63f5-11f0-ae19-959fd20885e0%22:%7B%22title%22:%22KansasCity%22%7D,%22creationdate%22:%22In%20the%20last%20year%22%7D,%22createdAt%22:%222026-03-11T15:55:33.926Z%22,%22dateRange%22:%7B%22creationdate%22:%7B%22start%22:%222025-03-11T06:00:00Z%22,%22end%22:%222027-03-12T07:00:00Z%22%7D%7D,%22daysBefore%22:%7B%22creationdate%22:%22365%22%7D,%22facetSummary%22:%22Time-span%20(creationdate):%20In%20the%20last%20year%22,%22priority%22:-1,%22panelName%22:%22Search%22,%22presentation%22:%22%22,%22sorting%22:%22%22,%22customFilters%22:%5B%5D,%22customFacetStrings%22:%7B%7D,%22orgUnit%22:%22org_unit:8a8f26f5-63f5-11f0-ae19-959fd20885e0%22%7D%7D | K76: MIA: https://cue.gcp.misitemgr.com/cue-web/#/main?escenicid=315000509&extra=%7B%22package%22:%22ece-auto-gen-91dbd7a1-f67b-43ed-a4b6-ad0c4b8063fe%22%7D&filter=%7B%22searchCriteria%22:%7B%22name%22:%22%22,%22searchTerm%22:%22%22,%22contentType%22:%22%2Fwebservice%2Fescenic%2Fpublication%2Fbnd%2Fmodel%2Fcontent-type%2Fstoryline%22,%22labels%22:%7B%22%2Fwebservice%2Fescenic%2Fpublication%2Fbnd%2Fmodel%2Fcontent-type%2Fstoryline%22:%7B%22title%22:%22Story%22%7D,%22%2Fwebservice%2Fescenic%2Fcontent%2Fstate%2Fpublished%22:%7B%22title%22:%22Published%22%7D,%22org_unit:8a8f26f5-63f5-11f0-ae19-959fd20885e0%22:%7B%22title%22:%22KansasCity%22%7D,%22creationdate%22:%22In%20the%20last%20year%22%7D,%22createdAt%22:%222026-03-10T20:54:15.375Z%22,%22dateRange%22:%7B%22creationdate%22:%7B%22start%22:%222025-03-10T06:00:00Z%22,%22end%22:%222027-03-11T07:00:00Z%22%7D%7D,%22daysBefore%22:%7B%22creationdate%22:%22365%22%7D,%22facetSummary%22:%22Document%20Type:%20Story,%20Time-span%20(creationdate):%20In%20the%20last%20year,%20States:%20Published%22,%22priority%22:-1,%22panelName%22:%22Search%22,%22presentation%22:%22%22,%22sorting%22:%22%22,%22customFilters%22:%5B%5D,%22customFacetStrings%22:%7B%7D,%22state%22:%22%2Fwebservice%2Fescenic%2Fcontent%2Fstate%2Fpublished%22,%22orgUnit%22:%22org_unit:8a8f26f5-63f5-11f0-ae19-959fd20885e0%22%7D%7D | L76: Everyday Living | N76: CUE | O76: API
A77: 46082 | B77: 46093 | C77: What to know if you're considering a hair regrowth treatment (KW: Hair Growth) | D77: Article | E77: In Progress | F77: High | G77: Lauren S | I77: ww: https://www.womansworld.com/wp-admin/post.php?post=610216&action=edit | J77: mia: https://cue.gcp.misitemgr.com/cue-web/#/main?uri=https:%2F%2Fcue.gcp.misitemgr.com%2Fwebservice%2Fescenic%2Fcontainer%2F5bc6641a-22fb-11f1-8a30-d996080f151c&mimetype=x-ece%2Fcontainer&extra=%7B%22package%22:%22ece-auto-gen-17e2968c-cd87-4373-b5fd-1b327eb57002%22%7D&filter=%7B%22searchCriteria%22:%7B%22name%22:%22%22,%22searchTerm%22:%22%22,%22contentType%22:%22%2Fwebservice%2Fescenic%2Fpublication%2Fbnd%2Fmodel%2Fcontent-type%2Fstoryline%22,%22labels%22:%7B%22%2Fwebservice%2Fescenic%2Fpublication%2Fbnd%2Fmodel%2Fcontent-type%2Fstoryline%22:%7B%22title%22:%22Story%22%7D,%22%2Fwebservice%2Fescenic%2Fcontent%2Fstate%2Fpublished%22:%7B%22title%22:%22Published%22%7D,%22org_unit:8acc2ff9-63f5-11f0-ae19-959fd20885e0%22:%7B%22title%22:%22Miami%22%7D,%22%2Fwebservice%2Fescenic%2Fsection%2F4990%22:%7B%22pathInfo%22:%22miamiherald%22,%22title%22:%22Living%22%7D,%22creationdate%22:%22In%20the%20last%20year%22%7D,%22createdAt%22:%222026-03-19T17:30:46.839Z%22,%22dateRange%22:%7B%22creationdate%22:%7B%22start%22:%222025-03-19T04:00:00Z%22,%22end%22:%222027-03-20T04:00:00Z%22%7D%7D,%22daysBefore%22:%7B%22creationdate%22:%22365%22%7D,%22facetSummary%22:%22Document%20Type:%20Story,%20Time-span%20(creationdate):%20In%20the%20last%20year,%20States:%20Published,%20Sections:%20Living%22,%22priority%22:-1,%22panelName%22:%22Search%22,%22presentation%22:%22%22,%22sorting%22:%22%22,%22customFilters%22:%5B%5D,%22customFacetStrings%22:%7B%7D,%22state%22:%22%2Fwebservice%2Fescenic%2Fcontent%2Fstate%2Fpublished%22,%22sections%22:%22%2Fwebservice%2Fescenic%2Fsection%2F4990%22,%22orgUnit%22:%22org_unit:8acc2ff9-63f5-11f0-ae19-959fd20885e0%22%7D%7D | K77: kcm: https://cue.gcp.misitemgr.com/cue-web/#/main?uri=https:%2F%2Fcue.gcp.misitemgr.com%2Fwebservice%2Fescenic%2Fcontainer%2F6983b226-22fb-11f1-8dd4-85110eda7de5&mimetype=x-ece%2Fcontainer&extra=%7B%22package%22:%22ece-auto-gen-27c579eb-52b8-431e-a726-b53459a14b0e%22%7D&filter=%7B%22searchCriteria%22:%7B%22name%22:%22%22,%22searchTerm%22:%22%22,%22contentType%22:%22%2Fwebservice%2Fescenic%2Fpublication%2Fbnd%2Fmodel%2Fcontent-type%2Fstoryline%22,%22labels%22:%7B%22%2Fwebservice%2Fescenic%2Fpublication%2Fbnd%2Fmodel%2Fcontent-type%2Fstoryline%22:%7B%22title%22:%22Story%22%7D,%22%2Fwebservice%2Fescenic%2Fcontent%2Fstate%2Fpublished%22:%7B%22title%22:%22Published%22%7D,%22org_unit:8a8f26f5-63f5-11f0-ae19-959fd20885e0%22:%7B%22title%22:%22KansasCity%22%7D,%22%2Fwebservice%2Fescenic%2Fsection%2F2551%22:%7B%22pathInfo%22:%22kansascity%22,%22title%22:%22Living%22%7D,%22creationdate%22:%22In%20the%20last%20year%22%7D,%22createdAt%22:%222026-03-19T14:57:03.542Z%22,%22dateRange%22:%7B%22creationdate%22:%7B%22start%22:%222025-03-19T04:00:00Z%22,%22end%22:%222027-03-20T04:00:00Z%22%7D%7D,%22daysBefore%22:%7B%22creationdate%22:%22365%22%7D,%22facetSummary%22:%22Document%20Type:%20Story,%20Time-span%20(creationdate):%20In%20the%20last%20year,%20States:%20Published,%20Sections:%20Living%22,%22priority%22:-1,%22panelName%22:%22Search%22,%22presentation%22:%22%22,%22sorting%22:%22%22,%22customFilters%22:%5B%5D,%22customFacetStrings%22:%7B%7D,%22state%22:%22%2Fwebservice%2Fescenic%2Fcontent%2Fstate%2Fpublished%22,%22sections%22:%22%2Fwebservice%2Fescenic%2Fsection%2F2551%22,%22orgUnit%22:%22org_unit:8a8f26f5-63f5-11f0-ae19-959fd20885e0%22%7D%7D | L77: Everyday Living | M77: WW | N77: CUE | O77: API
A78: 46082 | B78: 46093 | C78: What is Hyaluronic Acid and how do you know if you need it (KW: Hyaluronic Acid) | D78: Article | E78: In Progress | F78: High | G78: Lauren S | I78: ww: https://www.womansworld.com/wp-admin/post.php?post=609847&action=edit | J78: mia: https://cue.gcp.misitemgr.com/cue-web/#/main?escenicid=315001814&extra=%7B%22package%22:%22ece-auto-gen-551a1000-b7f3-4795-8ae2-6bf84bb9551c%22%7D | K78: kcm: https://cue.gcp.misitemgr.com/cue-web/#/main?escenicid=315001825&extra=%7B%22package%22:%22ece-auto-gen-06a72eb1-d3fc-445a-b45f-916ecdf70f81%22%7D | L78: Everyday Living | M78: WW | N78: CUE | O78: API
A79: 46082 | B79: 46093 | C79: The Inflation Risk Most Retirees Are Ignoring (KW: Inflation) | D79: Article | E79: In Progress | F79: High | G79: Lauren S | I79: ftw: https://cue.gcp.misitemgr.com/cue-web/#/main?uri=https:%2F%2Fcue.gcp.misitemgr.com%2Fwebservice%2Fescenic%2Fcontainer%2F2491fe49-2233-11f1-879e-8784efaee08b&mimetype=x-ece%2Fcontainer&extra=%7B%22package%22:%22ece-auto-gen-4221d8df-78f4-41ee-a17f-f933d48da161%22%7D&filter=%7B%22searchCriteria%22:%7B%22name%22:%22%22,%22searchTerm%22:%22%22,%22contentType%22:%22%2Fwebservice%2Fescenic%2Fpublication%2Fbnd%2Fmodel%2Fcontent-type%2Fstoryline%22,%22labels%22:%7B%22%2Fwebservice%2Fescenic%2Fpublication%2Fbnd%2Fmodel%2Fcontent-type%2Fstoryline%22:%7B%22title%22:%22Story%22%7D,%22%2Fwebservice%2Fescenic%2Fcontent%2Fstate%2Fpublished%22:%7B%22title%22:%22Published%22%7D,%22org_unit:8a6a87f2-63f5-11f0-ae19-959fd20885e0%22:%7B%22title%22:%22FortWorth%22%7D,%22%2Fwebservice%2Fescenic%2Fsection%2F6008%22:%7B%22pathInfo%22:%22star-telegram:%20News%20%2F%22,%22title%22:%22Business%22%7D,%22creationdate%22:%22In%20the%20last%20year%22%7D,%22createdAt%22:%222026-03-18T15:43:16.520Z%22,%22dateRange%22:%7B%22creationdate%22:%7B%22start%22:%222025-03-18T04:00:00Z%22,%22end%22:%222027-03-19T04:00:00Z%22%7D%7D,%22daysBefore%22:%7B%22creationdate%22:%22365%22%7D,%22facetSummary%22:%22Document%20Type:%20Story,%20Time-span%20(creationdate):%20In%20the%20last%20year,%20States:%20Published,%20Sections:%20Business%22,%22priority%22:-1,%22panelName%22:%22Search%22,%22presentation%22:%22%22,%22sorting%22:%22%22,%22customFilters%22:%5B%5D,%22customFacetStrings%22:%7B%7D,%22state%22:%22%2Fwebservice%2Fescenic%2Fcontent%2Fstate%2Fpublished%22,%22sections%22:%22%2Fwebservice%2Fescenic%2Fsection%2F6008%22,%22orgUnit%22:%22org_unit:8a6a87f2-63f5-11f0-ae19-959fd20885e0%22%7D%7D | J79: mia: https://cue.gcp.misitemgr.com/cue-web/#/main?escenicid=315089613&extra=%7B%22package%22:%22ece-auto-gen-594ac4e4-dd15-433c-a894-1f8e347c1e16%22%7D&filter=%7B%22searchCriteria%22:%7B%22name%22:%22%22,%22searchTerm%22:%22%22,%22contentType%22:%22%2Fwebservice%2Fescenic%2Fpublication%2Fbnd%2Fmodel%2Fcontent-type%2Fstoryline%22,%22labels%22:%7B%22%2Fwebservice%2Fescenic%2Fpublication%2Fbnd%2Fmodel%2Fcontent-type%2Fstoryline%22:%7B%22title%22:%22Story%22%7D,%22%2Fwebservice%2Fescenic%2Fcontent%2Fstate%2Fpublished%22:%7B%22title%22:%22Published%22%7D,%22org_unit:8acc2ff9-63f5-11f0-ae19-959fd20885e0%22:%7B%22title%22:%22Miami%22%7D,%22%2Fwebservice%2Fescenic%2Fsection%2F5020%22:%7B%22pathInfo%22:%22miamiherald:%20News%20%2F%22,%22title%22:%22Business%22%7D,%22creationdate%22:%22In%20the%20last%20year%22%7D,%22createdAt%22:%222026-03-17T19:35:10.234Z%22,%22dateRange%22:%7B%22creationdate%22:%7B%22start%22:%222025-03-17T04:00:00Z%22,%22end%22:%222027-03-18T04:00:00Z%22%7D%7D,%22daysBefore%22:%7B%22creationdate%22:%22365%22%7D,%22facetSummary%22:%22Document%20Type:%20Story,%20Time-span%20(creationdate):%20In%20the%20last%20year,%20States:%20Published,%20Sections:%20Business%22,%22priority%22:-1,%22panelName%22:%22Search%22,%22presentation%22:%22%22,%22sorting%22:%22%22,%22customFilters%22:%5B%5D,%22customFacetStrings%22:%7B%7D,%22state%22:%22%2Fwebservice%2Fescenic%2Fcontent%2Fstate%2Fpublished%22,%22sections%22:%22%2Fwebservice%2Fescenic%2Fsection%2F5020%22,%22orgUnit%22:%22org_unit:8acc2ff9-63f5-11f0-ae19-959fd20885e0%22%7D%7D | K79: kcm: https://cue.gcp.misitemgr.com/cue-web/#/main?uri=https:%2F%2Fcue.gcp.misitemgr.com%2Fwebservice%2Fescenic%2Fcontainer%2F1ab34a58-2233-11f1-879e-8784efaee08b&mimetype=x-ece%2Fcontainer&extra=%7B%22package%22:%22ece-auto-gen-34a50693-f853-4eed-99ae-ed95eaf701e2%22%7D | N79: CUE
A80: 46082 | B80: 46093 | C80: Roth Conversion Strategy: A Step-by-Step Guide for Using Your Roth IRA (KW: Roth IRA) | D80: Article | E80: In Progress | F80: High | G80: Allison | I80: https://cue.gcp.misitemgr.com/cue-web/#/main?escenicid=315027602&extra=%7B%22package%22:%22ece-auto-gen-65eb76af-8211-425c-ab53-0e3aefe16fa0%22%7D&filter=%7B%22searchCriteria%22:%7B%22name%22:%22%22,%22searchTerm%22:%22Retirement%22,%22contentType%22:%22%2Fwebservice%2Fescenic%2Fpublication%2Fmcclatchy-newsroom%2Fmodel%2Fcontent-type%2Fstoryline%22,%22labels%22:%7B%22%2Fwebservice%2Fescenic%2Fpublication%2Fmcclatchy-newsroom%2Fmodel%2Fcontent-type%2Fstoryline%22:%7B%22title%22:%22Story%22%7D,%22%2Fwebservice%2Fescenic%2Fcontent%2Fstate%2Fpublished%22:%7B%22title%22:%22Published%22%7D,%22%2Fwebservice%2Fescenic%2Fperson%2F25705%22:%7B%22title%22:%22Lauren%20Jarvis-Gibson%22%7D,%22%2Fwebservice%2Fescenic%2Fperson%2F25701%22:%7B%22title%22:%22Lauren%20Schuster%22%7D,%22%2Fwebservice%2Fescenic%2Fperson%2F23145%22:%7B%22title%22:%22Allison%20Palmer%22%7D,%22creationdate%22:%22In%20the%20last%20year%22%7D,%22createdAt%22:%222026-03-12T16:02:09.610Z%22,%22dateRange%22:%7B%22creationdate%22:%7B%22start%22:%222025-03-09T05:00:00Z%22,%22end%22:%222027-03-10T05:00:00Z%22%7D%7D,%22daysBefore%22:%7B%22creationdate%22:%22365%22%7D,%22facetSummary%22:%22Document%20Type:%20Story,%20Time-span%20(creationdate):%20In%20the%20last%20year,%20States:%20Published%22,%22priority%22:-1,%22panelName%22:%22Search%22,%22presentation%22:%22%22,%22sorting%22:%22%22,%22customFilters%22:%5B%5D,%22customFacetStrings%22:%7B%22author%22:%22%2Fwebservice%2Fescenic%2Fperson%2F25705%20%2Fwebservice%2Fescenic%2Fperson%2F25701%20%2Fwebservice%2Fescenic%2Fperson%2F23145%22%7D,%22state%22:%22%2Fwebservice%2Fescenic%2Fcontent%2Fstate%2Fpublished%22%7D,%22savedSearch%22:%22Content%20Team-apalmer@mcclatchy.com%22%7D | J80: https://cue.gcp.misitemgr.com/cue-web/#/main?uri=https:%2F%2Fcue.gcp.misitemgr.com%2Fwebservice%2Fescenic%2Fcontainer%2F42aae595-1e27-11f1-a8a1-03a0e69fd3db&mimetype=x-ece%2Fcontainer&extra=%7B%22package%22:%22ece-auto-gen-eb2ea377-e7f2-4994-9fe5-ea5d26440e4b%22%7D | K80: https://cue.gcp.misitemgr.com/cue-web/#/main?escenicid=315027409&extra=%7B%22package%22:%22ece-auto-gen-71b14f48-12fb-496d-8df3-b2981c64ed7a%22%7D&filter=%7B%22searchCriteria%22:%7B%22name%22:%22%22,%22searchTerm%22:%22Retirement%22,%22contentType%22:%22%2Fwebservice%2Fescenic%2Fpublication%2Fmcclatchy-newsroom%2Fmodel%2Fcontent-type%2Fstoryline%22,%22labels%22:%7B%22%2Fwebservice%2Fescenic%2Fpublication%2Fmcclatchy-newsroom%2Fmodel%2Fcontent-type%2Fstoryline%22:%7B%22title%22:%22Story%22%7D,%22%2Fwebservice%2Fescenic%2Fcontent%2Fstate%2Fpublished%22:%7B%22title%22:%22Published%22%7D,%22%2Fwebservice%2Fescenic%2Fperson%2F25705%22:%7B%22title%22:%22Lauren%20Jarvis-Gibson%22%7D,%22%2Fwebservice%2Fescenic%2Fperson%2F25701%22:%7B%22title%22:%22Lauren%20Schuster%22%7D,%22%2Fwebservice%2Fescenic%2Fperson%2F23145%22:%7B%22title%22:%22Allison%20Palmer%22%7D,%22creationdate%22:%22In%20the%20last%20year%22%7D,%22createdAt%22:%222026-03-12T15:52:23.853Z%22,%22dateRange%22:%7B%22creationdate%22:%7B%22start%22:%222025-03-09T05:00:00Z%22,%22end%22:%222027-03-10T05:00:00Z%22%7D%7D,%22daysBefore%22:%7B%22creationdate%22:%22365%22%7D,%22facetSummary%22:%22Document%20Type:%20Story,%20Time-span%20(creationdate):%20In%20the%20last%20year,%20States:%20Published%22,%22priority%22:-1,%22panelName%22:%22Search%22,%22presentation%22:%22%22,%22sorting%22:%22%22,%22customFilters%22:%5B%5D,%22customFacetStrings%22:%7B%22author%22:%22%2Fwebservice%2Fescenic%2Fperson%2F25705%20%2Fwebservice%2Fescenic%2Fperson%2F25701%20%2Fwebservice%2Fescenic%2Fperson%2F23145%22%7D,%22state%22:%22%2Fwebservice%2Fescenic%2Fcontent%2Fstate%2Fpublished%22%7D,%22savedSearch%22:%22Content%20Team-apalmer@mcclatchy.com%22%7D | N80: CUE
A81: 46082 | B81: 46093 | C81: What Happens to Your Portfolio If Markets Drop 30% at Retirement? (KW: Retirement) | D81: Article | E81: In Progress | F81: High | G81: Lauran J-G | I81: ftw: https://cue.gcp.misitemgr.com/cue-web/#/main?escenicid=315105704&extra=%7B%22package%22:%22ece-auto-gen-d9dd7ef8-0e98-4665-a766-2debd5d450b8%22%7D&filter=%7B%22searchCriteria%22:%7B%22name%22:%22%22,%22searchTerm%22:%22money%22,%22contentType%22:%22%2Fwebservice%2Fescenic%2Fpublication%2Fbnd%2Fmodel%2Fcontent-type%2Fstoryline%22,%22labels%22:%7B%22%2Fwebservice%2Fescenic%2Fpublication%2Fbnd%2Fmodel%2Fcontent-type%2Fstoryline%22:%7B%22title%22:%22Story%22%7D,%22%2Fwebservice%2Fescenic%2Fcontent%2Fstate%2Fpublished%22:%7B%22title%22:%22Published%22%7D,%22org_unit:8a8f26f5-63f5-11f0-ae19-959fd20885e0%22:%7B%22title%22:%22KansasCity%22%7D,%22creationdate%22:%22In%20the%20last%20year%22%7D,%22createdAt%22:%222026-03-19T18:28:51.218Z%22,%22dateRange%22:%7B%22creationdate%22:%7B%22start%22:%222025-03-18T06:00:00Z%22,%22end%22:%222027-03-19T06:00:00Z%22%7D%7D,%22daysBefore%22:%7B%22creationdate%22:%22365%22%7D,%22facetSummary%22:%22Document%20Type:%20Story,%20Time-span%20(creationdate):%20In%20the%20last%20year,%20States:%20Published%22,%22priority%22:-1,%22panelName%22:%22Search%22,%22presentation%22:%22%22,%22sorting%22:%22%22,%22customFilters%22:%5B%5D,%22customFacetStrings%22:%7B%7D,%22state%22:%22%2Fwebservice%2Fescenic%2Fcontent%2Fstate%2Fpublished%22,%22orgUnit%22:%22org_unit:8a8f26f5-63f5-11f0-ae19-959fd20885e0%22%7D%7D | J81: mia: https://cue.gcp.misitemgr.com/cue-web/#/main?escenicid=315105499&extra=%7B%22package%22:%22ece-auto-gen-d27169f9-b625-4512-a6dc-f0dff6d7ecf9%22%7D&filter=%7B%22searchCriteria%22:%7B%22name%22:%22%22,%22searchTerm%22:%22%22,%22contentType%22:%22%2Fwebservice%2Fescenic%2Fpublication%2Fbnd%2Fmodel%2Fcontent-type%2Fstoryline%22,%22labels%22:%7B%22%2Fwebservice%2Fescenic%2Fpublication%2Fbnd%2Fmodel%2Fcontent-type%2Fstoryline%22:%7B%22title%22:%22Story%22%7D,%22org_unit:8a8f26f5-63f5-11f0-ae19-959fd20885e0%22:%7B%22title%22:%22KansasCity%22%7D,%22%2Fwebservice%2Fescenic%2Fcontent%2Fstate%2Fpublished%22:%7B%22title%22:%22Published%22%7D,%22creationdate%22:%22In%20the%20last%20year%22%7D,%22createdAt%22:%222026-03-18T21:05:24.109Z%22,%22dateRange%22:%7B%22creationdate%22:%7B%22start%22:%222025-03-18T06:00:00Z%22,%22end%22:%222027-03-19T06:00:00Z%22%7D%7D,%22daysBefore%22:%7B%22creationdate%22:%22365%22%7D,%22facetSummary%22:%22Document%20Type:%20Story,%20Time-span%20(creationdate):%20In%20the%20last%20year,%20States:%20Published%22,%22priority%22:-1,%22panelName%22:%22Search%22,%22presentation%22:%22%22,%22sorting%22:%22%22,%22customFilters%22:%5B%5D,%22customFacetStrings%22:%7B%7D,%22state%22:%22%2Fwebservice%2Fescenic%2Fcontent%2Fstate%2Fpublished%22,%22orgUnit%22:%22org_unit:8a8f26f5-63f5-11f0-ae19-959fd20885e0%22%7D%7D | K81: kcm: https://cue.gcp.misitemgr.com/cue-web/#/main?escenicid=315105712&extra=%7B%22package%22:%22ece-auto-gen-f381c1b2-4b1c-4417-8edc-8630aa15dc6a%22%7D&filter=%7B%22searchCriteria%22:%7B%22name%22:%22%22,%22searchTerm%22:%22%22,%22labels%22:%7B%22org_unit:8a8f26f5-63f5-11f0-ae19-959fd20885e0%22:%7B%22title%22:%22KansasCity%22%7D,%22creationdate%22:%22In%20the%20last%20year%22%7D,%22createdAt%22:%222026-03-19T18:59:05.942Z%22,%22dateRange%22:%7B%22creationdate%22:%7B%22start%22:%222025-03-19T06:00:00Z%22,%22end%22:%222027-03-20T06:00:00Z%22%7D%7D,%22daysBefore%22:%7B%22creationdate%22:%22365%22%7D,%22facetSummary%22:%22Time-span%20(creationdate):%20In%20the%20last%20year%22,%22priority%22:-1,%22panelName%22:%22Search%22,%22presentation%22:%22%22,%22sorting%22:%22%22,%22customFilters%22:%5B%5D,%22customFacetStrings%22:%7B%7D,%22orgUnit%22:%22org_unit:8a8f26f5-63f5-11f0-ae19-959fd20885e0%22%7D%7D | L81: Everyday Living | N81: CUE
N82: CUE
N83: CUE
N84: CUE
A85: 46082 | C85: Which neighborhoods in Fort Worth are right for you? | D85: Article | E85: Approved | G85: Lauran J-G | I85: https://docs.google.com/document/d/1ZrDvrhffIQBoVSKLjRLV78kShNPRTpwv2PFZg5gzO9U/edit?tab=t.0 | L85: Everyday Living | N85: CUE | O85: Homebuyers Guides
A86: 46082 | C86: Texas Homebuyers Assistance Programs: Loans, Grants & Down Payment Help | D86: Article | E86: Approved | G86: Lauran J-G | L86: Everyday Living | N86: CUE | O86: Homebuyers Guides
A87: 46082 | C87: Which Fort Worth neighborhoods have the best schools? | D87: Article | E87: Approved | G87: Lauran J-G | L87: Everyday Living | N87: CUE | O87: Homebuyers Guides
A88: 46082 | C88: The Home Inspection Process in Fort Worth: What Buyers Need to Know | D88: Article | E88: Approved | G88: Lauran J-G | L88: Everyday Living | N88: CUE | O88: Homebuyers Guides
A89: 46082 | C89: Fort Worth Real Estate Market Trends: What Buyers Should Watch | D89: Article | E89: Approved | G89: Lauran J-G | L89: Everyday Living | N89: CUE | O89: Homebuyers Guides
A90: 46082 | C90: Understanding Property Taxes in Tarrant County | D90: Article | E90: Approved | G90: Lauran J-G | L90: Everyday Living | N90: CUE | O90: Homebuyers Guides
N91: CUE
N92: CUE
N93: CUE
N94: CUE
N95: CUE
N96: CUE
N97: CUE
N98: CUE
N99: CUE
N100: CUE
N101: CUE
N102: CUE
... N178: CUE

Sheet Creature Features
A1: Creature Feature Pitches

Sheet APPLE REWRITE CALENDAR
A1: Date | B1: Day of Week | C1: Week | D1: Article 1 - Title | E1: Article 1 - Source | F1: Article 1 - Original Views | G1: Article 1 - Published | H1: Article 1 - Rewrite Score | I1: Article 2 - Title | J1: Article 2 - Source | K1: Article 2 - Original Views | L1: Article 2 - Published | M1: Article 2 - Rewrite Score | N1: Status | O1: Writer Assigned | P1: Draft Due Date | Q1: Notes
A2: 46062 | B2: Monday | C2: Week 1 | D2: ‘Big boy’ — weighing 525 pounds — found hiding under California home after wildfire | E2: Miami Herald | F2: 1052633 | G2: 45687 | H2: 15 | I2: OnlyFans' Annie Knight ‘Bleeding’ After Sleeping With 583 Men in 6 Hours | J2: Us Weekly | K2: 1045121 | L2: 45798 | M2: 15 | N2: Not Started
A3: 46063 | B3: Tuesday | C3: Week 1 | D3: Bill Belichick's Girlfriend Jordon Hudson Stuns in Vintage-Style Bikini | E3: Us Weekly | F3: 863790 | G3: 45829 | H3: 14 | I3: OnlyFans’ Lily Phillips Reveals How Much Money She Makes From Sex Challenges | J3: Us Weekly | K3: 855886 | L3: 45671 | M3: 14 | N3: Not Started
A4: 46064 | B4: Wednesday | C4: Week 1 | D4: Kylie Jenner and J. Lo’s Celebrity Hair Stylist Jesus Guerrero Dies | E4: Us Weekly | F4: 516992 | G4: 45711 | H4: 14 | I4: Virginia Giuffre, a crusader for Jeffrey Epstein victims, dies at 41 | J4: Miami Herald | K4: 1144867 | L4: 45772 | M4: 13 | N4: Not Started
A5: 46065 | B5: Thursday | C5: Week 1 | D5: The Rise Of The Competitive-Sex Trend. They’re sleeping with hundreds of men a day — and earning millions. Creators and experts explore the implications of turning sex stunts into a revenue stream | E5: Us Weekly | F5: 698185 | G5: 45848 | H5: 13 | I5: The Real Reason 24-Year-Old Jordon Hudson Is Dating Bill Belichick: Source | J5: Us Weekly | K5: 641930 | L5: 45779 | M5: 13 | N5: Not Started
A6: 46066 | B6: Friday | C6: Week 1 | D6: Hundreds at Alligator Alcatraz have no criminal charges or convictions, records show | E6: Miami Herald | F6: 627809 | G6: 45851 | H6: 13 | I6: Jennifer Love Hewitt Shows Off her Curves in Gorgeous Little Black Dress on Red Carpet | J6: Us Weekly | K6: 610246 | L6: 45853 | M6: 13 | N6: Not Started
A7: 46069 | B7: Monday | C7: Week 2 | D7: Cop beats Homeland Security agent in ‘parking lot rage’ at CA Costco, lawyer says | E7: Miami Herald | F7: 599532 | G7: 45846 | H7: 13 | I7: Homeowner guns down 19-year-old installing fiber optic cable, Texas cops say | J7: Miami Herald | K7: 598807 | L7: 45834 | M7: 13 | N7: Not Started
A8: 46070 | B8: Tuesday | C8: Week 2 | D8: Elizabeth Hurley Debuts New Relationship With Billy Ray Cyrus | E8: Us Weekly | F8: 578036 | G8: 45767 | H8: 13 | I8: Tom Hardy Details Health Woes: ‘Not Going to Get Better’ | J8: Us Weekly | K8: 568517 | L8: 45787 | M8: 13 | N8: Not Started
A9: 46071 | B9: Wednesday | C9: Week 2 | D9: Bill Belichick's Girlfriend Jordon Hudson Pays Off Millions Owed on Homes | E9: Us Weekly | F9: 507638 | G9: 45800 | H9: 13 | I9: ‘Like a machine gun’: 4 dead, 20 injured in mass shooting in Beaufort County, SC | J9: Hilton Head Island Packet | K9: 1133340 | L9: 45942 | M9: 12 | N9: Not Started
A10: 46072 | B10: Thursday | C10: Week 2 | D10: Every Naked Dress That Heated Up the 2025 Grammys Red Carpet | E10: Us Weekly | F10: 1094133 | G10: 45690 | H10: 12 | I10: Jordon Hudson References Taylor Swift While Questioning Bill Belichick Breakup | J10: Us Weekly | K10: 841667 | L10: 45852 | M10: 12 | N10: Not Started
A11: 46073 | B11: Friday | C11: Week 2 | D11: Why Colin Farrell Is Putting Son, 21, in Long-Term Care Facility | E11: Us Weekly | F11: 817624 | G11: 45766 | H11: 12 | I11: ‘Rare’ silver creature spotted in snowy Colorado wilderness. See the striking photo | J11: Miami Herald | K11: 798058 | L11: 45708 | M11: 12 | N11: Not Started
A12: 46076 | B12: Monday | C12: Week 3 | D12: Tiffany Trump posted a photo of her baby — and a lot of people had the same comment | E12: Miami Herald | F12: 793805 | G12: 45845 | H12: 12 | I12: Johnny Bananas Shares Golf Cart Video Days After Fatal John Elway Crash | J12: Us Weekly | K12: 760898 | L12: 45780 | M12: 12 | N12: Not Started
A13: 46077 | B13: Tuesday | C13: Week 3 | D13: Jennifer Lopez Shares Photos of Severe Facial Injury From AMAs Rehearsals | E13: Us Weekly | F13: 712290 | G13: 45790 | H13: 12 | I13: Danica Patrick Shows Off Her Toned Physique in Skin-Baring Burning Man Outfits | J13: Us Weekly | K13: 667086 | L13: 45901 | M13: 12 | N13: Not Started
... A26: 46094 | B26: Friday | C26: Week 5 | D26: Kansas dad sensed daughter was killed in Israeli embassy staff shooting: ‘Panic’ | E26: The Kansas City Star | F26: 672946 | G26: 45799 | H26: 11 | I26: Noah Cyrus Performs Nearly Naked in Nipple-Baring Dress at Stagecoach | J26: Us Weekly | K26: 670353 | L26: 45775 | M26: 11 | N26: Not Started
A28: https://docs.google.com/document/d/1wKQSyJd8nd4FaSN7rHetVRFhBENed3IOB1c06FVyn_w/edit?tab=t.0

Sheet Status & Priority Legend
A1: Status Legend | C1: Priority Legend | E1: Owner Legend | H1: Vertical Legend
A3: Idea | C3: High | E3: Allison | H3: Everyday Living
A4: Pitched | C4: Medium | E4: Taylor (FL) | H4: Mindbody
A5: Approved | C5: Low | E5: Hanna | H5: Experiences
A6: Assigned | E6: Ryan | H6: Discover
A7: In Progress | E7: Lauren S
A8: Review | E8: Lauran J-G
A9: Scheduled | E9: Sara
A10: Published
A11: On Hold

Sheet Sheet8
A1: L&E Content Metrics - Week of 12/28
B2: Pageviews | H2: Day of Month | I2: Days in Month
A3: Metric | B3: Actual | C3: WoW | D3: Pacing as of Jan 4 | E3: Jan Forecast | F3: Pacing as of Jan 4 | G3: Jan Forecast | H3: 4 | I3: 31
A4: Us Weekly | B4: =IF(H4>=1000000, ROUND(H4/1000000,1)&"M", IF(H4>=1000, ROUND(H4/1000,0)&"k", H4)) -> #REF! | C4: =IFERROR(__xludf.DUMMYFUNCTION("IMPORTRANGE(""https://docs.google.com/spreadsheets/d/1WPTu1QswsqdJqLW9voi9-RjbUd5PdxtEvHiMQlq1yuc/edit?gid=504933931#gid=504933931"", ""Wow Deck Updates!E4:E7"")"),0.007253418071011186) -> 0.0072534181 | D4: =IFERROR(__xludf.DUMMYFUNCTION("IMPORTRANGE(""https://docs.google.com/spreadsheets/d/1WPTu1QswsqdJqLW9voi9-RjbUd5PdxtEvHiMQlq1yuc/edit?gid=504933931#gid=504933931"", ""Wow Deck Updates!F4:G7"")"),"5.5M") -> 5.5M | E4: =IFERROR(__xludf.DUMMYFUNCTION("""COMPUTED_VALUE"""),"42.4M") -> 42.4M | H4: =USW!B19 -> #REF!
A5: Woman's World | B5: =IF(H5>=1000000, ROUND(H5/1000000,1)&"M", IF(H5>=1000, ROUND(H5/1000,0)&"k", H5)) -> #REF! | C5: =IFERROR(__xludf.DUMMYFUNCTION("""COMPUTED_VALUE"""),0.10228493581578743) -> 0.10228494 | D5: =IFERROR(__xludf.DUMMYFUNCTION("""COMPUTED_VALUE"""),"353k") -> 353k | E5: =IFERROR(__xludf.DUMMYFUNCTION("""COMPUTED_VALUE"""),"2.7M") -> 2.7M | H5: =WW!B19 -> #REF!
A6: SOD | B6: =IF(H6>=1000000, ROUND(H6/1000000,1)&"M", IF(H6>=1000, ROUND(H6/1000,0)&"k", H6)) -> #REF! | C6: =IFERROR(__xludf.DUMMYFUNCTION("""COMPUTED_VALUE"""),-0.16114886438719728) -> -0.16114886 | D6: =IFERROR(__xludf.DUMMYFUNCTION("""COMPUTED_VALUE"""),"203k") -> 203k | E6: =IFERROR(__xludf.DUMMYFUNCTION("""COMPUTED_VALUE"""),"1.6M") -> 1.6M | H6: =SOD!B18 -> #REF!
A7: Total | B7: =IF(H7>=1000000, ROUND(H7/1000000,1)&"M", IF(H7>=1000, ROUND(H7/1000,0)&"k", H7)) -> #REF! | C7: =IFERROR(__xludf.DUMMYFUNCTION("""COMPUTED_VALUE"""),0.005998829166773771) -> 0.0059988292 | D7: =IFERROR(__xludf.DUMMYFUNCTION("""COMPUTED_VALUE"""),"6M") -> 6M | E7: =IFERROR(__xludf.DUMMYFUNCTION("""COMPUTED_VALUE"""),"46.7M") -> 46.7M | H7: =sum(B34,B44,B54) -> #REF!
B8: Sessions
A9: Metric | B9: Actual | C9: WoW | D9: Pacing as of Jan 4 | E9: Jan Forecast | F9: Pacing as of Jan 4 | G9: Jan Forecast
A10: Us Weekly | B10: =IF(H10>=1000000, ROUND(H10/1000000,1)&"M", IF(H10>=1000, ROUND(H10/1000,0)&"k", H10)) -> #REF! | C10: =IFERROR(__xludf.DUMMYFUNCTION("IMPORTRANGE(""https://docs.google.com/spreadsheets/d/1WPTu1QswsqdJqLW9voi9-RjbUd5PdxtEvHiMQlq1yuc/edit?gid=504933931#gid=504933931"", ""Wow Deck Updates!E10:E13"")"),0.019570818116781415) -> 0.019570818 | D10: =IFERROR(__xludf.DUMMYFUNCTION("IMPORTRANGE(""https://docs.google.com/spreadsheets/d/1WPTu1QswsqdJqLW9voi9-RjbUd5PdxtEvHiMQlq1yuc/edit?gid=504933931#gid=504933931"", ""Wow Deck Updates!F10:G13"")"),"3.6M") -> 3.6M | E10: =IFERROR(__xludf.DUMMYFUNCTION("""COMPUTED_VALUE"""),"28.1M") -> 28.1M | H10: =USW!B37 -> #REF!
A11: Woman's World | B11: =IF(H11>=1000000, ROUND(H11/1000000,1)&"M", IF(H11>=1000, ROUND(H11/1000,0)&"k", H11)) -> #REF! | C11: =IFERROR(__xludf.DUMMYFUNCTION("""COMPUTED_VALUE"""),0.0820099401031088) -> 0.08200994 | D11: =IFERROR(__xludf.DUMMYFUNCTION("""COMPUTED_VALUE"""),"278k") -> 278k | E11: =IFERROR(__xludf.DUMMYFUNCTION("""COMPUTED_VALUE"""),"2.2M") -> 2.2M | H11: =WW!B34 -> #REF!
A12: SOD | B12: =IF(H12>=1000000, ROUND(H12/1000000,1)&"M", IF(H12>=1000, ROUND(H12/1000,0)&"k", H12)) -> #REF! | C12: =IFERROR(__xludf.DUMMYFUNCTION("""COMPUTED_VALUE"""),-0.20348928981875078) -> -0.20348929 | D12: =IFERROR(__xludf.DUMMYFUNCTION("""COMPUTED_VALUE"""),"133k") -> 133k | E12: =IFERROR(__xludf.DUMMYFUNCTION("""COMPUTED_VALUE"""),"1M") -> 1M | H12: =SOD!B33 -> #REF!
A13: Total | B13: =IF(H13>=1000000, ROUND(H13/1000000,1)&"M", IF(H13>=1000, ROUND(H13/1000,0)&"k", H13)) -> #REF! | C13: =IFERROR(__xludf.DUMMYFUNCTION("""COMPUTED_VALUE"""),0.015018412617322173) -> 0.015018413 | D13: =IFERROR(__xludf.DUMMYFUNCTION("""COMPUTED_VALUE"""),"4M") -> 4M | E13: =IFERROR(__xludf.DUMMYFUNCTION("""COMPUTED_VALUE"""),"31.2M") -> 31.2M | H13: =sum(B31,B41,B51) -> #REF!
H14: Day of Month | I14: Days in Month
A15: L&E Content Metrics - Week of 2/8 | H15: 15 | I15: 28
B16: Pageviews
A17: Metric | B17: Actual | C17: WoW | D17: Pacing as of Feb 15 | E17: Feb Forecast | F17: Pacing as of Feb 15 | G17: Feb Forecast
A18: Us Weekly | B18: =IF(H34>=1000000, ROUND(H34/1000000,1)&"M", IF(H34>=1000, ROUND(H34/1000,0)&"k", H34)) -> #REF! | C18: =(H34-G34)/G34 -> #REF! | D18: =IF(F18>=1000000, ROUND(F18/1000000,1)&"M", IF(F18>=1000, ROUND(F18/1000,0)&"k", F18)) -> 22.1M | E18: =IF(G18>=1000000, ROUND(G18/1000000,1)&"M", IF(G18>=1000, ROUND(G18/1000,0)&"k", G18)) -> 41.3M | F18: 22112954 | G18: =F18/$H$15*$I$15 -> 41277514
A19: Woman's World | B19: =IF(H44>=1000000, ROUND(H44/1000000,1)&"M", IF(H44>=1000, ROUND(H44/1000,0)&"k", H44)) -> #REF! | C19: =(H44-G44)/G44 -> #REF! | D19: =IF(F19>=1000000, ROUND(F19/1000000,1)&"M", IF(F19>=1000, ROUND(F19/1000,0)&"k", F19)) -> 1.2M | E19: =IF(G19>=1000000, ROUND(G19/1000000,1)&"M", IF(G19>=1000, ROUND(G19/1000,0)&"k", G19)) -> 2.3M | F19: 1234643 | G19: =F19/$H$15*$I$15 -> 2304666.9
A20: SOD | B20: =IF(H54>=1000000, ROUND(H54/1000000,1)&"M", IF(H54>=1000, ROUND(H54/1000,0)&"k", H54)) -> #REF! | C20: =(H54-G54)/G54 -> #REF! | D20: =IF(F20>=1000000, ROUND(F20/1000000,1)&"M", IF(F20>=1000, ROUND(F20/1000,0)&"k", F20)) -> 1.2M | E20: =IF(G20>=1000000, ROUND(G20/1000000,1)&"M", IF(G20>=1000, ROUND(G20/1000,0)&"k", G20)) -> 2.3M | F20: 1215963 | G20: =F20/$H$15*$I$15 -> 2269797.6
A21: Total | B21: =IF(H21>=1000000, ROUND(H21/1000000,1)&"M", IF(H21>=1000, ROUND(H21/1000,0)&"k", H21)) -> #REF! | C21: =(I21-H21)/H21 -> #REF! | D21: =IF(F21>=1000000, ROUND(F21/1000000,1)&"M", IF(F21>=1000, ROUND(F21/1000,0)&"k", F21)) -> 24.6M | E21: =IF(G21>=1000000, ROUND(G21/1000000,1)&"M", IF(G21>=1000, ROUND(G21/1000,0)&"k", G21)) -> 45.9M | F21: =sum(F18:F20) -> 24563560 | G21: =sum(G18:G20) -> 45851979 | H21: =sum(H34,H44,H54) -> #REF! | I21: =sum(G34,G44,G54) -> #REF! | J21: =sum(F34,F44,F54) -> #REF! | K21: =sum(E34,E44,E54) -> #REF! | L21: =sum(C34,C44,C54) -> #REF!
B22: Sessions
A23: Metric | B23: Actual | C23: WoW | D23: Pacing as of Feb 15 | E23: Feb Forecast | F23: Pacing as of Feb 15 | G23: Feb Forecast
A24: Us Weekly | B24: =IF(H31>=1000000, ROUND(H31/1000000,1)&"M", IF(H31>=1000, ROUND(H31/1000,0)&"k", H31)) -> #REF! | C24: =(H31-G31)/G31 -> #REF! | D24: =IF(F24>=1000000, ROUND(F24/1000000,1)&"M", IF(F24>=1000, ROUND(F24/1000,0)&"k", F24)) -> 13.7M | E24: =IF(G24>=1000000, ROUND(G24/1000000,1)&"M", IF(G24>=1000, ROUND(G24/1000,0)&"k", G24)) -> 25.5M | F24: 13658881 | G24: =F24/$H$15*$I$15 -> 25496578
A25: Woman's World | B25: =IF(H41>=1000000, ROUND(H41/1000000,1)&"M", IF(H41>=1000, ROUND(H41/1000,0)&"k", H41)) -> #REF! | C25: =(H41-G41)/G41 -> #REF! | D25: =IF(F25>=1000000, ROUND(F25/1000000,1)&"M", IF(F25>=1000, ROUND(F25/1000,0)&"k", F25)) -> 977k | E25: =IF(G25>=1000000, ROUND(G25/1000000,1)&"M", IF(G25>=1000, ROUND(G25/1000,0)&"k", G25)) -> 1.8M | F25: 976769 | G25: =F25/$H$15*$I$15 -> 1823302.1
A26: SOD | B26: =IF(H51>=1000000, ROUND(H51/1000000,1)&"M", IF(H51>=1000, ROUND(H51/1000,0)&"k", H51)) -> #REF! | C26: =(H51-G51)/G51 -> #REF! | D26: =IF(F26>=1000000, ROUND(F26/1000000,1)&"M", IF(F26>=1000, ROUND(F26/1000,0)&"k", F26)) -> 823k | E26: =IF(G26>=1000000, ROUND(G26/1000000,1)&"M", IF(G26>=1000, ROUND(G26/1000,0)&"k", G26)) -> 1.5M | F26: 822694 | G26: =F26/$H$15*$I$15 -> 1535695.5
A27: Total | B27: =IF(H27>=1000000, ROUND(H27/1000000,1)&"M", IF(H27>=1000, ROUND(H27/1000,0)&"k", H27)) -> #REF! | C27: =(I27-H27)/H27 -> #REF! | D27: =IF(F27>=1000000, ROUND(F27/1000000,1)&"M", IF(F27>=1000, ROUND(F27/1000,0)&"k", F27)) -> 15.5M | E27: =IF(G27>=1000000, ROUND(G27/1000000,1)&"M", IF(G27>=1000, ROUND(G27/1000,0)&"k", G27)) -> 28.9M | F27: =sum(F24:F26) -> 15458344 | G27: =sum(G24:G26) -> 28855575 | H27: =sum(H31,H41,H51) -> #REF! | I27: =sum(G31,G41,G51) -> #REF! | J27: =sum(F31,F41,F51) -> #REF! | K27: =sum(E31,E41,E51) -> #REF! | L27: =sum(C31,C41,C51) -> #REF!
A29: Us Weekly | B29: 46019 | C29: 46026 | D29: 46033 | E29: 46040 | F29: 46047 | G29: 46054 | H29: 46061 | I29: % Wow
A30: Total Published Articles | B30: =USW!B7 -> #REF! | C30: =USW!C7 -> #REF! | D30: =USW!D7 -> #REF! | E30: =USW!E7 -> #REF! | F30: =USW!F7 -> #REF! | G30: =USW!G7 -> #REF! | H30: =USW!H7 -> #REF! | I30: =(H30-G30)/G30 -> #REF!
A31: Sessions | B31: =USW!B37 -> #REF! | C31: =USW!C37 -> #REF! | D31: =USW!D37 -> #REF! | E31: =USW!E37 -> #REF! | F31: =USW!F37 -> #REF! | G31: =USW!G37 -> #REF! | H31: =USW!H37 -> #REF! | I31: =(H31-G31)/G31 -> #REF!
A32: Sessions from Social | B32: =USW!B28 -> #REF! | C32: =USW!C28 -> #REF! | D32: =USW!D28 -> #REF! | E32: =USW!E28 -> #REF! | F32: =USW!F28 -> #REF! | G32: =USW!G28 -> #REF! | H32: =USW!H28 -> #REF! | I32: =(H32-G32)/G32 -> #REF!
A33: % sessions from Social | B33: =B32/B31 -> #REF! | C33: =C32/C31 -> #REF! | D33: =D32/D31 -> #REF! | E33: =E32/E31 -> #REF! | F33: =F32/F31 -> #REF! | G33: =G32/G31 -> #REF! | H33: =H32/H31 -> #REF! | I33: =(H33-G33)/G33 -> #REF!
A34: Pageviews | B34: =USW!B19 -> #REF! | C34: =USW!C19 -> #REF! | D34: =USW!D19 -> #REF! | E34: =USW!E19 -> #REF! | F34: =USW!F19 -> #REF! | G34: =USW!G19 -> #REF! | H34: =USW!H19 -> #REF! | I34: =(H34-G34)/G34 -> #REF!
A35: Pageviews from Social | B35: =USW!B29 -> #REF! | C35: =USW!C29 -> #REF! | D35: =USW!D29 -> #REF! | E35: =USW!E29 -> #REF! | F35: =USW!F29 -> #REF! | G35: =USW!G29 -> #REF! | H35: =USW!H29 -> #REF! | I35: =(H35-G35)/G35 -> #REF!
A36: % PV from Social | B36: =B35/B34 -> #REF! | C36: =C35/C34 -> #REF! | D36: =D35/D34 -> #REF! | E36: =E35/E34 -> #REF! | F36: =F35/F34 -> #REF! | G36: =G35/G34 -> #REF! | H36: =H35/H34 -> #REF! | I36: =(H36-G36)/G36 -> #REF!
A37: Avg PV/Story | B37: =B34/B30 -> #REF! | C37: =C34/C30 -> #REF! | D37: =D34/D30 -> #REF! | E37: =E34/E30 -> #REF! | F37: =F34/F30 -> #REF! | G37: =G34/G30 -> #REF! | H37: =H34/H30 -> #REF! | I37: =(H37-G37)/G37 -> #REF!
A39: Woman's World | B39: 46019 | C39: 46026 | D39: 46033 | E39: 46040 | F39: 46047 | G39: 46054 | H39: 46061 | I39: % Wow
A40: Total Published Articles | B40: =WW!B7 -> #REF! | C40: =WW!C7 -> #REF! | D40: =WW!D7 -> #REF! | E40: =WW!E7 -> #REF! | F40: =WW!F7 -> #REF! | G40: =WW!G7 -> #REF! | H40: =WW!H7 -> #REF! | I40: =(H40-G40)/G40 -> #REF!
A41: Sessions | B41: =WW!B34 -> #REF! | C41: =WW!C34 -> #REF! | D41: =WW!D34 -> #REF! | E41: =WW!E34 -> #REF! | F41: =WW!F34 -> #REF! | G41: =WW!G34 -> #REF! | H41: =WW!H34 -> #REF! | I41: =(H41-G41)/G41 -> #REF!
A42: Sessions from Social | B42: =WW!B25 -> #REF! | C42: =WW!C25 -> #REF! | D42: =WW!D25 -> #REF! | E42: =WW!E25 -> #REF! | F42: =WW!F25 -> #REF! | G42: =WW!G25 -> #REF! | H42: =WW!H25 -> #REF! | I42: =(H42-G42)/G42 -> #REF!
A43: % sessions from Social | B43: =B42/B41 -> #REF! | C43: =C42/C41 -> #REF! | D43: =D42/D41 -> #REF! | E43: =E42/E41 -> #REF! | F43: =F42/F41 -> #REF! | G43: =G42/G41 -> #REF! | H43: =H42/H41 -> #REF! | I43: =(H43-G43)/G43 -> #REF!
A44: Pageviews | B44: =WW!B19 -> #REF! | C44: =WW!C19 -> #REF! | D44: =WW!D19 -> #REF! | E44: =WW!E19 -> #REF! | F44: =WW!F19 -> #REF! | G44: =WW!G19 -> #REF! | H44: =WW!H19 -> #REF! | I44: =(H44-G44)/G44 -> #REF!
A45: Pageviews from Social | B45: =WW!B26 -> #REF! | C45: =WW!C26 -> #REF! | D45: =WW!D26 -> #REF! | E45: =WW!E26 -> #REF! | F45: =WW!F26 -> #REF! | G45: =WW!G26 -> #REF! | H45: =WW!H26 -> #REF! | I45: =(H45-G45)/G45 -> #REF!
A46: % PV from Social | B46: =B45/B44 -> #REF! | C46: =C45/C44 -> #REF! | D46: =D45/D44 -> #REF! | E46: =E45/E44 -> #REF! | F46: =F45/F44 -> #REF! | G46: =G45/G44 -> #REF! | H46: =H45/H44 -> #REF! | I46: =(H46-G46)/G46 -> #REF!
A47: Avg PV/Story | B47: =B44/B40 -> #REF! | C47: =C44/C40 -> #REF! | D47: =D44/D40 -> #REF! | E47: =E44/E40 -> #REF! | F47: =F44/F40 -> #REF! | G47: =G44/G40 -> #REF! | H47: =H44/H40 -> #REF! | I47: =(H47-G47)/G47 -> #REF!
A49: SOD | B49: 46019 | C49: 46026 | D49: 46033 | E49: 46040 | F49: 46047 | G49: 46054 | H49: 46061 | I49: % Wow
A50: Total Published Articles | B50: =SOD!B7 -> #REF! | C50: =SOD!C7 -> #REF! | D50: =SOD!D7 -> #REF! | E50: =SOD!E7 -> #REF! | F50: =SOD!F7 -> #REF! | G50: =SOD!G7 -> #REF! | H50: =SOD!H7 -> #REF! | I50: =(H50-G50)/G50 -> #REF!
A51: Sessions | B51: =SOD!B33 -> #REF! | C51: =SOD!C33 -> #REF! | D51: =SOD!D33 -> #REF! | E51: =SOD!E33 -> #REF! | F51: =SOD!F33 -> #REF! | G51: =SOD!G33 -> #REF! | H51: =SOD!H33 -> #REF! | I51: =(H51-G51)/G51 -> #REF!
A52: Sessions from Social | B52: =SOD!B24 -> #REF! | C52: =SOD!C24 -> #REF! | D52: =SOD!D24 -> #REF! | E52: =SOD!E24 -> #REF! | F52: =SOD!F24 -> #REF! | G52: =SOD!G24 -> #REF! | H52: =SOD!H24 -> #REF! | I52: =(H52-G52)/G52 -> #REF!
A53: % sessions from Social | B53: =B52/B51 -> #REF! | C53: =C52/C51 -> #REF! | D53: =D52/D51 -> #REF! | E53: =E52/E51 -> #REF! | F53: =F52/F51 -> #REF! | G53: =G52/G51 -> #REF! | H53: =H52/H51 -> #REF! | I53: =(H53-G53)/G53 -> #REF!
A54: Pageviews | B54: =SOD!B18 -> #REF! | C54: =SOD!C18 -> #REF! | D54: =SOD!D18 -> #REF! | E54: =SOD!E18 -> #REF! | F54: =SOD!F18 -> #REF! | G54: =SOD!G18 -> #REF! | H54: =SOD!H18 -> #REF! | I54: =(H54-G54)/G54 -> #REF!
A55: Pageviews from Social | B55: =SOD!B25 -> #REF! | C55: =SOD!C25 -> #REF! | D55: =SOD!D25 -> #REF! | E55: =SOD!E25 -> #REF! | F55: =SOD!F25 -> #REF! | G55: =SOD!G25 -> #REF! | H55: =SOD!H25 -> #REF! | I55: =(H55-G55)/G55 -> #REF!
A56: % PV from Social | B56: =B55/B54 -> #REF! | C56: =C55/C54 -> #REF! | D56: =D55/D54 -> #REF! | E56: =E55/E54 -> #REF! | F56: =F55/F54 -> #REF! | G56: =G55/G54 -> #REF! | H56: =H55/H54 -> #REF! | I56: =(H56-G56)/G56 -> #REF!
A57: Avg PV/Story | B57: =B54/B50 -> #REF! | C57: =C54/C50 -> #REF! | D57: =D54/D50 -> #REF! | E57: =E54/E50 -> #REF! | F57: =F54/F50 -> #REF! | G57: =G54/G50 -> #REF! | H57: =H54/H50 -> #REF! | I57: =(H57-G57)/G57 -> #REF!
A59: ModMoms | B59: 46019 | C59: 46026 | D59: 46033 | E59: 46040 | F59: 46047 | G59: 46054 | H59: 46061 | I59: % Wow
A60: Total Published Articles | B60: =ModMoms!B7 -> #REF! | C60: =ModMoms!C7 -> #REF! | D60: =ModMoms!D7 -> #REF! | E60: =ModMoms!E7 -> #REF! | F60: =ModMoms!F7 -> #REF! | G60: =ModMoms!G7 -> #REF! | H60: =ModMoms!H7 -> #REF! | I60: =(H60-G60)/G60 -> #REF!
A61: Sessions | B61: =ModMoms!B33 -> #REF! | C61: =ModMoms!C33 -> #REF! | D61: =ModMoms!D33 -> #REF! | E61: =ModMoms!E33 -> #REF! | F61: =ModMoms!F33 -> #REF! | G61: =ModMoms!G33 -> #REF! | H61: =ModMoms!H33 -> #REF! | I61: =(H61-G61)/G61 -> #REF!
A62: Sessions from Social | B62: =ModMoms!B24 -> #REF! | C62: =ModMoms!C24 -> #REF! | D62: =ModMoms!D24 -> #REF! | E62: =ModMoms!E24 -> #REF! | F62: =ModMoms!F24 -> #REF! | G62: =ModMoms!G24 -> #REF! | H62: =ModMoms!H24 -> #REF! | I62: =(H62-G62)/G62 -> #REF!
A63: % sessions from Social | B63: =B62/B61 -> #REF! | C63: =C62/C61 -> #REF! | D63: =D62/D61 -> #REF! | E63: =E62/E61 -> #REF! | F63: =F62/F61 -> #REF! | G63: =G62/G61 -> #REF! | H63: =H62/H61 -> #REF! | I63: =(H63-G63)/G63 -> #REF!
A64: Pageviews | B64: =ModMoms!B18 -> #REF! | C64: =ModMoms!C18 -> #REF! | D64: =ModMoms!D18 -> #REF! | E64: =ModMoms!E18 -> #REF! | F64: =ModMoms!F18 -> #REF! | G64: =ModMoms!G18 -> #REF! | H64: =ModMoms!H18 -> #REF! | I64: =(H64-G64)/G64 -> #REF!
A65: Pageviews from Social | B65: =ModMoms!B25 -> #REF! | C65: =ModMoms!C25 -> #REF! | D65: =ModMoms!D25 -> #REF! | E65: =ModMoms!E25 -> #REF! | F65: =ModMoms!F25 -> #REF! | G65: =ModMoms!G25 -> #REF! | H65: =ModMoms!H25 -> #REF! | I65: =(H65-G65)/G65 -> #REF!
A66: % PV from Social | B66: =B65/B64 -> #REF! | C66: =C65/C64 -> #REF! | D66: =D65/D64 -> #REF! | E66: =E65/E64 -> #REF! | F66: =F65/F64 -> #REF! | G66: =G65/G64 -> #REF! | H66: =H65/H64 -> #REF! | I66: =(H66-G66)/G66 -> #REF!
A67: Avg PV/Story | B67: =B64/B60 -> #REF! | C67: =C64/C60 -> #REF! | D67: =D64/D60 -> #REF! | E67: =E64/E60 -> #REF! | F67: =F64/F60 -> #REF! | G67: =G64/G60 -> #REF! | H67: =H64/H60 -> #REF! | I67: =(H67-G67)/G67 -> #REF!
A69: LS | B69: 46019 | C69: 46026 | D69: 46033 | E69: 46040 | F69: 46047 | G69: 46054 | H69: 46061 | I69: % Wow
A70: Total Published Articles | B70: =LS!B7 -> #REF! | C70: =LS!C7 -> #REF! | D70: =LS!D7 -> #REF! | E70: =LS!E7 -> #REF! | F70: =LS!F7 -> #REF! | G70: =LS!G7 -> #REF! | H70: =LS!H7 -> #REF! | I70: =(H70-G70)/G70 -> #REF!
A71: Sessions | B71: =LS!B33 -> #REF! | C71: =LS!C33 -> #REF! | D71: =LS!D33 -> #REF! | E71: =LS!E33 -> #REF! | F71: =LS!F33 -> #REF! | G71: =LS!G33 -> #REF! | H71: =LS!H33 -> #REF! | I71: =(H71-G71)/G71 -> #REF!
A72: Sessions from Social | B72: =LS!B24 -> #REF! | C72: =LS!C24 -> #REF! | D72: =LS!D24 -> #REF! | E72: =LS!E24 -> #REF! | F72: =LS!F24 -> #REF! | G72: =LS!G24 -> #REF! | H72: =LS!H24 -> #REF! | I72: =(H72-G72)/G72 -> #REF!
A73: % sessions from Social | B73: =B72/B71 -> #REF! | C73: =C72/C71 -> #REF! | D73: =D72/D71 -> #REF! | E73: =E72/E71 -> #REF! | F73: =F72/F71 -> #REF! | G73: =G72/G71 -> #REF! | H73: =H72/H71 -> #REF! | I73: =(H73-G73)/G73 -> #REF!
A74: Pageviews | B74: =LS!B18 -> #REF! | C74: =LS!C18 -> #REF! | D74: =LS!D18 -> #REF! | E74: =LS!E18 -> #REF! | F74: =LS!F18 -> #REF! | G74: =LS!G18 -> #REF! | H74: =LS!H18 -> #REF! | I74: =(H74-G74)/G74 -> #REF!
A75: Pageviews from Social | B75: =LS!B25 -> #REF! | C75: =LS!C25 -> #REF! | D75: =LS!D25 -> #REF! | E75: =LS!E25 -> #REF! | F75: =LS!F25 -> #REF! | G75: =LS!G25 -> #REF! | H75: =LS!H25 -> #REF! | I75: =(H75-G75)/G75 -> #REF!
A76: % PV from Social | B76: =B75/B74 -> #REF! | C76: =C75/C74 -> #REF! | D76: =D75/D74 -> #REF! | E76: =E75/E74 -> #REF! | F76: =F75/F74 -> #REF! | G76: =G75/G74 -> #REF! | H76: =H75/H74 -> #REF! | I76: =(H76-G76)/G76 -> #REF!
A77: Avg PV/Story | B77: =B74/B70 -> #REF! | C77: =C74/C70 -> #REF! | D77: =D74/D70 -> #REF! | E77: =E74/E70 -> #REF! | F77: =F74/F70 -> #REF! | G77: =G74/G70 -> #REF! | H77: =H74/H70 -> #REF! | I77: =(H77-G77)/G77 -> #REF!

Sheet Sheet12
A1: Creature Features -- Miami internal syndication
A2: Kansas City -- Sports internal syndication

Sheet Sheet9
A1: The Commons
A2: Week # | B2: 8 | C2: 9 | D2: 10 | E2: 11 | F2: 12 | G2: 13 | H2: 14 | I2: 15 | J2: 16 | K2: 17 | L2: 18 | M2: 19 | N2: 20 | O2: 21 | P2: 22 | Q2: 23 | R2: 24 | S2: 25 | T2: 26 | U2: 27 | V2: 28 | W2: 29 | X2: 30 | Y2: 31 | Z2: 32 | AA2: 33 | AB2: 34 | AC2: 35 | AD2: 36 | AE2: 37 | AF2: 38 | AG2: 39 | AH2: 40 | AI2: 41 | AJ2: 42 | AK2: 43 | AL2: 44 | AM2: 45 | AN2: 46 | AO2: 47 | AP2: 48 | AQ2: 49 | AR2: 50 | AS2: 51 | AT2: 52 | AU2: 53
A3: Date of week start (Sunday) | B3: 46068 | C3: 46075 | D3: 46082 | E3: 46089 | F3: 46096 | G3: 46103 | H3: 46110 | I3: 46117 | J3: 46124 | K3: 46131 | L3: 46138 | M3: 46145 | N3: 46152 | O3: 46159 | P3: 46166 | Q3: 46173 | R3: 46180 | S3: 46187 | T3: 46194 | U3: 46201 | V3: 46208 | W3: 46215 | X3: 46222 | Y3: 46229 | Z3: 46236 | AA3: 46243 | AB3: 46250 | AC3: 46257 | AD3: 46264 | AE3: 46271 | AF3: 46278 | AG3: 46285 | AH3: 46292 | AI3: 46299 | AJ3: 46306 | AK3: 46313 | AL3: 46320 | AM3: 46327 | AN3: 46334 | AO3: 46341 | AP3: 46348 | AQ3: 46355 | AR3: 46362 | AS3: 46369 | AT3: 46376 | AU3: 46383
A4: Notes/ ACTION ITEMS
A6: PRODUCTION
A7: Total Articles
A8: - Articles
A9: - Galleries
A10: - Video Pages
A13: Posts per Day
A14: Sessions per Post - Using Univ
A15: Sessions per Day - Using Univ
A17: On Site Page Views - GA4
A18: Views
A19: Views per Post
... A72: Avg engagement time/session (seconds)

Sheet Sheet16
